Workbook

Sheet Summary
A1: Virginia Soda Tax Revenue Estimate | G1: Illustrative Summary Report
A2: Proposed 5.0% Statewide Soda Tax Beginning January 2025
A3: Prepared by: Wataru Hoeltermann | G3: Scenario date: January 1, 2025
A4: 1. Bottom-Line Estimates
A5: Measure | B5: Estimate | D5: Interpretation
A6: Estimated 2025 soda tax revenue | B6: ='Revenue and Consumption'!N10 -> 83996983 | D6: Projected 2025 full-year revenue from a 5% Virginia soda tax, after accounting for the estimated demand response.
A8: No-tax baseline soda consumption | B8: =INT('Revenue and Consumption'!F10) -> 2328279060 | D8: 2024 scaled soda units sold, used as the baseline for 2025 tax scenario
A9: Estimated soda consumption after tax response | B9: =INT('Revenue and Consumption'!K10) -> 2229519348 | D9: Estimated units sold after applying demand response to the baseline
A10: Estimated reduction in consumption | B10: =B8-B9 -> 98759712 | D10: Estimated decline in annual soda units sold relative to the no-tax baseline.
A12: 2. Price Elasticity of Soda Demand by Income Tier | D12: 3. Key Findings
A13: A constant elasticity log-log specification was used: | D13: Finding 1 | F13: Under stated assumptions, the proposed 5% Virginia soda tax is estimated to generate approximately $84.0 million in 2025 revenue.
A14: ln(soda units sold) = α + β ln(soda price per unit)
A15: Where the coefficient β is interpreted as the price elasticity of demand.
A16: Income Tier | B16: Elasticity | D16: Finding 2 | F16: Estimated 2025 soda consumption falls by about 98.8 million units, or roughly by 4.24%, relative to the no-tax baseline.
A17: High ( 100k and above ) | B17: =Elasticity!G7 -> -0.71035913
A18: Medium ( 40k to 100k ) | B18: =Elasticity!G8 -> -0.92885328
A19: Low ( less than 40k ) | B19: =Elasticity!G9 -> -1.9421318 | D19: Finding 3 | F19: Medium-income ZIP stores drive the largest share of revenue and unit reduction because they account for most Virginia soda sales in the sample
A20: Full-sample elasticity estimates were negative across all income tiers, with Low-income ZIP/ZCTA stores showing the strongest price response. In the state-level diagnostic results, High-income stores in Virginia and West Virginia showed positive elasticities of 0.51 and 0.69, respectively. Because positive elasticities are inconsistent with the expected downward-sloping demand relationship and appeared only in narrower state-tier cuts, these results were treated as anomalies and flagged for caution rather than used in the main revenue estimate.
D22: Finding 4 | F22: Estimated price elasticities are negative across income tiers, supporting the use of separate High, Medium, and Low income-tier demand responses.
D26: 4. Key Assumptions
D27: Assumption | F27: Description
D28: 1) Full tax pass-through | F28: Assumes 100% of the tax is reflected in consumer soda prices, increasing consumer soda prices by 5%.
D30: 2) Representative scaling | F30: The 33 Virginia sample stores are treated as representative of 1,000 statewide stores.
D32: 3) Income-tier price elasticities | F32: High, Medium, and Low ZIP/ZCTA price elasticities are applied separately, then summed for the statewide estimate
D35: 4) Price-driven demand response | F35: Revenue is calculated from soda sales after the estimated unit reduction as an expected response to a price increase.
D38: 5) Unit of Analysis | F38: The dataset’s "soda_units_sold" field is treated as the analysis unit provided in the assignment, not as fluid ounces, servings, or containers of a known size. Therefore, the consumption estimate is reported as a change in dataset units sold, not as a fluid-ounce health or volume estimate.
A42: 5. Method in Brief
A43: Step | B43: Description
A44: 1. Complete data inputs | B44: Pulled 2024 ACS 5-year median household income data from the Census API using table "B19013" at ZIP-level. Combined 2022–2024 income data to calculate three-year average income and classify each ZIP/ZCTA into the appropriate income tier.
A45: 2. Build analytical dataset | B45: Used Power Query to reshape the supplied wide monthly sales sheets into a store-month fact table, then linked each record to store, date, state, ZIP/ZCTA income, and income-tier fields for pivoting and slicing.
A46: 3. Explore patterns and anomalies | B46: Reviewed sales, soda units, soda prices, geography, income tiers, and time patterns using PivotTables and charts. I expected higher prices to reduce quantity demanded, but also checked for unstable estimates caused by small store counts or state-tier anomalies.
A47: 4. Estimate demand response | B47: Estimated full-sample soda price elasticity by income tier using a log-log demand specification relating soda units sold to soda price per unit. These elasticity estimates were used as the behavioral response inputs for the tax scenario.
A48: 5. Estimate Virginia tax impact | B48: Used 2024 Virginia soda units and sales as the no-tax baseline, scaled the 33 Virginia sample stores to the assignment assumption of 1,000 stores, applied the proposed 5.0% tax under full pass-through, and calculated post-response tax revenue and the change in soda consumption.

Sheet Time and Place
Q4: Graphs are illustrated from sample set given.
Q5: Takeaways:
Q6: Price per soda is mostly stable, with notable tax-period change to NC due to a large 5% soda tax.
Q9: MD and DC both have a much less demonstrated change, albeit a lower soda tax, they end around the same price per unit as non-taxed states such as VA and WV.
Q22: Takeaways:
Q23: Soda units sold show clear seasonality, with a rise in sales during summer and dip during winter.
Q26: Each state follows a very similar timing, with Georgia consuming approximately 40k more than other states during summertime.
Q29: North Carolina's tax effect is very apparent, with a visible dip in consumption after the tax policy on July, 2023.

Sheet Elasticity and Sales
A4: state | B4: VA
A5: year | B5: 2024
A7: Row Labels | B7: Sum of soda_sales | C7: Sum of soda_sales2
A8: High | B8: 17472271 | C8: 0.30179804
A9: Med | B9: 38908750 | C9: 0.67206976
A10: Low | B10: 1512895.2 | C10: 0.026132197
A11: Grand Total | B11: 57893916 | C11: 1
A15: Income Tier | B15: Elasticity
A16: High | B16: -0.71
A17: Medium | B17: -0.93
A18: Low | B18: -1.94
A35: Low-income ZIP/ZCTA stores show the strongest estimated price response, while High and Medium tiers are less responsive.
A61: Stores in Low-income neighborhoods has the strongest estimated price response, while in High- and Medium-income neighborhoods are less responsive.

Sheet Revenue Estimates & Sensitivity

Sheet Conclusion
A3: 6. Interpretations and Limitations
A4: These estimates should be interpreted as an illustrative fiscal scenario, not as a full causal evaluation of soda tax policy. Under the stated assumptions, the proposed 5% Virginia soda tax is projected to raise revenue while reducing estimated soda units sold. The taxable base remains large enough to generate positive revenue after behavioral adjustment, and the income-tier results suggests that price responsiveness differs across store-area income groups. Actual distributional effects would depend on who bears the tax burden and how the revenue is used thereafter.
A5: Estimate results could differ under alternative scaling methods, different pass-through rates, or store-weighting methods. ZIP/ZCTA-level income tiers represent store information and may not necessarily be capturing household-level tax burden in that area, as people may shop in different zip codes than their home. Elasticity estimates are also based on observed price and quantity patterns, not accounting for random price variation, so it may not reflect product mix, seasonality, store differences, or other omitted factors. This model also does not account for substitution, cross-border shopping, health outcomes, or long-run behaviors.
A7: 7. Further Analysis
A8: Further Analysis | B8: Purpose
A9: Model specification tests | B9: Estimate alternative models with store fixed effects, month/year controls, and income-tier interactions to test whether elasticity estimates are stable.
A10: Geographic detail | B10: Map ZIP/ZCTA-level patterns and test whether results vary by border areas, urban/rural location, or nearby taxed jurisdictions.
A11: Product and unit definition | B11: Clarify if the unit of analysis represents bottles, cases, ounces, or another measurement. We can test whether excise (volume-based) tax estimates differ from price-based.
A12: Substitution and behavior | B12: Examine substitution with other beverages, cross-state shopping, seasonality impacts, long-run behavioral adjustments, and store-level heterogeneity.
A13: Full fiscal impact model | B13: Extend the scenario to include administrative costs, compliance costs, revenue usage, household tax burden, and broader distributional effects.

Sheet Compact tables
A1: Main VA Estimate: 100% Pass-Through Scenario
A2: state | B2: VA
A3: Income | B3: 2024
A5: Income Tier | B5: VA Sample Store Count | C5: Soda Price Per Unit | D5: 2024 Soda Units | E5: 2024 Soda Sales | F5: Scaled Units | G5: Scaled (33 to 1000 stores) 2024 Soda Sales | H5: Soda Price Per Unit | I5: Elasticity | J5: Tax Rate | K5: Est. % Change of Units (log-log proiection) | L5: Estimated Units After Demand Shift | M5: Estimated Unit Change | N5: Sales after Demand Shift | O5: Estimated Tax Revenue | P5: Notes
A6: High | B6: 11 | C6: 0.75451212 | D6: 23124174 | E6: 17472271 | F6: =1000/33*GETPIVOTDATA("[Measures].[Sum of soda_units_sold]",$A$6,"[DimZip].[zip_inc_tier]","[DimZip].[zip_inc_tier].&[High]") -> 7.0073255e+08 | G6: =1000/33*GETPIVOTDATA("[Measures].[Sum of soda_sales]",$A$6,"[DimZip].[zip_inc_tier]","[DimZip].[zip_inc_tier].&[High]") -> 5.2946275e+08 | I6: =Elasticity!G7 -> -0.71035913 | J6: 0.05 | K6: =(1+J6)^I6-1 -> -0.03406481 | L6: =F6*(1+K6) -> 6.7686222e+08 | M6: =L6-F6 -> -23870321 | N6: =G6/F6*L6 -> 5.114267e+08 | O6: =N6*0.05 -> 25571335 | P6: Using VA-only High income tier elasticity produced an elastic (0.51) estimate, but this was only flagged as anomalous and not used for estimations.
A7: Medium | B7: 21 | C7: 0.75284167 | D7: 51721008 | E7: 38908750 | F7: =1000/33*GETPIVOTDATA("[Measures].[Sum of soda_units_sold]",$A$6,"[DimZip].[zip_inc_tier]","[DimZip].[zip_inc_tier].&[Med]") -> 1.5673033e+09 | G7: =1000/33*GETPIVOTDATA("[Measures].[Sum of soda_sales]",$A$6,"[DimZip].[zip_inc_tier]","[DimZip].[zip_inc_tier].&[Med]") -> 1.179053e+09 | I7: =Elasticity!G8 -> -0.92885328 | J7: 0.05 | K7: =(1+J7)^I7-1 -> -0.044307341 | L7: =F7*(1+K7) -> 1.4978602e+09 | M7: =L7-F7 -> -69443041 | N7: =G7/F7*L7 -> 1.1268123e+09 | O7: =N7*0.05 -> 56340617
A8: Low | B8: 1 | C8: 0.761225 | D8: 1988027 | E8: 1512895.2 | F8: =1000/33*GETPIVOTDATA("[Measures].[Sum of soda_units_sold]",$A$6,"[DimZip].[zip_inc_tier]","[DimZip].[zip_inc_tier].&[Low]") -> 60243242 | G8: =1000/33*GETPIVOTDATA("[Measures].[Sum of soda_sales]",$A$6,"[DimZip].[zip_inc_tier]","[DimZip].[zip_inc_tier].&[Low]") -> 45845310 | I8: =Elasticity!G9 -> -1.9421318 | J8: 0.05 | K8: =(1+J8)^I8-1 -> -0.090405995 | L8: =F8*(1+K8) -> 54796892 | M8: =L8-F8 -> -5446350.3 | N8: =G8/F8*L8 -> 41700619 | O8: =N8*0.05 -> 2085031 | P8: Only one VA Low income store was observed, so the upscaled estimate should be treated with caution.
A9: Total | B9: 33 | C9: 0.75365253 | D9: 76833209 | E9: 57893916 | F9: =1000/33*GETPIVOTDATA("[Measures].[Sum of soda_units_sold]",$A$6) -> 2.3282791e+09 | G9: =1000/33*GETPIVOTDATA("[Measures].[Sum of soda_sales]",$A$6) -> 1.7543611e+09 | I9: Tier-summed | J9: 0.05 | K9: =(1+J9)^I9-1 -> #VALUE! | L9: =SUM(L6:L8) -> 2.2295193e+09 | M9: =SUM(M6:M8) -> -98759712 | N9: =SUM(N6:N8) -> 1.6799397e+09 | O9: =SUM(O6:O8) -> 83996983
A10: Notes: Estimated demand response is based on elasticity and the assumed price increase. Tier-level estimates should be treated with caution as sample sizes differ, with the total row being our preferred estimates for revenue and demand effects.
R13: Pass-through sensitivity summary
R14: Pass-through | S14: Consumer Price Increase | T14: Post-Tax Units | U14: Unit Change | V14: Est. Tax Revenue
R15: 1 | S15: 0.05 | T15: 2.2295193e+09 | U15: -98759712 | V15: 83996983
R16: 0.75 | S16: 0.0375 | T16: 2.2533471e+09 | U16: -74931930 | V16: 84894760
R17: 0.5 | S17: 0.025 | T17: 2.2777358e+09 | U17: -50543247 | V17: 85813675
R18: Notes: Consistent trend of lower pass-through produces higher estimated tax revenue, as the smaller consumer price increase leads to a smaller reduction in quantity demanded and thus a larger taxable sales base.
R19: Sensitivity results are illustrative and depend on the assumed pass-through rates.
X21: gt

Sheet Elasticity
A1: Full sample, Constant elasticity (log-log) model for main method.
A2: A constant elasticity log-log model was used because the policy change is percentage-based and the assignment asks for price elasticity by income tier. The log-log specification allows the price coefficient to be interpreted directly as elasticity. This is treated as a transparent workbook-based estimate, not a full causal demand model.
A3: I chose log-log because it aligns the estimation method with the policy scenario: a 5% ad valorem tax creates a percentage price change, and elasticity is a percentage quantity response. More complex models could be tested, but this specification is transparent and appropriate for a short Excel-based assignment.
B5: Income Tier | C5: Obs. count | D5: Store count | E5: Avg soda PPU | F5: Avg monthly units | G5: Elasticity | H5: R-squared | I5: Interpretation
A6: Full Sample | B6: All | C6: =COUNT((dataset[ln_soda_units])) -> 3600 | D6: {=ROWS(_xlfn.UNIQUE(_xlfn._xlws.FILTER(dataset[store_id],(dataset[soda_units_sold]>0)*(dataset[soda_ppu]>0))))} -> 100 | E6: =AVERAGEIFS(dataset[soda_ppu],dataset[soda_units_sold],">0",dataset[soda_ppu],">0") -> 0.72502311 | F6: =AVERAGEIFS(dataset[soda_units_sold],dataset[soda_units_sold],">0",dataset[soda_ppu],">0") -> 203580.39 | G6: =SLOPE(dataset[ln_soda_units],dataset[ln_soda_ppu]) -> -0.97684053 | H6: {=RSQ(_xlfn._xlws.FILTER(dataset[ln_soda_units],(dataset[soda_units_sold]>0)*(dataset[soda_ppu]>0)),_xlfn._xlws.FILTER(dataset[ln_soda_ppu],(dataset[soda_units_sold]>0)*(dataset[soda_ppu]>0)))} -> 0.066619345
B7: High | C7: {=COUNT(_xlfn._xlws.FILTER(dataset[ln_soda_units],dataset[zip_inc_tier]="High",""))} -> 828 | D7: {=ROWS(_xlfn.UNIQUE(_xlfn._xlws.FILTER(dataset[store_id],dataset[zip_inc_tier]="High")))} -> 23 | E7: =AVERAGEIFS(dataset[soda_ppu],dataset[zip_inc_tier],"High") -> 0.72701304 | F7: =AVERAGEIFS(dataset[soda_units_sold],dataset[zip_inc_tier],"High") -> 181586.48 | G7: {=SLOPE( _xlfn._xlws.FILTER(dataset[ln_soda_units],dataset[zip_inc_tier]="High",""), _xlfn._xlws.FILTER(dataset[ln_soda_ppu],dataset[zip_inc_tier]="High","") )} -> -0.71035913 | H7: {=RSQ(_xlfn._xlws.FILTER(dataset[ln_soda_units],dataset[zip_inc_tier]="High"),_xlfn._xlws.FILTER(dataset[ln_soda_ppu],dataset[zip_inc_tier]="High"))} -> 0.024805876 | I7: Assuming 100% pass through, a 1% increase in soda price is associated with an estimated 0.71% decrease in soda units sold.
B8: Medium | C8: {=COUNT(_xlfn._xlws.FILTER(dataset[ln_soda_units],dataset[zip_inc_tier]="Med",""))} -> 2268 | D8: {=ROWS(_xlfn.UNIQUE(_xlfn._xlws.FILTER(dataset[store_id],dataset[zip_inc_tier]="Med")))} -> 63 | E8: =AVERAGEIFS(dataset[soda_ppu],dataset[zip_inc_tier],"Med") -> 0.72360018 | F8: =AVERAGEIFS(dataset[soda_units_sold],dataset[zip_inc_tier],"Med") -> 212169.27 | G8: {=SLOPE( _xlfn._xlws.FILTER(dataset[ln_soda_units],dataset[zip_inc_tier]="Med",""), _xlfn._xlws.FILTER(dataset[ln_soda_ppu],dataset[zip_inc_tier]="Med","") )} -> -0.92885328 | H8: {=RSQ(_xlfn._xlws.FILTER(dataset[ln_soda_units],dataset[zip_inc_tier]="Med"),_xlfn._xlws.FILTER(dataset[ln_soda_ppu],dataset[zip_inc_tier]="Med"))} -> 0.08081638 | I8: Assuming 100% pass through, a 1% increase in soda price is associated with an estimated 0.93% decrease in soda units sold.
B9: Low | C9: {=COUNT(_xlfn._xlws.FILTER(dataset[ln_soda_units],dataset[zip_inc_tier]="Low",""))} -> 180 | D9: {=ROWS(_xlfn.UNIQUE(_xlfn._xlws.FILTER(dataset[store_id],dataset[zip_inc_tier]="Low")))} -> 5 | E9: =AVERAGEIFS(dataset[soda_ppu],dataset[zip_inc_tier],"Low") -> 0.73157556 | F9: =AVERAGEIFS(dataset[soda_units_sold],dataset[zip_inc_tier],"Low") -> 194329.01 | G9: {=SLOPE( _xlfn._xlws.FILTER(dataset[ln_soda_units],dataset[zip_inc_tier]="Low",""), _xlfn._xlws.FILTER(dataset[ln_soda_ppu],dataset[zip_inc_tier]="Low","") )} -> -1.9421318 | H9: {=RSQ(_xlfn._xlws.FILTER(dataset[ln_soda_units],dataset[zip_inc_tier]="Low"),_xlfn._xlws.FILTER(dataset[ln_soda_ppu],dataset[zip_inc_tier]="Low"))} -> 0.2421674 | I9: Assuming 100% pass through, a 1% increase in soda price is associated with an estimated 1.94% decrease in soda units sold.
A10: Subsamples:
A11: VA only | B11: All | C11: {=COUNT(_xlfn._xlws.FILTER(dataset[ln_soda_units],dataset[state]="VA",""))} -> 1188 | D11: {=ROWS(_xlfn.UNIQUE(_xlfn._xlws.FILTER(dataset[store_id],(dataset[state]="VA")*(dataset[soda_units_sold]>0)*(dataset[soda_ppu]>0))))} -> 33 | E11: =AVERAGEIFS(dataset[soda_ppu],dataset[state],"VA",dataset[soda_units_sold],">0",dataset[soda_ppu],">0") -> 0.72935589 | F11: =AVERAGEIFS(dataset[soda_units_sold],dataset[state],"VA",dataset[soda_units_sold],">0",dataset[soda_ppu],">0") -> 196974.36 | G11: {=SLOPE(_xlfn._xlws.FILTER(dataset[ln_soda_units],dataset[state]="VA",""),_xlfn._xlws.FILTER(dataset[ln_soda_ppu],dataset[state]="VA",""))} -> -0.34704711 | H11: {=RSQ(_xlfn._xlws.FILTER(dataset[ln_soda_units],(dataset[state]="VA")*(dataset[soda_units_sold]>0)*(dataset[soda_ppu]>0)),_xlfn._xlws.FILTER(dataset[ln_soda_ppu],(dataset[state]="VA")*(dataset[soda_units_sold]>0)*(dataset[soda_ppu]>0)))} -> 0.0046073872 | I11: Very little sensitivity check, but very low r-squared suggests that price alone explains little of the variation in Virginia's soda units with respect to price.
B12: High | C12: {=COUNT(_xlfn._xlws.FILTER(dataset[ln_soda_units],(dataset[zip_inc_tier]="High")*(dataset[state]="VA"),""))} -> 396 | D12: {=ROWS(_xlfn.UNIQUE(_xlfn._xlws.FILTER(dataset[store_id],(dataset[zip_inc_tier]="High")*(dataset[state]="VA"))))} -> 11 | E12: =AVERAGEIFS(dataset[soda_ppu],dataset[zip_inc_tier],"High",dataset[state],"VA") -> 0.73048005 | F12: =AVERAGEIFS(dataset[soda_units_sold],dataset[zip_inc_tier],"High",dataset[state],"VA") -> 177787.49 | G12: {=SLOPE( _xlfn._xlws.FILTER(dataset[ln_soda_units],(dataset[zip_inc_tier]="High")*(dataset[state]="VA"),""), _xlfn._xlws.FILTER(dataset[ln_soda_ppu],(dataset[zip_inc_tier]="High")*(dataset[state]="VA"),"") )} -> 0.5059806 | H12: {=RSQ(_xlfn._xlws.FILTER(dataset[ln_soda_units],(dataset[zip_inc_tier]="High")*(dataset[state]="VA")),_xlfn._xlws.FILTER(dataset[ln_soda_ppu],(dataset[zip_inc_tier]="High")*(dataset[state]="VA")))} -> 0.0094590573 | I12: The positive elasticity should be treated as a data anomaly and not interpreted that higher prices increase soda demand.
B13: Medium | C13: {=COUNT(_xlfn._xlws.FILTER(dataset[ln_soda_units],(dataset[zip_inc_tier]="Med")*(dataset[state]="VA"),""))} -> 756 | D13: {=ROWS(_xlfn.UNIQUE(_xlfn._xlws.FILTER(dataset[store_id],(dataset[zip_inc_tier]="Med")*(dataset[state]="VA"))))} -> 21 | E13: =AVERAGEIFS(dataset[soda_ppu],dataset[zip_inc_tier],"Med",dataset[state],"VA") -> 0.72851071 | F13: =AVERAGEIFS(dataset[soda_units_sold],dataset[zip_inc_tier],"Med",dataset[state],"VA") -> 208286.47 | G13: {=SLOPE( _xlfn._xlws.FILTER(dataset[ln_soda_units],(dataset[zip_inc_tier]="Med")*(dataset[state]="VA"),""), _xlfn._xlws.FILTER(dataset[ln_soda_ppu],(dataset[zip_inc_tier]="Med")*(dataset[state]="VA"),"") )} -> -0.78466403 | H13: {=RSQ(_xlfn._xlws.FILTER(dataset[ln_soda_units],(dataset[zip_inc_tier]="Med")*(dataset[state]="VA")),_xlfn._xlws.FILTER(dataset[ln_soda_ppu],(dataset[zip_inc_tier]="Med")*(dataset[state]="VA")))} -> 0.031851899 | I13: Assuming 100% pass through, a 1% increase in soda price is associated with an estimated 0.78% decrease in soda units sold.
B14: Low | C14: {=COUNT(_xlfn._xlws.FILTER(dataset[ln_soda_units],(dataset[zip_inc_tier]="Low")*(dataset[state]="VA"),""))} -> 36 | D14: {=ROWS(_xlfn.UNIQUE(_xlfn._xlws.FILTER(dataset[store_id],(dataset[zip_inc_tier]="Low")*(dataset[state]="VA"))))} -> 1 | E14: =AVERAGEIFS(dataset[soda_ppu],dataset[zip_inc_tier],"Low",dataset[state],"VA") -> 0.73473889 | F14: =AVERAGEIFS(dataset[soda_units_sold],dataset[zip_inc_tier],"Low",dataset[state],"VA") -> 170475.61 | G14: {=SLOPE( _xlfn._xlws.FILTER(dataset[ln_soda_units],(dataset[zip_inc_tier]="Low")*(dataset[state]="VA"),""), _xlfn._xlws.FILTER(dataset[ln_soda_ppu],(dataset[zip_inc_tier]="Low")*(dataset[state]="VA"),"") )} -> -1.0151468 | H14: {=RSQ(_xlfn._xlws.FILTER(dataset[ln_soda_units],(dataset[zip_inc_tier]="Low")*(dataset[state]="VA")),_xlfn._xlws.FILTER(dataset[ln_soda_ppu],(dataset[zip_inc_tier]="Low")*(dataset[state]="VA")))} -> 0.031076426 | I14: Assuming 100% pass through, a 1% increase in soda price is associated with an estimated 1.02% decrease in soda units sold.
A16: DC | B16: All | C16: {=COUNT(_xlfn._xlws.FILTER(dataset[ln_soda_units],dataset[state]="DC",""))} -> 72 | D16: {=ROWS(_xlfn.UNIQUE(_xlfn._xlws.FILTER(dataset[store_id],(dataset[state]="DC")*(dataset[soda_units_sold]>0)*(dataset[soda_ppu]>0))))} -> 2 | E16: =AVERAGEIFS(dataset[soda_ppu],dataset[state],"DC",dataset[soda_units_sold],">0",dataset[soda_ppu],">0") -> 0.72162917 | F16: =AVERAGEIFS(dataset[soda_units_sold],dataset[state],"DC",dataset[soda_units_sold],">0",dataset[soda_ppu],">0") -> 204413.64 | G16: {=SLOPE(_xlfn._xlws.FILTER(dataset[ln_soda_units],dataset[state]="DC",""),_xlfn._xlws.FILTER(dataset[ln_soda_ppu],dataset[state]="DC",""))} -> -0.4049745 | H16: {=RSQ(_xlfn._xlws.FILTER(dataset[ln_soda_units],(dataset[state]="DC")*(dataset[soda_units_sold]>0)*(dataset[soda_ppu]>0)),_xlfn._xlws.FILTER(dataset[ln_soda_ppu],(dataset[state]="DC")*(dataset[soda_units_sold]>0)*(dataset[soda_ppu]>0)))} -> 0.0058344604 | I16: Existing 2% tax every year
B17: High | C17: {=COUNT(_xlfn._xlws.FILTER(dataset[ln_soda_units],(dataset[zip_inc_tier]="High")*(dataset[state]="DC"),""))} -> 36 | D17: {=ROWS(_xlfn.UNIQUE(_xlfn._xlws.FILTER(dataset[store_id],(dataset[zip_inc_tier]="High")*(dataset[state]="DC"))))} -> 1 | E17: =AVERAGEIFS(dataset[soda_ppu],dataset[zip_inc_tier],"High",dataset[state],"DC") -> 0.72408889 | F17: =AVERAGEIFS(dataset[soda_units_sold],dataset[zip_inc_tier],"High",dataset[state],"DC") -> 204131.31 | G17: {=SLOPE( _xlfn._xlws.FILTER(dataset[ln_soda_units],(dataset[zip_inc_tier]="High")*(dataset[state]="DC"),""), _xlfn._xlws.FILTER(dataset[ln_soda_ppu],(dataset[zip_inc_tier]="High")*(dataset[state]="DC"),"") )} -> -0.22237294 | H17: {=RSQ(_xlfn._xlws.FILTER(dataset[ln_soda_units],(dataset[zip_inc_tier]="High")*(dataset[state]="DC")),_xlfn._xlws.FILTER(dataset[ln_soda_ppu],(dataset[zip_inc_tier]="High")*(dataset[state]="DC")))} -> 0.0015577963
B18: Medium | C18: {=COUNT(_xlfn._xlws.FILTER(dataset[ln_soda_units],(dataset[zip_inc_tier]="Med")*(dataset[state]="DC"),""))} -> 0 | I18: No sample observations in this income tier for this state.
B19: Low | C19: {=COUNT(_xlfn._xlws.FILTER(dataset[ln_soda_units],(dataset[zip_inc_tier]="Low")*(dataset[state]="DC"),""))} -> 0 | I19: No sample observations in this income tier for this state.
A20: MD | B20: All | C20: {=COUNT(_xlfn._xlws.FILTER(dataset[ln_soda_units],dataset[state]="MD",""))} -> 540 | D20: {=ROWS(_xlfn.UNIQUE(_xlfn._xlws.FILTER(dataset[store_id],(dataset[state]="MD")*(dataset[soda_units_sold]>0)*(dataset[soda_ppu]>0))))} -> 15 | E20: =AVERAGEIFS(dataset[soda_ppu],dataset[state],"MD",dataset[soda_units_sold],">0",dataset[soda_ppu],">0") -> 0.73191185 | F20: =AVERAGEIFS(dataset[soda_units_sold],dataset[state],"MD",dataset[soda_units_sold],">0",dataset[soda_ppu],">0") -> 192794.26 | G20: {=SLOPE(_xlfn._xlws.FILTER(dataset[ln_soda_units],dataset[state]="MD",""),_xlfn._xlws.FILTER(dataset[ln_soda_ppu],dataset[state]="MD",""))} -> -1.4393072 | H20: {=RSQ(_xlfn._xlws.FILTER(dataset[ln_soda_units],(dataset[state]="MD")*(dataset[soda_units_sold]>0)*(dataset[soda_ppu]>0)),_xlfn._xlws.FILTER(dataset[ln_soda_ppu],(dataset[state]="MD")*(dataset[soda_units_sold]>0)*(dataset[soda_ppu]>0)))} -> 0.085184499 | I20: 1% tax starting in January 2023 and increased it to 2% in January of 2024
B21: High | C21: {=COUNT(_xlfn._xlws.FILTER(dataset[ln_soda_units],(dataset[zip_inc_tier]="High")*(dataset[state]="MD"),""))} -> 252 | D21: {=ROWS(_xlfn.UNIQUE(_xlfn._xlws.FILTER(dataset[store_id],(dataset[zip_inc_tier]="High")*(dataset[state]="MD"))))} -> 7 | E21: =AVERAGEIFS(dataset[soda_ppu],dataset[zip_inc_tier],"High",dataset[state],"MD") -> 0.73967302 | F21: =AVERAGEIFS(dataset[soda_units_sold],dataset[zip_inc_tier],"High",dataset[state],"MD") -> 174528.21 | G21: {=SLOPE( _xlfn._xlws.FILTER(dataset[ln_soda_units],(dataset[zip_inc_tier]="High")*(dataset[state]="MD"),""), _xlfn._xlws.FILTER(dataset[ln_soda_ppu],(dataset[zip_inc_tier]="High")*(dataset[state]="MD"),"") )} -> -1.4528595 | H21: {=RSQ(_xlfn._xlws.FILTER(dataset[ln_soda_units],(dataset[zip_inc_tier]="High")*(dataset[state]="MD")),_xlfn._xlws.FILTER(dataset[ln_soda_ppu],(dataset[zip_inc_tier]="High")*(dataset[state]="MD")))} -> 0.079733121
B22: Medium | C22: {=COUNT(_xlfn._xlws.FILTER(dataset[ln_soda_units],(dataset[zip_inc_tier]="Med")*(dataset[state]="MD"),""))} -> 288 | D22: {=ROWS(_xlfn.UNIQUE(_xlfn._xlws.FILTER(dataset[store_id],(dataset[zip_inc_tier]="Med")*(dataset[state]="MD"))))} -> 8 | E22: =AVERAGEIFS(dataset[soda_ppu],dataset[zip_inc_tier],"Med",dataset[state],"MD") -> 0.72512083 | F22: =AVERAGEIFS(dataset[soda_units_sold],dataset[zip_inc_tier],"Med",dataset[state],"MD") -> 208777.05 | G22: {=SLOPE( _xlfn._xlws.FILTER(dataset[ln_soda_units],(dataset[zip_inc_tier]="Med")*(dataset[state]="MD"),""), _xlfn._xlws.FILTER(dataset[ln_soda_ppu],(dataset[zip_inc_tier]="Med")*(dataset[state]="MD"),"") )} -> -0.69447111 | H22: {=RSQ(_xlfn._xlws.FILTER(dataset[ln_soda_units],(dataset[zip_inc_tier]="Med")*(dataset[state]="MD")),_xlfn._xlws.FILTER(dataset[ln_soda_ppu],(dataset[zip_inc_tier]="Med")*(dataset[state]="MD")))} -> 0.03054278
B23: Low | C23: {=COUNT(_xlfn._xlws.FILTER(dataset[ln_soda_units],(dataset[zip_inc_tier]="Low")*(dataset[state]="MD"),""))} -> 0 | I23: No sample observations in this income tier for this state.
A24: NC | B24: All | C24: {=COUNT(_xlfn._xlws.FILTER(dataset[ln_soda_units],dataset[state]="NC",""))} -> 684 | D24: {=ROWS(_xlfn.UNIQUE(_xlfn._xlws.FILTER(dataset[store_id],(dataset[state]="NC")*(dataset[soda_units_sold]>0)*(dataset[soda_ppu]>0))))} -> 19 | E24: =AVERAGEIFS(dataset[soda_ppu],dataset[state],"NC",dataset[soda_units_sold],">0",dataset[soda_ppu],">0") -> 0.75083143 | F24: =AVERAGEIFS(dataset[soda_units_sold],dataset[state],"NC",dataset[soda_units_sold],">0",dataset[soda_ppu],">0") -> 203433.56 | G24: {=SLOPE(_xlfn._xlws.FILTER(dataset[ln_soda_units],dataset[state]="NC",""),_xlfn._xlws.FILTER(dataset[ln_soda_ppu],dataset[state]="NC",""))} -> -0.92154405 | H24: {=RSQ(_xlfn._xlws.FILTER(dataset[ln_soda_units],(dataset[state]="NC")*(dataset[soda_units_sold]>0)*(dataset[soda_ppu]>0)),_xlfn._xlws.FILTER(dataset[ln_soda_ppu],(dataset[state]="NC")*(dataset[soda_units_sold]>0)*(dataset[soda_ppu]>0)))} -> 0.075439791 | I24: 5% tax starting July 2023
B25: High | C25: {=COUNT(_xlfn._xlws.FILTER(dataset[ln_soda_units],(dataset[zip_inc_tier]="High")*(dataset[state]="NC"),""))} -> 0 | I25: No sample observations in this income tier for this state.
B26: Medium | C26: {=COUNT(_xlfn._xlws.FILTER(dataset[ln_soda_units],(dataset[zip_inc_tier]="Med")*(dataset[state]="NC"),""))} -> 504 | D26: {=ROWS(_xlfn.UNIQUE(_xlfn._xlws.FILTER(dataset[store_id],(dataset[zip_inc_tier]="Med")*(dataset[state]="NC"))))} -> 14 | E26: =AVERAGEIFS(dataset[soda_ppu],dataset[zip_inc_tier],"Med",dataset[state],"NC") -> 0.7544502 | F26: =AVERAGEIFS(dataset[soda_units_sold],dataset[zip_inc_tier],"Med",dataset[state],"NC") -> 203516.74 | G26: {=SLOPE( _xlfn._xlws.FILTER(dataset[ln_soda_units],(dataset[zip_inc_tier]="Med")*(dataset[state]="NC"),""), _xlfn._xlws.FILTER(dataset[ln_soda_ppu],(dataset[zip_inc_tier]="Med")*(dataset[state]="NC"),"") )} -> -0.81394402 | H26: {=RSQ(_xlfn._xlws.FILTER(dataset[ln_soda_units],(dataset[zip_inc_tier]="Med")*(dataset[state]="NC")),_xlfn._xlws.FILTER(dataset[ln_soda_ppu],(dataset[zip_inc_tier]="Med")*(dataset[state]="NC")))} -> 0.058742898
B27: Low | C27: {=COUNT(_xlfn._xlws.FILTER(dataset[ln_soda_units],(dataset[zip_inc_tier]="Low")*(dataset[state]="NC"),""))} -> 72 | D27: {=ROWS(_xlfn.UNIQUE(_xlfn._xlws.FILTER(dataset[store_id],(dataset[zip_inc_tier]="Low")*(dataset[state]="NC"))))} -> 2 | E27: =AVERAGEIFS(dataset[soda_ppu],dataset[zip_inc_tier],"Low",dataset[state],"NC") -> 0.75161389 | F27: =AVERAGEIFS(dataset[soda_units_sold],dataset[zip_inc_tier],"Low",dataset[state],"NC") -> 193479.46 | G27: {=SLOPE( _xlfn._xlws.FILTER(dataset[ln_soda_units],(dataset[zip_inc_tier]="Low")*(dataset[state]="NC"),""), _xlfn._xlws.FILTER(dataset[ln_soda_ppu],(dataset[zip_inc_tier]="Low")*(dataset[state]="NC"),"") )} -> -1.5619225 | H27: {=RSQ(_xlfn._xlws.FILTER(dataset[ln_soda_units],(dataset[zip_inc_tier]="Low")*(dataset[state]="NC")),_xlfn._xlws.FILTER(dataset[ln_soda_ppu],(dataset[zip_inc_tier]="Low")*(dataset[state]="NC")))} -> 0.22024515
A28: WV | B28: All | C28: {=COUNT(_xlfn._xlws.FILTER(dataset[ln_soda_units],dataset[state]="WV",""))} -> 468 | D28: {=ROWS(_xlfn.UNIQUE(_xlfn._xlws.FILTER(dataset[store_id],(dataset[state]="WV")*(dataset[soda_units_sold]>0)*(dataset[soda_ppu]>0))))} -> 13 | E28: =AVERAGEIFS(dataset[soda_ppu],dataset[state],"WV",dataset[soda_units_sold],">0",dataset[soda_ppu],">0") -> 0.73142308 | F28: =AVERAGEIFS(dataset[soda_units_sold],dataset[state],"WV",dataset[soda_units_sold],">0",dataset[soda_ppu],">0") -> 203054.45 | G28: {=SLOPE(_xlfn._xlws.FILTER(dataset[ln_soda_units],dataset[state]="WV",""),_xlfn._xlws.FILTER(dataset[ln_soda_ppu],dataset[state]="WV",""))} -> -1.0495232 | H28: {=RSQ(_xlfn._xlws.FILTER(dataset[ln_soda_units],(dataset[state]="WV")*(dataset[soda_units_sold]>0)*(dataset[soda_ppu]>0)),_xlfn._xlws.FILTER(dataset[ln_soda_ppu],(dataset[state]="WV")*(dataset[soda_units_sold]>0)*(dataset[soda_ppu]>0)))} -> 0.068141226 | I28: Neighboring State
B29: High | C29: {=COUNT(_xlfn._xlws.FILTER(dataset[ln_soda_units],(dataset[zip_inc_tier]="High")*(dataset[state]="WV"),""))} -> 36 | D29: {=ROWS(_xlfn.UNIQUE(_xlfn._xlws.FILTER(dataset[store_id],(dataset[zip_inc_tier]="High")*(dataset[state]="WV"))))} -> 1 | E29: =AVERAGEIFS(dataset[soda_ppu],dataset[zip_inc_tier],"High",dataset[state],"WV") -> 0.75346389 | F29: =AVERAGEIFS(dataset[soda_units_sold],dataset[zip_inc_tier],"High",dataset[state],"WV") -> 184153.19 | G29: {=SLOPE( _xlfn._xlws.FILTER(dataset[ln_soda_units],(dataset[zip_inc_tier]="High")*(dataset[state]="WV"),""), _xlfn._xlws.FILTER(dataset[ln_soda_ppu],(dataset[zip_inc_tier]="High")*(dataset[state]="WV"),"") )} -> 0.68975056 | H29: {=RSQ(_xlfn._xlws.FILTER(dataset[ln_soda_units],(dataset[zip_inc_tier]="High")*(dataset[state]="WV")),_xlfn._xlws.FILTER(dataset[ln_soda_ppu],(dataset[zip_inc_tier]="High")*(dataset[state]="WV")))} -> 0.018933474 | I29: The only other High-income anomaly is in WV
B30: Medium | C30: {=COUNT(_xlfn._xlws.FILTER(dataset[ln_soda_units],(dataset[zip_inc_tier]="Med")*(dataset[state]="WV"),""))} -> 288 | D30: {=ROWS(_xlfn.UNIQUE(_xlfn._xlws.FILTER(dataset[store_id],(dataset[zip_inc_tier]="Med")*(dataset[state]="WV"))))} -> 8 | E30: =AVERAGEIFS(dataset[soda_ppu],dataset[zip_inc_tier],"Med",dataset[state],"WV") -> 0.71975104 | F30: =AVERAGEIFS(dataset[soda_units_sold],dataset[zip_inc_tier],"Med",dataset[state],"WV") -> 212701.03 | G30: {=SLOPE( _xlfn._xlws.FILTER(dataset[ln_soda_units],(dataset[zip_inc_tier]="Med")*(dataset[state]="WV"),""), _xlfn._xlws.FILTER(dataset[ln_soda_ppu],(dataset[zip_inc_tier]="Med")*(dataset[state]="WV"),"") )} -> -0.7019305 | H30: {=RSQ(_xlfn._xlws.FILTER(dataset[ln_soda_units],(dataset[zip_inc_tier]="Med")*(dataset[state]="WV")),_xlfn._xlws.FILTER(dataset[ln_soda_ppu],(dataset[zip_inc_tier]="Med")*(dataset[state]="WV")))} -> 0.034710873
B31: Low | C31: {=COUNT(_xlfn._xlws.FILTER(dataset[ln_soda_units],(dataset[zip_inc_tier]="Low")*(dataset[state]="WV"),""))} -> 36 | D31: {=ROWS(_xlfn.UNIQUE(_xlfn._xlws.FILTER(dataset[store_id],(dataset[zip_inc_tier]="Low")*(dataset[state]="WV"))))} -> 1 | E31: =AVERAGEIFS(dataset[soda_ppu],dataset[zip_inc_tier],"Low",dataset[state],"WV") -> 0.73891111 | F31: =AVERAGEIFS(dataset[soda_units_sold],dataset[zip_inc_tier],"Low",dataset[state],"WV") -> 172414.17 | G31: {=SLOPE( _xlfn._xlws.FILTER(dataset[ln_soda_units],(dataset[zip_inc_tier]="Low")*(dataset[state]="WV"),""), _xlfn._xlws.FILTER(dataset[ln_soda_ppu],(dataset[zip_inc_tier]="Low")*(dataset[state]="WV"),"") )} -> -1.2768575 | H31: {=RSQ(_xlfn._xlws.FILTER(dataset[ln_soda_units],(dataset[zip_inc_tier]="Low")*(dataset[state]="WV")),_xlfn._xlws.FILTER(dataset[ln_soda_ppu],(dataset[zip_inc_tier]="Low")*(dataset[state]="WV")))} -> 0.04364113
A32: GA | B32: All | C32: {=COUNT(_xlfn._xlws.FILTER(dataset[ln_soda_units],dataset[state]="GA",""))} -> 648 | D32: {=ROWS(_xlfn.UNIQUE(_xlfn._xlws.FILTER(dataset[store_id],(dataset[state]="GA")*(dataset[soda_units_sold]>0)*(dataset[soda_ppu]>0))))} -> 18 | E32: =AVERAGEIFS(dataset[soda_ppu],dataset[state],"GA",dataset[soda_units_sold],">0",dataset[soda_ppu],">0") -> 0.67985185 | F32: =AVERAGEIFS(dataset[soda_units_sold],dataset[state],"GA",dataset[soda_units_sold],">0",dataset[soda_ppu],">0") -> 225122.13 | G32: {=SLOPE(_xlfn._xlws.FILTER(dataset[ln_soda_units],dataset[state]="GA",""),_xlfn._xlws.FILTER(dataset[ln_soda_ppu],dataset[state]="GA",""))} -> -0.6339563 | H32: {=RSQ(_xlfn._xlws.FILTER(dataset[ln_soda_units],(dataset[state]="GA")*(dataset[soda_units_sold]>0)*(dataset[soda_ppu]>0)),_xlfn._xlws.FILTER(dataset[ln_soda_ppu],(dataset[state]="GA")*(dataset[soda_units_sold]>0)*(dataset[soda_ppu]>0)))} -> 0.021398984 | I32: Neighboring State
B33: High | C33: {=COUNT(_xlfn._xlws.FILTER(dataset[ln_soda_units],(dataset[zip_inc_tier]="High")*(dataset[state]="GA"),""))} -> 108 | D33: {=ROWS(_xlfn.UNIQUE(_xlfn._xlws.FILTER(dataset[store_id],(dataset[zip_inc_tier]="High")*(dataset[state]="GA"))))} -> 3 | E33: =AVERAGEIFS(dataset[soda_ppu],dataset[zip_inc_tier],"High",dataset[state],"GA") -> 0.67691852 | F33: =AVERAGEIFS(dataset[soda_units_sold],dataset[zip_inc_tier],"High",dataset[state],"GA") -> 203614.9 | G33: {=SLOPE( _xlfn._xlws.FILTER(dataset[ln_soda_units],(dataset[zip_inc_tier]="High")*(dataset[state]="GA"),""), _xlfn._xlws.FILTER(dataset[ln_soda_ppu],(dataset[zip_inc_tier]="High")*(dataset[state]="GA"),"") )} -> -0.66169378 | H33: {=RSQ(_xlfn._xlws.FILTER(dataset[ln_soda_units],(dataset[zip_inc_tier]="High")*(dataset[state]="GA")),_xlfn._xlws.FILTER(dataset[ln_soda_ppu],(dataset[zip_inc_tier]="High")*(dataset[state]="GA")))} -> 0.019079092
B34: Medium | C34: {=COUNT(_xlfn._xlws.FILTER(dataset[ln_soda_units],(dataset[zip_inc_tier]="Med")*(dataset[state]="GA"),""))} -> 432 | D34: {=ROWS(_xlfn.UNIQUE(_xlfn._xlws.FILTER(dataset[store_id],(dataset[zip_inc_tier]="Med")*(dataset[state]="GA"))))} -> 12 | E34: =AVERAGEIFS(dataset[soda_ppu],dataset[zip_inc_tier],"Med",dataset[state],"GA") -> 0.68056736 | F34: =AVERAGEIFS(dataset[soda_units_sold],dataset[zip_inc_tier],"Med",dataset[state],"GA") -> 230965.78 | G34: {=SLOPE( _xlfn._xlws.FILTER(dataset[ln_soda_units],(dataset[zip_inc_tier]="Med")*(dataset[state]="GA"),""), _xlfn._xlws.FILTER(dataset[ln_soda_ppu],(dataset[zip_inc_tier]="Med")*(dataset[state]="GA"),"") )} -> -0.65710754 | H34: {=RSQ(_xlfn._xlws.FILTER(dataset[ln_soda_units],(dataset[zip_inc_tier]="Med")*(dataset[state]="GA")),_xlfn._xlws.FILTER(dataset[ln_soda_ppu],(dataset[zip_inc_tier]="Med")*(dataset[state]="GA")))} -> 0.027287226
B35: Low | C35: {=COUNT(_xlfn._xlws.FILTER(dataset[ln_soda_units],(dataset[zip_inc_tier]="Low")*(dataset[state]="GA"),""))} -> 36 | D35: {=ROWS(_xlfn.UNIQUE(_xlfn._xlws.FILTER(dataset[store_id],(dataset[zip_inc_tier]="Low")*(dataset[state]="GA"))))} -> 1 | E35: =AVERAGEIFS(dataset[soda_ppu],dataset[zip_inc_tier],"Low",dataset[state],"GA") -> 0.681 | F35: =AVERAGEIFS(dataset[soda_units_sold],dataset[zip_inc_tier],"Low",dataset[state],"GA") -> 241796.33 | G35: {=SLOPE( _xlfn._xlws.FILTER(dataset[ln_soda_units],(dataset[zip_inc_tier]="Low")*(dataset[state]="GA"),""), _xlfn._xlws.FILTER(dataset[ln_soda_ppu],(dataset[zip_inc_tier]="Low")*(dataset[state]="GA"),"") )} -> -0.61684725 | H35: {=RSQ(_xlfn._xlws.FILTER(dataset[ln_soda_units],(dataset[zip_inc_tier]="Low")*(dataset[state]="GA")),_xlfn._xlws.FILTER(dataset[ln_soda_ppu],(dataset[zip_inc_tier]="Low")*(dataset[state]="GA")))} -> 0.0096546116
A36: *Full Sample includes elasticity from zip codes with no median income data available.
A38: Income Tier | B38: 2022 Avg PPU | C38: 2022 Avg Units | D38: 2024 Avg PPU | E38: 2024 Avg Units | F38: Midpoint Elasticity | G38: Note
A39: All | B39: =IFERROR(AVERAGEIFS(dataset[soda_ppu],dataset[zip_inc_tier],"High",dataset[year_month],">=202201",dataset[year_month],"<=202212",dataset[soda_ppu],">0",dataset[soda_units_sold],">0"),"No rows") -> 0.70590181 | C39: =IFERROR(AVERAGEIFS(dataset[soda_units_sold],dataset[year_month],">=202201",dataset[year_month],"<=202212",dataset[soda_ppu],">0",dataset[soda_units_sold],">0"),"No rows") -> 207267.44 | D39: =IFERROR(AVERAGEIFS(dataset[soda_ppu],dataset[year_month],">=202401",dataset[year_month],"<=202412",dataset[soda_ppu],">0",dataset[soda_units_sold],">0"),"No rows") -> 0.75325942 | E39: =IFERROR(AVERAGEIFS(dataset[soda_units_sold],dataset[year_month],">=202401",dataset[year_month],"<=202412",dataset[soda_ppu],">0",dataset[soda_units_sold],">0"),"No rows") -> 199263.95 | F39: =((E39-C39)/AVERAGE(C39,E39))/((D39-B39)/AVERAGE(B39,D39)) -> -0.60659501
A40: High | B40: =IFERROR(AVERAGEIFS(dataset[soda_ppu],dataset[zip_inc_tier],"High",dataset[year_month],">=202201",dataset[year_month],"<=202212",dataset[soda_ppu],">0",dataset[soda_units_sold],">0"),"No rows") -> 0.70590181 | C40: =IFERROR(AVERAGEIFS(dataset[soda_units_sold],dataset[zip_inc_tier],A40,dataset[year_month],">=202201",dataset[year_month],"<=202212",dataset[soda_ppu],">0",dataset[soda_units_sold],">0"),"No rows") -> 183807.1 | D40: =IFERROR(AVERAGEIFS(dataset[soda_ppu],dataset[zip_inc_tier],A40,dataset[year_month],">=202401",dataset[year_month],"<=202412",dataset[soda_ppu],">0",dataset[soda_units_sold],">0"),"No rows") -> 0.75279493 | E40: =IFERROR(AVERAGEIFS(dataset[soda_units_sold],dataset[zip_inc_tier],A40,dataset[year_month],">=202401",dataset[year_month],"<=202412",dataset[soda_ppu],">0",dataset[soda_units_sold],">0"),"No rows") -> 178699.89 | F40: =((E40-C40)/AVERAGE(C40,E40))/((D40-B40)/AVERAGE(B40,D40)) -> -0.43825104 | G40: Midpoint estimate suggests relatively inelastic demand; average units declined by less than the proportional increase in price.
A41: Medium | B41: =IFERROR(AVERAGEIFS(dataset[soda_ppu],dataset[zip_inc_tier],"Med",dataset[year_month],">=202201",dataset[year_month],"<=202212",dataset[soda_ppu],">0",dataset[soda_units_sold],">0"),"No rows") -> 0.69925278 | C41: =IFERROR(AVERAGEIFS(dataset[soda_units_sold],dataset[zip_inc_tier],"Med",dataset[year_month],">=202201",dataset[year_month],"<=202212",dataset[soda_ppu],">0",dataset[soda_units_sold],">0"),"No rows") -> 216231.04 | D41: =IFERROR(AVERAGEIFS(dataset[soda_ppu],dataset[zip_inc_tier],"Med",dataset[year_month],">=202401",dataset[year_month],"<=202412",dataset[soda_ppu],">0",dataset[soda_units_sold],">0"),"No rows") -> 0.75211415 | E41: =IFERROR(AVERAGEIFS(dataset[soda_units_sold],dataset[zip_inc_tier],"Med",dataset[year_month],">=202401",dataset[year_month],"<=202412",dataset[soda_ppu],">0",dataset[soda_units_sold],">0"),"No rows") -> 207636.96 | F41: =((E41-C41)/AVERAGE(C41,E41))/((D41-B41)/AVERAGE(B41,D41)) -> -0.55668267
A42: Low | B42: =IFERROR(AVERAGEIFS(dataset[soda_ppu],dataset[zip_inc_tier],"Low",dataset[year_month],">=202201",dataset[year_month],"<=202212",dataset[soda_ppu],">0",dataset[soda_units_sold],">0"),"No rows") -> 0.70662167 | C42: =IFERROR(AVERAGEIFS(dataset[soda_units_sold],dataset[zip_inc_tier],A42,dataset[year_month],">=202201",dataset[year_month],"<=202212",dataset[soda_ppu],">0",dataset[soda_units_sold],">0"),"No rows") -> 199425.65 | D42: =IFERROR(AVERAGEIFS(dataset[soda_ppu],dataset[zip_inc_tier],A42,dataset[year_month],">=202401",dataset[year_month],"<=202412",dataset[soda_ppu],">0",dataset[soda_units_sold],">0"),"No rows") -> 0.76279667 | E42: =IFERROR(AVERAGEIFS(dataset[soda_units_sold],dataset[zip_inc_tier],A42,dataset[year_month],">=202401",dataset[year_month],"<=202412",dataset[soda_ppu],">0",dataset[soda_units_sold],">0"),"No rows") -> 187032.03 | F42: =((E42-C42)/AVERAGE(C42,E42))/((D42-B42)/AVERAGE(B42,D42)) -> -0.83887738
A43: Midpoint elasticity was included as sensitivity check against the main constant elasticity. This midpoint estimate only compares average 2022 and 2024 price and quantity levels as such:
A44: Midpoint elasticity = % change in average units / % change in average price
A45: Similar signs across both methods support the direction of the demand response, with the log-log estimate remaining as the primary elasticity estimate.
B50: Formula / explanation
A51: Method | B51: ln(soda_units_sold) = a + b ln(soda_ppu)
A52: Model | B52: The coefficient b is interpreted as price elasticity of demand
A53: Elasticity | B53: Estimated separately for High, Medium, and Low income ZIP/ZCTA store-month observations
A54: Sample | B54: No Data income tier, zero/negative soda units, zero/negative soda price
A55: Excluded rows | B55: The proposed tax is a 5% price increase, and elasticity is a percent quantity response to a percent price change
A56: Reason for log-log model
A58: The Medium and Low estimates follow the expected downward-sloping demand pattern. The High-income estimate is positive, so I retain it for transparency but treat it as a model anomaly rather than evidence of upward-sloping demand.
A59: Income tier | B59: Expected sign | C59: Estimated sign | D59: Possible explanation | G59: How interpreted
A60: High | B60: Negative | C60: Positive | D60: Higher prices may be correlated with store size, premium product mix, stronger local demand, or timing effects | G60: Retained for transparency, but treated cautiously
A61: Medium | B61: Negative | C61: Negative | D61: Matches basic demand expectation | G61: Used directly in tax scenario
A62: Low | B62: Negative | C62: Negative | D62: Matches basic demand expectation | G62: Used directly in tax scenario

Sheet Revenue and Consumption
A1: This worksheet estimates the 2025 Virginia soda tax revenue and expected change in soda consumption under the proposed 5% ad valorem tax. This estimate uses 2024 Virginia soda sales and units as the baseline, scaling the Virginia sample of 33 to 1,000 stores as per the assignment. This will apply the full-sample income-tier constant elasticity estimates from the elasticity worksheet. Pass-through scenarios show how results change if 50%, 75%, or 100% of the tax is reflected in consumer prices.
A2: 100% Pass-Through Scenario
A3: state | B3: VA
A4: Income | B4: 2024
B6: VA Sample Store Count | C6: 2024 Soda Units | D6: 2024 Soda Sales | E6: Scale Factor | F6: Scaled Units | G6: Scaled Soda Sales | H6: Elasticity | I6: Tax Rate | J6: Est. % Change of Units (log-log proiection) | K6: Post-Tax Units | L6: Unit Change | M6: Sales after Demand Shift | N6: Est. Tax Revenue | O6: Notes
A7: High | B7: 11 | C7: 23124174 | D7: 17472271 | E7: 1000 / 33 = 30.30 | F7: =1000/33*GETPIVOTDATA("[Measures].[Sum of soda_units_sold]",$A$6,"[DimZip].[zip_inc_tier]","[DimZip].[zip_inc_tier].&[High]") -> 7.0073255e+08 | G7: =1000/33*GETPIVOTDATA("[Measures].[Sum of soda_sales]",$A$6,"[DimZip].[zip_inc_tier]","[DimZip].[zip_inc_tier].&[High]") -> 5.2946275e+08 | H7: =Elasticity!G7 -> -0.71035913 | I7: 0.05 | J7: =(1+I7)^H7-1 -> -0.03406481 | K7: =F7*(1+J7) -> 6.7686222e+08 | L7: =K7-F7 -> -23870321 | M7: =G7/F7*K7 -> 5.114267e+08 | N7: =M7*0.05 -> 25571335 | O7: Using VA-only High income tier elasticity produced an elastic (0.51) estimate, but this was only flagged as anomalous and not used for estimations.
A8: Medium | B8: 21 | C8: 51721008 | D8: 38908750 | E8: 1000 / 33 = 30.30 | F8: =1000/33*GETPIVOTDATA("[Measures].[Sum of soda_units_sold]",$A$6,"[DimZip].[zip_inc_tier]","[DimZip].[zip_inc_tier].&[Med]") -> 1.5673033e+09 | G8: =1000/33*GETPIVOTDATA("[Measures].[Sum of soda_sales]",$A$6,"[DimZip].[zip_inc_tier]","[DimZip].[zip_inc_tier].&[Med]") -> 1.179053e+09 | H8: =Elasticity!G8 -> -0.92885328 | I8: 0.05 | J8: =(1+I8)^H8-1 -> -0.044307341 | K8: =F8*(1+J8) -> 1.4978602e+09 | L8: =K8-F8 -> -69443041 | M8: =G8/F8*K8 -> 1.1268123e+09 | N8: =M8*0.05 -> 56340617
A9: Low | B9: 1 | C9: 1988027 | D9: 1512895.2 | E9: 1000 / 33 = 30.30 | F9: =1000/33*GETPIVOTDATA("[Measures].[Sum of soda_units_sold]",$A$6,"[DimZip].[zip_inc_tier]","[DimZip].[zip_inc_tier].&[Low]") -> 60243242 | G9: =1000/33*GETPIVOTDATA("[Measures].[Sum of soda_sales]",$A$6,"[DimZip].[zip_inc_tier]","[DimZip].[zip_inc_tier].&[Low]") -> 45845310 | H9: =Elasticity!G9 -> -1.9421318 | I9: 0.05 | J9: =(1+I9)^H9-1 -> -0.090405995 | K9: =F9*(1+J9) -> 54796892 | L9: =K9-F9 -> -5446350.3 | M9: =G9/F9*K9 -> 41700619 | N9: =M9*0.05 -> 2085031 | O9: Only one VA Low income store was observed, so the upscaled estimate should be treated with caution.
A10: Total | B10: 33 | C10: 76833209 | D10: 57893916 | E10: 1000 / 33 = 30.30 | F10: =1000/33*GETPIVOTDATA("[Measures].[Sum of soda_units_sold]",$A$6) -> 2.3282791e+09 | G10: =1000/33*GETPIVOTDATA("[Measures].[Sum of soda_sales]",$A$6) -> 1.7543611e+09 | H10: =Elasticity!G6 -> -0.97684053 | I10: 0.05 | J10: =(1+I10)^H10-1 -> -0.046542293 | K10: =SUM(K7:K9) -> 2.2295193e+09 | L10: =SUM(L7:L9) -> -98759712 | M10: =SUM(M7:M9) -> 1.6799397e+09 | N10: =SUM(N7:N9) -> 83996983
A11: Notes: Estimated demand response is based on elasticity and the assumed price increase. Tier-level estimates should be treated with caution as sample sizes differ, with the total row being our preferred estimates for revenue and demand effects.
A13: Pass-through sensitivity summary
A14: Pass-through | B14: Consumer Price Increase | C14: Post-Tax Units | D14: Unit Change | E14: % Unit Change | F14: Sales after Demand Shift | G14: Est. Tax Revenue
A15: 1 | B15: =0.05*A15 -> 0.05 | C15: =SUM(F7*(1+(1+B15)^H7-1),F8*(1+(1+B15)^H8-1),F9*(1+(1+B15)^H9-1)) -> 2.2295193e+09 | D15: =C15-F$10 -> -98759712 | E15: =(1+B15)^H10-1 -> -0.046542293 | F15: =SUM($G$7*(1+(1+B15)^$H$7-1),$G$8*(1+(1+B15)^$H$8-1),$G$9*(1+(1+B15)^$H$9-1)) -> 1.6799397e+09 | G15: =F15*0.05 -> 83996983
A16: 0.75 | B16: =0.05*A16 -> 0.0375 | C16: =SUM(F7*(1+(1+B16)^H7-1),F8*(1+(1+B16)^H8-1),F9*(1+(1+B16)^H9-1)) -> 2.2533471e+09 | D16: =C16-F$10 -> -74931930 | E16: =D16/F$10 -> -0.032183397 | F16: =SUM($G$7*(1+(1+B16)^$H$7-1),$G$8*(1+(1+B16)^$H$8-1),$G$9*(1+(1+B16)^$H$9-1)) -> 1.6978952e+09 | G16: =F16*0.05 -> 84894760
A17: 0.5 | B17: =0.05*A17 -> 0.025 | C17: =SUM(F7*(1+(1+B17)^H7-1),F8*(1+(1+B17)^H8-1),F9*(1+(1+B17)^H9-1)) -> 2.2777358e+09 | D17: =C17-F$10 -> -50543247 | E17: =D17/F$10 -> -0.021708415 | F17: =SUM($G$7*(1+(1+B17)^$H$7-1),$G$8*(1+(1+B17)^$H$8-1),$G$9*(1+(1+B17)^$H$9-1)) -> 1.7162735e+09 | G17: =F17*0.05 -> 85813675
A18: Total
A19: Notes: Consistent trend of lower pass-through produces higher estimated tax revenue, as the smaller consumer price increase leads to a smaller reduction in quantity demanded and thus a larger taxable sales base.
A22: Maryland Raw Soda Sales by Income Tier and Year
A23: state | B23: MD
A24: year_month | B24: All
B27: 2022 | F27: 2023 | J27: 2024
A28: Income Tier | B28: Store Count | C28: Avg Soda PPU | D28: Soda Units | E28: Soda Sales | F28: Store Count | G28: Avg Soda PPU | H28: Soda Units | I28: Soda Sales | J28: Store Count | K28: Avg Soda PPU | L28: Soda Units | M28: Soda Sales
A29: High | B29: 7 | C29: 0.71396548 | D29: 14882697 | E29: 10597280 | F29: 7 | G29: 0.734125 | H29: 14743133 | I29: 10779559 | J29: 7 | K29: 0.77092857 | L29: 14355280 | M29: 11043593
A30: Med | B30: 8 | C30: 0.69946146 | D30: 20429023 | E30: 14276206 | F30: 8 | G30: 0.72212188 | H30: 20090519 | I30: 14491121 | J30: 8 | K30: 0.75377917 | L30: 19608249 | M30: 14766446
A31: Grand Total | B31: 15 | C31: 0.70623 | D31: 35311720 | E31: 24873486 | F31: 15 | G31: 0.72772333 | H31: 34833652 | I31: 25270680 | J31: 15 | K31: 0.76178222 | L31: 33963529 | M31: 25810039
A33: North Carolina Raw Soda Sales by Income Tier and Year
A34: state | B34: NC
A35: year_month | B35: All
B38: 2022 | F38: 2023 | J38: 2024
A39: Income Tier | B39: Store Count | C39: Avg Soda PPU | D39: Soda Units | E39: Soda Sales | F39: Store Count | G39: Avg Soda PPU | H39: Soda Units | I39: Soda Sales | J39: Store Count | K39: Avg Soda PPU | L39: Soda Units | M39: Soda Sales
A40: Med | B40: 14 | C40: 0.71668095 | D40: 35621041 | E40: 25507289 | F40: 14 | G40: 0.75000357 | H40: 34204703 | I40: 25619798 | J40: 14 | K40: 0.79666607 | L40: 32746694 | M40: 26056467
A41: Low | B41: 2 | C41: 0.71374167 | D41: 4941584 | E41: 3518580.5 | F41: 2 | G41: 0.74614167 | H41: 4675391 | I41: 3471846.4 | J41: 2 | K41: 0.79495833 | L41: 4313546 | M41: 3422024.6
A42: No Data | B42: 3 | C42: 0.69621389 | D42: 7807255 | E42: 5429283.4 | F42: 3 | G42: 0.72691389 | H42: 7566403 | I42: 5492162.2 | J42: 3 | K42: 0.77713889 | L42: 7271937 | M42: 5642889.3
A43: Grand Total | B43: 19 | C43: 0.71313991 | D43: 48369880 | E43: 34455153 | F43: 19 | G43: 0.74595132 | H43: 46446497 | I43: 34583807 | J43: 19 | K43: 0.79340307 | L43: 44332177 | M43: 35121381
A45: Georgia Raw Soda Sales by Income Tier and Year
A46: state | B46: GA
A47: year_month | B47: All
B50: 2022 | F50: 2023 | J50: 2024
A51: Income Tier | B51: Store Count | C51: Avg Soda PPU | D51: Soda Units | E51: Soda Sales | F51: Store Count | G51: Avg Soda PPU | H51: Soda Units | I51: Soda Sales | J51: Store Count | K51: Avg Soda PPU | L51: Soda Units | M51: Soda Sales
A52: High | B52: 3 | C52: 0.65757222 | D52: 7432441 | E52: 4885861.3 | F52: 3 | G52: 0.67552778 | H52: 7319399 | I52: 4937740.8 | J52: 3 | K52: 0.69765556 | L52: 7238569 | M52: 5048473.9
A53: Med | B53: 12 | C53: 0.66132153 | D53: 33685822 | E53: 22251441 | F53: 12 | G53: 0.67691181 | H53: 33334799 | I53: 22527252 | J53: 12 | K53: 0.70346875 | L53: 32756594 | M53: 23030221
A54: Low | B54: 1 | C54: 0.66363333 | D54: 2926646 | E54: 1938679.6 | F54: 1 | G54: 0.67988333 | H54: 2886953 | I54: 1962333.5 | J54: 1 | K54: 0.69948333 | L54: 2891069 | M54: 2023517.5
A55: No Data | B55: 2 | C55: 0.6569125 | D55: 5209190 | E55: 3414274 | F55: 2 | G55: 0.6802125 | H55: 5121626 | I55: 3478558 | J55: 2 | K55: 0.70102917 | L55: 5076033 | M55: 3555345.6
A56: Grand Total | B56: 18 | C56: 0.66033519 | D56: 49254099 | E56: 32490256 | F56: 18 | G56: 0.67721296 | H56: 48662777 | I56: 32905884 | J56: 18 | K56: 0.70200741 | L56: 47962265 | M56: 33657558
A58: Maryland Tax-Step Diagnostics: 0% to 1%; 1% to 2%
A59: State | B59: Income Tier | C59: Policy Step | D59: Tax Rate Change | E59: Pre Avg PPU | F59: Post Avg PPU | G59: Actual % Price Change | H59: Elasticity Sample Period | I59: Elasticity Used | J59: Pre Soda Units | K59: Post Soda Units | L59: Predicted % Unit Change | M59: Actual % Unit Change | N59: Prediction Gap | O59: Note
A60: MD | B60: High | C60: 2022 to 2023 | D60: 0% to 1% | E60: =GETPIVOTDATA("[Measures].[Average of soda_ppu]",$A$26,"[DimZip].[zip_inc_tier]","[DimZip].[zip_inc_tier].&[High]","[DimDate].[year]","[DimDate].[year].&[2022]") -> 0.71396548 | F60: =GETPIVOTDATA("[Measures].[Average of soda_ppu]",$A$26,"[DimZip].[zip_inc_tier]","[DimZip].[zip_inc_tier].&[High]","[DimDate].[year]","[DimDate].[year].&[2023]") -> 0.734125 | G60: =(F60-E60)/E60 -> 0.028235992 | H60: 2022 | I60: {=SLOPE(_xlfn._xlws.FILTER(dataset[ln_soda_units],(dataset[zip_inc_tier]=B60)*(VALUE(dataset[year_month])>=202201)*(VALUE(dataset[year_month])<=202212)),_xlfn._xlws.FILTER(dataset[ln_soda_ppu],(dataset[zip_inc_tier]=B60)*(VALUE(dataset[year_month])>=202201)*(VALUE(dataset[year_month])<=202212)))} -> -0.61625475 | J60: {=D29:D31} -> 14882697 | K60: {=H29:H31} -> 14743133 | L60: =I60*G60 -> -0.017400565 | M60: =(K60-J60)/J60 -> -0.0093776014 | N60: =M60-L60 -> 0.0080229632
A61: MD | B61: Medium | C61: 2022 to 2023 | D61: 0% to 1% | E61: =GETPIVOTDATA("[Measures].[Average of soda_ppu]",$A$26,"[DimZip].[zip_inc_tier]","[DimZip].[zip_inc_tier].&[Med]","[DimDate].[year]","[DimDate].[year].&[2022]") -> 0.69946146 | F61: =GETPIVOTDATA("[Measures].[Average of soda_ppu]",$A$26,"[DimZip].[zip_inc_tier]","[DimZip].[zip_inc_tier].&[Med]","[DimDate].[year]","[DimDate].[year].&[2023]") -> 0.72212188 | G61: =(F61-E61)/E61 -> 0.032396948 | H61: 2022 | I61: {=SLOPE(_xlfn._xlws.FILTER(dataset[ln_soda_units],(dataset[zip_inc_tier]="Med")*(VALUE(dataset[year_month])>=202201)*(VALUE(dataset[year_month])<=202212)),_xlfn._xlws.FILTER(dataset[ln_soda_ppu],(dataset[zip_inc_tier]="Med")*(VALUE(dataset[year_month])>=202201)*(VALUE(dataset[year_month])<=202212)))} -> -0.99005931 | J61: 20429023 | K61: 20090519 | L61: =I61*G61 -> -0.0320749 | M61: =(K61-J61)/J61 -> -0.01656976 | N61: =M61-L61 -> 0.015505141
A62: MD | B62: Total | C62: 2022 to 2023 | D62: 0% to 1% | E62: =GETPIVOTDATA("[Measures].[Average of soda_ppu]",$A$26,"[DimDate].[year]","[DimDate].[year].&[2022]") -> 0.70623 | F62: =GETPIVOTDATA("[Measures].[Average of soda_ppu]",$A$26,"[DimDate].[year]","[DimDate].[year].&[2023]") -> 0.72772333 | G62: =(F62-E62)/E62 -> 0.0304339 | H62: 2022 | I62: {=SLOPE(_xlfn._xlws.FILTER(dataset[ln_soda_units],(dataset[year_month]>=202201)*(dataset[year_month]<=202212)),_xlfn._xlws.FILTER(dataset[ln_soda_ppu],(dataset[year_month]>=202201)*(dataset[year_month]<=202212)))} -> -1.1127167 | J62: 35311720 | K62: 34833652 | L62: =I62*G62 -> -0.033864309 | M62: =(K62-J62)/J62 -> -0.013538508 | N62: =M62-L62 -> 0.020325801
A63: MD | B63: High | C63: 2023 to 2024 | D63: 1% to 2% | E63: =GETPIVOTDATA("[Measures].[Average of soda_ppu]",$A$26,"[DimZip].[zip_inc_tier]","[DimZip].[zip_inc_tier].&[High]","[DimDate].[year]","[DimDate].[year].&[2023]") -> 0.734125 | F63: =GETPIVOTDATA("[Measures].[Average of soda_ppu]",$A$26,"[DimZip].[zip_inc_tier]","[DimZip].[zip_inc_tier].&[High]","[DimDate].[year]","[DimDate].[year].&[2024]") -> 0.77092857 | G63: =(F63-E63)/E63 -> 0.050132568 | H63: 2022, 2023 | I63: {=SLOPE(_xlfn._xlws.FILTER(dataset[ln_soda_units],(dataset[zip_inc_tier]="High")*(dataset[year_month]>=202201)*(dataset[year_month]<=202312)),_xlfn._xlws.FILTER(dataset[ln_soda_ppu],(dataset[zip_inc_tier]="High")*(dataset[year_month]>=202201)*(dataset[year_month]<=202312)))} -> -0.92754934 | J63: {=H29:H31} -> 14743133 | K63: {=L29:L31} -> 14355280 | L63: =I63*G63 -> -0.04650043 | M63: =(K63-J63)/J63 -> -0.026307366 | N63: =M63-L63 -> 0.020193064 | O63: substantially higher actual % price change compared to tax increase
A64: MD | B64: Medium | C64: 2023 to 2024 | D64: 1% to 2% | E64: =GETPIVOTDATA("[Measures].[Average of soda_ppu]",$A$26,"[DimZip].[zip_inc_tier]","[DimZip].[zip_inc_tier].&[Med]","[DimDate].[year]","[DimDate].[year].&[2023]") -> 0.72212188 | F64: =GETPIVOTDATA("[Measures].[Average of soda_ppu]",$A$26,"[DimZip].[zip_inc_tier]","[DimZip].[zip_inc_tier].&[Med]","[DimDate].[year]","[DimDate].[year].&[2024]") -> 0.75377917 | G64: =(F64-E64)/E64 -> 0.043839264 | H64: 2022, 2023 | I64: {=SLOPE(_xlfn._xlws.FILTER(dataset[ln_soda_units],(dataset[zip_inc_tier]="Med")*(dataset[year_month]>=202201)*(dataset[year_month]<=202312)),_xlfn._xlws.FILTER(dataset[ln_soda_ppu],(dataset[zip_inc_tier]="Med")*(dataset[year_month]>=202201)*(dataset[year_month]<=202312)))} -> -1.0933144 | J64: 20090519 | K64: 19608249 | L64: =I64*G64 -> -0.0479301 | M64: =(K64-J64)/J64 -> -0.024004855 | N64: =M64-L64 -> 0.023925244
A65: MD | B65: Total | C65: 2023 to 2024 | D65: 1% to 2% | E65: =GETPIVOTDATA("[Measures].[Average of soda_ppu]",$A$26,"[DimDate].[year]","[DimDate].[year].&[2023]") -> 0.72772333 | F65: =GETPIVOTDATA("[Measures].[Average of soda_ppu]",$A$26,"[DimDate].[year]","[DimDate].[year].&[2024]") -> 0.76178222 | G65: =(F65-E65)/E65 -> 0.046801974 | H65: 2022, 2023 | I65: {=SLOPE(_xlfn._xlws.FILTER(dataset[ln_soda_units],(dataset[year_month]>=202201)*(dataset[year_month]<=202312)),_xlfn._xlws.FILTER(dataset[ln_soda_ppu],(dataset[year_month]>=202201)*(dataset[year_month]<=202312)))} -> -1.1982267 | J65: 34833652 | K65: 33963529 | L65: =I65*G65 -> -0.056079377 | M65: =(K65-J65)/J65 -> -0.024979379 | N65: =M65-L65 -> 0.031099998
A67: North Carolina Tax Diagnostics: 0% to 5%
A68: State | B68: Income Tier | C68: Policy Step | D68: Tax Rate Change | E68: Pre Avg PPU | F68: Post Avg PPU | G68: Actual % Price Change | H68: Elasticity Sample Period | I68: Elasticity Used | J68: Pre Soda Units | K68: Post Soda Units | L68: Predicted % Unit Change | M68: Actual % Unit Change | N68: Prediction Gap | O68: Note
A69: NC | B69: Medium | C69: 2022 to 2024 | D69: 0% to 5% | E69: =GETPIVOTDATA("[Measures].[Average of soda_ppu]",$A$37,"[DimZip].[zip_inc_tier]","[DimZip].[zip_inc_tier].&[Med]","[DimDate].[year]","[DimDate].[year].&[2022]") -> 0.71668095 | F69: =GETPIVOTDATA("[Measures].[Average of soda_ppu]",$A$37,"[DimZip].[zip_inc_tier]","[DimZip].[zip_inc_tier].&[Med]","[DimDate].[year]","[DimDate].[year].&[2023]") -> 0.75000357 | G69: =F69/E69-1 -> 0.046495751 | H69: 2022 | I69: {=SLOPE(_xlfn._xlws.FILTER(dataset[ln_soda_units],(dataset[zip_inc_tier]="Med")*(VALUE(dataset[year_month])>=202201)*(VALUE(dataset[year_month])<=202212)),_xlfn._xlws.FILTER(dataset[ln_soda_ppu],(dataset[zip_inc_tier]="Med")*(VALUE(dataset[year_month])>=202201)*(VALUE(dataset[year_month])<=202212)))} -> -0.99005931 | J69: =GETPIVOTDATA("[Measures].[Sum of soda_units_sold]",$A$37,"[DimZip].[zip_inc_tier]","[DimZip].[zip_inc_tier].&[Med]","[DimDate].[year]","[DimDate].[year].&[2022]") -> 35621041 | K69: {=L40:L41} -> 32746694 | L69: =I69*G69 -> -0.046033551 | M69: =(K69-J69)/J69 -> -0.080692392 | N69: =M69-L69 -> -0.034658841
A70: NC | B70: Low | C70: 2022 to 2024 | D70: 0% to 5% | E70: =GETPIVOTDATA("[Measures].[Average of soda_ppu]",$A$37,"[DimZip].[zip_inc_tier]","[DimZip].[zip_inc_tier].&[Low]","[DimDate].[year]","[DimDate].[year].&[2022]") -> 0.71374167 | F70: =GETPIVOTDATA("[Measures].[Average of soda_ppu]",$A$37,"[DimZip].[zip_inc_tier]","[DimZip].[zip_inc_tier].&[Low]","[DimDate].[year]","[DimDate].[year].&[2023]") -> 0.74614167 | G70: =F70/E70-1 -> 0.045394576 | H70: 2022 | I70: {=SLOPE(_xlfn._xlws.FILTER(dataset[ln_soda_units],(dataset[zip_inc_tier]="Low")*(VALUE(dataset[year_month])>=202201)*(VALUE(dataset[year_month])<=202212)),_xlfn._xlws.FILTER(dataset[ln_soda_ppu],(dataset[zip_inc_tier]="Low")*(VALUE(dataset[year_month])>=202201)*(VALUE(dataset[year_month])<=202212)))} -> -2.9659282 | J70: =GETPIVOTDATA("[Measures].[Sum of soda_units_sold]",$A$37,"[DimZip].[zip_inc_tier]","[DimZip].[zip_inc_tier].&[Low]","[DimDate].[year]","[DimDate].[year].&[2022]") -> 4941584 | K70: 4313546 | L70: =I70*G70 -> -0.13463705 | M70: =(K70-J70)/J70 -> -0.12709245 | N70: =M70-L70 -> 0.0075446043
A71: NC | B71: Total | C71: 2022 to 2024 | D71: 0% to 5% | E71: =GETPIVOTDATA("[Measures].[Average of soda_ppu]",$A$37,"[DimDate].[year]","[DimDate].[year].&[2022]") -> 0.71313991 | F71: =GETPIVOTDATA("[Measures].[Average of soda_ppu]",$A$37,"[DimDate].[year]","[DimDate].[year].&[2024]") -> 0.79340307 | G71: =F71/E71-1 -> 0.11254896 | H71: 2022 | I71: {=SLOPE(_xlfn._xlws.FILTER(dataset[ln_soda_units],(dataset[year_month]>=202201)*(dataset[year_month]<=202212)),_xlfn._xlws.FILTER(dataset[ln_soda_ppu],(dataset[year_month]>=202201)*(dataset[year_month]<=202212)))} -> -1.1127167 | J71: =GETPIVOTDATA("[Measures].[Sum of soda_units_sold]",$A$37,"[DimDate].[year]","[DimDate].[year].&[2022]") -> 48369880 | K71: =GETPIVOTDATA("[Measures].[Sum of soda_units_sold]",$A$37,"[DimDate].[year]","[DimDate].[year].&[2024]") -> 44332177 | L71: =I71*G71 -> -0.12523511 | M71: =(K71-J71)/J71 -> -0.083475564 | N71: =M71-L71 -> 0.041759549 | O71: substantially higher actual % price change compared to tax increase
A72: Note: 2023 is excluded as it is a mixed tax year.
A74: Control State: Georgia
A75: Control Usage | B75: State | C75: Policy Step | D75: Pre Avg PPU | E75: Post Avg PPU | F75: Actual % Price Change | G75: Elasticity Sample Period | H75: Elasticity Used | I75: Pre Soda Units | J75: Post Soda Units | K75: Predicted % Unit Change | L75: Actual % Unit Change | M75: Residual Unit Gap | N75: Adjusted Gap vs GA | O75: Note
A76: MD Step 1 control | B76: GA | C76: 2022 to 2023 | D76: =GETPIVOTDATA("[Measures].[Average of soda_ppu]",$A$49,"[DimDate].[year]","[DimDate].[year].&[2022]") -> 0.66033519 | E76: =GETPIVOTDATA("[Measures].[Average of soda_ppu]",$A$49,"[DimDate].[year]","[DimDate].[year].&[2023]") -> 0.67721296 | F76: =E76/D76-1 -> 0.02555941 | G76: =H62 -> 2022 | H76: =I62 -> -1.1127167 | I76: =GETPIVOTDATA("[Measures].[Sum of soda_units_sold]",$A$49,"[DimDate].[year]","[DimDate].[year].&[2022]") -> 49254099 | J76: =GETPIVOTDATA("[Measures].[Sum of soda_units_sold]",$A$49,"[DimDate].[year]","[DimDate].[year].&[2023]") -> 48662777 | K76: =H76*F76 -> -0.028440383 | L76: =(J76-I76)/I76 -> -0.012005539 | M76: =100*(L76-K76) -> 1.6434844 | N76: =100*(N62-M76/100) -> 0.38909576
A77: MD Step 2 control | B77: GA | C77: 2023 to 2024 | D77: =GETPIVOTDATA("[Measures].[Average of soda_ppu]",$A$49,"[DimDate].[year]","[DimDate].[year].&[2023]") -> 0.67721296 | E77: =GETPIVOTDATA("[Measures].[Average of soda_ppu]",$A$49,"[DimDate].[year]","[DimDate].[year].&[2024]") -> 0.70200741 | F77: =E77/D77-1 -> 0.036612478 | G77: =H65 -> 2022, 2023 | H77: =I65 -> -1.1982267 | I77: =GETPIVOTDATA("[Measures].[Sum of soda_units_sold]",$A$49,"[DimDate].[year]","[DimDate].[year].&[2023]") -> 48662777 | J77: =GETPIVOTDATA("[Measures].[Sum of soda_units_sold]",$A$49,"[DimDate].[year]","[DimDate].[year].&[2024]") -> 47962265 | K77: =H77*F77 -> -0.04387005 | L77: =(J77-I77)/I77 -> -0.014395233 | M77: =100*(L77-K77) -> 2.9474817 | N77: =100*(N65-M77/100) -> 0.16251812
A78: NC control | B78: GA | C78: 2022 to 2024 | D78: =GETPIVOTDATA("[Measures].[Average of soda_ppu]",$A$49,"[DimDate].[year]","[DimDate].[year].&[2022]") -> 0.66033519 | E78: =GETPIVOTDATA("[Measures].[Average of soda_ppu]",$A$49,"[DimDate].[year]","[DimDate].[year].&[2024]") -> 0.70200741 | F78: =E78/D78-1 -> 0.063107681 | G78: =H71 -> 2022 | H78: =I71 -> -1.1127167 | I78: =GETPIVOTDATA("[Measures].[Sum of soda_units_sold]",$A$49,"[DimDate].[year]","[DimDate].[year].&[2022]") -> 49254099 | J78: =GETPIVOTDATA("[Measures].[Sum of soda_units_sold]",$A$49,"[DimDate].[year]","[DimDate].[year].&[2024]") -> 47962265 | K78: =H78*F78 -> -0.070220971 | L78: =(J78-I78)/I78 -> -0.026227949 | M78: =100*(L78-K78) -> 4.3993022 | N78: =100*(N71-M78/100) -> -0.22334734
A79: Note: The low percentage point changes between MD/NC and the control with no tax policies of GA suggests that a simple price-elasticity prediction is picking up broader patterns, and is not clean from a tax-specific effect.
A80: MD and NC diagnostics showed positive prediction gaps, showing that soda declined less than the elasticity-price model predicted.

Sheet Pivot
A1: Row Labels | B1: Sum of soda_sales | D1: Row Labels | E1: Sum of soda_sales | G1: Row Labels | H1: Sum of total_sales | I1: Sum of soda_sales
A2: 202201 | B2: 9824079.7 | D2: High | E2: 1.0906948e+08 | G2: DC | H2: 1.9974161e+08 | I2: 10616441
A3: 202202 | B3: 11132229 | D3: Low | E3: 25422407 | G3: GA | H3: 1.6276913e+09 | I3: 99053698
A4: 202203 | B4: 13102487 | D4: Med | E4: 3.470828e+08 | G4: MD | H4: 1.6628749e+09 | I4: 75954205
A5: 202204 | B5: 15255726 | D5: No Data | E5: 48048820 | G5: NC | H5: 1.6442658e+09 | I5: 1.0416034e+08
A6: 202205 | B6: 16742029 | D6: Grand Total | E6: 5.2962351e+08 | G6: VA | H6: 3.3024633e+09 | I6: 1.7050606e+08
A7: 202206 | B7: 17459533 | G7: WV | H7: 1.1245847e+09 | I7: 69332765
A8: 202207 | B8: 18006092 | G8: Grand Total | H8: 9.5616216e+09 | I8: 5.2962351e+08
A9: 202208 | B9: 15799476
A10: 202209 | B10: 15071250
A11: 202210 | B11: 14509826
A12: 202211 | B12: 13740015
A13: 202212 | B13: 13338841
A14: 202301 | B14: 9920396.6
A15: 202302 | B15: 11278475
A16: 202303 | B16: 13227993
A17: 202304 | B17: 15452669
A18: 202305 | B18: 17000119
A19: 202306 | B19: 17621038
A20: 202307 | B20: 18174788
... A37: 202412 | B37: 13840959
A38: Grand Total | B38: 5.2962351e+08

Sheet Visuals
A1: Summary Statistics | F1: obs: 3600
A2: Variable | B2: Mean | C2: Std.Dev. | D2: Min | E2: Median | F2: Max
A3: ='[1]Flat Data'!C1 -> total_sales | B3: =AVERAGE('[1]Flat Data'!C:C) -> 2656006 | C3: =_xlfn.STDEV.S('[1]Flat Data'!C:C) -> 660219.08 | D3: =MIN('[1]Flat Data'!C:C) -> 1286241 | E3: =MEDIAN('[1]Flat Data'!C:C) -> 2531489.1 | F3: =MAX('[1]Flat Data'!C:C) -> 5934473.6
A4: ='[1]Flat Data'!D1 -> soda_ppu | B4: =AVERAGE('[1]Flat Data'!D:D) -> 0.72502307 | C4: =_xlfn.STDEV.S('[1]Flat Data'!D:D) -> 0.041324884 | D4: =MIN('[1]Flat Data'!D:D) -> 0.60061552 | E4: =MEDIAN('[1]Flat Data'!D:D) -> 0.7235069 | F4: =MAX('[1]Flat Data'!D:D) -> 0.8625723
A5: ='[1]Flat Data'!E1 -> soda_units_sold | B5: =AVERAGE('[1]Flat Data'!E:E) -> 203580.39 | C5: =_xlfn.STDEV.S('[1]Flat Data'!E:E) -> 40947.526 | D5: =MIN('[1]Flat Data'!E:E) -> 69424 | E5: =MEDIAN('[1]Flat Data'!E:E) -> 205126.5 | F5: =MAX('[1]Flat Data'!E:E) -> 328920
A6: ='[1]Flat Data'!F1 -> soda_sales | B6: =AVERAGE('[1]Flat Data'!F:F) -> 147117.64 | C6: =_xlfn.STDEV.S('[1]Flat Data'!F:F) -> 28176.006 | D6: =MIN('[1]Flat Data'!F:F) -> 48509.86 | E6: =MEDIAN('[1]Flat Data'!F:F) -> 149106.27 | F6: =MAX('[1]Flat Data'!F:F) -> 211795.79
A7: ='[1]Flat Data'!G1 -> soda_sales_shares | B7: =AVERAGE('[1]Flat Data'!G:G) -> 0.058517994 | C7: =_xlfn.STDEV.S('[1]Flat Data'!G:G) -> 0.01664612 | D7: =MIN('[1]Flat Data'!G:G) -> 0.011222857 | E7: =MEDIAN('[1]Flat Data'!G:G) -> 0.05832408 | F7: =MAX('[1]Flat Data'!G:G) -> 0.11159551
A8: ='[1]Flat Data'!K1 -> med_income_avg | B8: =AVERAGE('[1]Flat Data'!K:K) -> 70859.363 | C8: =_xlfn.STDEV.S('[1]Flat Data'!K:K) -> 36880.998 | D8: =MIN('[1]Flat Data'!K:K) -> 0 | E8: =MEDIAN('[1]Flat Data'!K:K) -> 69087.833 | F8: =MAX('[1]Flat Data'!K:K) -> 176011.67
A9: *Observation count is 3,600 store-month observations with 100 stores x 36 months.
A11: Income Tier | B11: Scope | C11: Store-Month Obs. | D11: Distinct Stores | E11: Avg Soda PPU | F11: Avg Monthly Soda Units | G11: Avg Soda Sales | H11: Avg Soda Sales Share
A12: High | B12: All
B13: VA
A14: Medium | B14: All
B15: VA
A16: Low | B16: All
B17: VA
A18: No Data | B18: All
B19: VA
A20: Total | B20: 3600 | C20: 100
A22: Income tier observations
A23: High | B23: Medium | C23: Low | D23: No Data
A24: =COUNTIF('[1]Flat Data'!J:J,"High") -> #VALUE! | B24: =COUNTIF('[1]Flat Data'!J:J,"Med") -> #VALUE! | C24: =COUNTIF('[1]Flat Data'!J:J,"Low") -> #VALUE! | D24: =COUNTIF('[1]Flat Data'!J:J,"No Data") -> #VALUE!
A26: State coverage (distinct stores)
A27: VA | B27: MD | C27: DC | D27: WV | E27: NC | F27: GA
A28: =COUNTIF('[1]Flat Data'!I:I,"VA")/36 -> #VALUE! | B28: =COUNTIF('[1]Flat Data'!I:I,"MD")/36 -> #VALUE! | C28: =COUNTIF('[1]Flat Data'!I:I,"DC")/36 -> #VALUE! | D28: =COUNTIF('[1]Flat Data'!I:I,"WV")/36 -> #VALUE! | E28: =COUNTIF('[1]Flat Data'!I:I,"NC")/36 -> #VALUE! | F28: =COUNTIF('[1]Flat Data'!I:I,"GA")/36 -> #VALUE!

Sheet dataset
A1: year_month | B1: store_id | C1: total_sales | D1: soda_ppu | E1: soda_units_sold | F1: soda_sales | G1: zip | H1: state | I1: zip_med_inc_avg | J1: zip_inc_tier | K1: implied_soda_ppu | L1: check_soda_ppu | M1: soda_sales_share | N1: ln_soda_units | O1: ln_soda_sales | P1: ln_soda_ppu | Q1: is_VA
A2: 202201 | B2: 2 | C2: 2267236.9 | D2: 0.7071 | E2: 142774 | F2: 100953.27 | G2: 20024 | H2: DC | I2: =HLOOKUP(G2,zip_tiers!$A$1:$EON$2,2,FALSE) -> 102576 | J2: =IF(I2="","No Data",IF(I2>=100000,"High",IF(I2>=40000,"Med","Low"))) -> High | K2: =dataset[[#This Row],[soda_sales]]/dataset[[#This Row],[soda_units_sold]] -> 0.70708444 | L2: =dataset[[#This Row],[implied_soda_ppu]]-dataset[[#This Row],[soda_ppu]] -> -1.5556754e-05 | M2: =dataset[[#This Row],[soda_sales]]/dataset[[#This Row],[total_sales]] -> 0.044527007 | N2: =LN(dataset[[#This Row],[soda_units_sold]]) -> 11.869018 | O2: =LN(dataset[[#This Row],[soda_sales]]) -> 11.522413 | P2: =LN(dataset[[#This Row],[soda_ppu]]) -> -0.34658318 | Q2: =IF(dataset[[#This Row],[state]]="VA",1,0) -> 0
A3: 202202 | B3: 2 | C3: 2508276.2 | D3: 0.6961 | E3: 159898 | F3: 111309.18 | G3: 20024 | H3: DC | I3: =HLOOKUP(G3,zip_tiers!$A$1:$EON$2,2,FALSE) -> 102576 | J3: =IF(I3="","No Data",IF(I3>=100000,"High",IF(I3>=40000,"Med","Low"))) -> High | K3: =dataset[[#This Row],[soda_sales]]/dataset[[#This Row],[soda_units_sold]] -> 0.69612618 | L3: =dataset[[#This Row],[implied_soda_ppu]]-dataset[[#This Row],[soda_ppu]] -> 2.6184192e-05 | M3: =dataset[[#This Row],[soda_sales]]/dataset[[#This Row],[total_sales]] -> 0.044376765 | N3: =LN(dataset[[#This Row],[soda_units_sold]]) -> 11.982291 | O3: =LN(dataset[[#This Row],[soda_sales]]) -> 11.620067 | P3: =LN(dataset[[#This Row],[soda_ppu]]) -> -0.36226195 | Q3: =IF(dataset[[#This Row],[state]]="VA",1,0) -> 0
A4: 202203 | B4: 2 | C4: 2817658.1 | D4: 0.7273 | E4: 185067 | F4: 134594.64 | G4: 20024 | H4: DC | I4: =HLOOKUP(G4,zip_tiers!$A$1:$EON$2,2,FALSE) -> 102576 | J4: =IF(I4="","No Data",IF(I4>=100000,"High",IF(I4>=40000,"Med","Low"))) -> High | K4: =dataset[[#This Row],[soda_sales]]/dataset[[#This Row],[soda_units_sold]] -> 0.7272752 | L4: =dataset[[#This Row],[implied_soda_ppu]]-dataset[[#This Row],[soda_ppu]] -> -2.4802369e-05 | M4: =dataset[[#This Row],[soda_sales]]/dataset[[#This Row],[total_sales]] -> 0.047768266 | N4: =LN(dataset[[#This Row],[soda_units_sold]]) -> 12.128473 | O4: =LN(dataset[[#This Row],[soda_sales]]) -> 11.810023 | P4: =LN(dataset[[#This Row],[soda_ppu]]) -> -0.31841623 | Q4: =IF(dataset[[#This Row],[state]]="VA",1,0) -> 0
A5: 202204 | B5: 2 | C5: 2944587.7 | D5: 0.737 | E5: 210840 | F5: 155395.96 | G5: 20024 | H5: DC | I5: =HLOOKUP(G5,zip_tiers!$A$1:$EON$2,2,FALSE) -> 102576 | J5: =IF(I5="","No Data",IF(I5>=100000,"High",IF(I5>=40000,"Med","Low"))) -> High | K5: =dataset[[#This Row],[soda_sales]]/dataset[[#This Row],[soda_units_sold]] -> 0.73703265 | L5: =dataset[[#This Row],[implied_soda_ppu]]-dataset[[#This Row],[soda_ppu]] -> 3.2645608e-05 | M5: =dataset[[#This Row],[soda_sales]]/dataset[[#This Row],[total_sales]] -> 0.052773419 | N5: =LN(dataset[[#This Row],[soda_units_sold]]) -> 12.258855 | O5: =LN(dataset[[#This Row],[soda_sales]]) -> 11.953732 | P5: =LN(dataset[[#This Row],[soda_ppu]]) -> -0.30516739 | Q5: =IF(dataset[[#This Row],[state]]="VA",1,0) -> 0
A6: 202205 | B6: 2 | C6: 3068859.8 | D6: 0.7225 | E6: 232179 | F6: 167743.05 | G6: 20024 | H6: DC | I6: =HLOOKUP(G6,zip_tiers!$A$1:$EON$2,2,FALSE) -> 102576 | J6: =IF(I6="","No Data",IF(I6>=100000,"High",IF(I6>=40000,"Med","Low"))) -> High | K6: =dataset[[#This Row],[soda_sales]]/dataset[[#This Row],[soda_units_sold]] -> 0.72247295 | L6: =dataset[[#This Row],[implied_soda_ppu]]-dataset[[#This Row],[soda_ppu]] -> -2.705025e-05 | M6: =dataset[[#This Row],[soda_sales]]/dataset[[#This Row],[total_sales]] -> 0.05465973 | N6: =LN(dataset[[#This Row],[soda_units_sold]]) -> 12.355264 | O6: =LN(dataset[[#This Row],[soda_sales]]) -> 12.030189 | P6: =LN(dataset[[#This Row],[soda_ppu]]) -> -0.32503786 | Q6: =IF(dataset[[#This Row],[state]]="VA",1,0) -> 0
A7: 202206 | B7: 2 | C7: 2997245.4 | D7: 0.694 | E7: 250867 | F7: 174091.2 | G7: 20024 | H7: DC | I7: =HLOOKUP(G7,zip_tiers!$A$1:$EON$2,2,FALSE) -> 102576 | J7: =IF(I7="","No Data",IF(I7>=100000,"High",IF(I7>=40000,"Med","Low"))) -> High | K7: =dataset[[#This Row],[soda_sales]]/dataset[[#This Row],[soda_units_sold]] -> 0.69395817 | L7: =dataset[[#This Row],[implied_soda_ppu]]-dataset[[#This Row],[soda_ppu]] -> -4.1834119e-05 | M7: =dataset[[#This Row],[soda_sales]]/dataset[[#This Row],[total_sales]] -> 0.058083734 | N7: =LN(dataset[[#This Row],[soda_units_sold]]) -> 12.432678 | O7: =LN(dataset[[#This Row],[soda_sales]]) -> 12.067335 | P7: =LN(dataset[[#This Row],[soda_ppu]]) -> -0.36528332 | Q7: =IF(dataset[[#This Row],[state]]="VA",1,0) -> 0
A8: 202207 | B8: 2 | C8: 2849718.7 | D8: 0.7117 | E8: 256267 | F8: 182384.29 | G8: 20024 | H8: DC | I8: =HLOOKUP(G8,zip_tiers!$A$1:$EON$2,2,FALSE) -> 102576 | J8: =IF(I8="","No Data",IF(I8>=100000,"High",IF(I8>=40000,"Med","Low"))) -> High | K8: =dataset[[#This Row],[soda_sales]]/dataset[[#This Row],[soda_units_sold]] -> 0.71169636 | L8: =dataset[[#This Row],[implied_soda_ppu]]-dataset[[#This Row],[soda_ppu]] -> -3.6434656e-06 | M8: =dataset[[#This Row],[soda_sales]]/dataset[[#This Row],[total_sales]] -> 0.064000804 | N8: =LN(dataset[[#This Row],[soda_units_sold]]) -> 12.453975 | O8: =LN(dataset[[#This Row],[soda_sales]]) -> 12.113871 | P8: =LN(dataset[[#This Row],[soda_ppu]]) -> -0.3400988 | Q8: =IF(dataset[[#This Row],[state]]="VA",1,0) -> 0
A9: 202208 | B9: 2 | C9: 2668677.8 | D9: 0.7081 | E9: 224536 | F9: 158994.89 | G9: 20024 | H9: DC | I9: =HLOOKUP(G9,zip_tiers!$A$1:$EON$2,2,FALSE) -> 102576 | J9: =IF(I9="","No Data",IF(I9>=100000,"High",IF(I9>=40000,"Med","Low"))) -> High | K9: =dataset[[#This Row],[soda_sales]]/dataset[[#This Row],[soda_units_sold]] -> 0.70810423 | L9: =dataset[[#This Row],[implied_soda_ppu]]-dataset[[#This Row],[soda_ppu]] -> 4.2287206e-06 | M9: =dataset[[#This Row],[soda_sales]]/dataset[[#This Row],[total_sales]] -> 0.059578153 | N9: =LN(dataset[[#This Row],[soda_units_sold]]) -> 12.321791 | O9: =LN(dataset[[#This Row],[soda_sales]]) -> 11.976627 | P9: =LN(dataset[[#This Row],[soda_ppu]]) -> -0.34516995 | Q9: =IF(dataset[[#This Row],[state]]="VA",1,0) -> 0
A10: 202209 | B10: 2 | C10: 2698851 | D10: 0.6967 | E10: 219688 | F10: 153048.59 | G10: 20024 | H10: DC | I10: =HLOOKUP(G10,zip_tiers!$A$1:$EON$2,2,FALSE) -> 102576 | J10: =IF(I10="","No Data",IF(I10>=100000,"High",IF(I10>=40000,"Med","Low"))) -> High | K10: =dataset[[#This Row],[soda_sales]]/dataset[[#This Row],[soda_units_sold]] -> 0.69666339 | L10: =dataset[[#This Row],[implied_soda_ppu]]-dataset[[#This Row],[soda_ppu]] -> -3.6613288e-05 | M10: =dataset[[#This Row],[soda_sales]]/dataset[[#This Row],[total_sales]] -> 0.056708795 | N10: =LN(dataset[[#This Row],[soda_units_sold]]) -> 12.299964 | O10: =LN(dataset[[#This Row],[soda_sales]]) -> 11.938511 | P10: =LN(dataset[[#This Row],[soda_ppu]]) -> -0.36140038 | Q10: =IF(dataset[[#This Row],[state]]="VA",1,0) -> 0
A11: 202210 | B11: 2 | C11: 3295612.1 | D11: 0.7044 | E11: 204975 | F11: 144374.91 | G11: 20024 | H11: DC | I11: =HLOOKUP(G11,zip_tiers!$A$1:$EON$2,2,FALSE) -> 102576 | J11: =IF(I11="","No Data",IF(I11>=100000,"High",IF(I11>=40000,"Med","Low"))) -> High | K11: =dataset[[#This Row],[soda_sales]]/dataset[[#This Row],[soda_units_sold]] -> 0.70435375 | L11: =dataset[[#This Row],[implied_soda_ppu]]-dataset[[#This Row],[soda_ppu]] -> -4.625247e-05 | M11: =dataset[[#This Row],[soda_sales]]/dataset[[#This Row],[total_sales]] -> 0.043808223 | N11: =LN(dataset[[#This Row],[soda_units_sold]]) -> 12.230643 | O11: =LN(dataset[[#This Row],[soda_sales]]) -> 11.880169 | P11: =LN(dataset[[#This Row],[soda_ppu]]) -> -0.3504089 | Q11: =IF(dataset[[#This Row],[state]]="VA",1,0) -> 0
A12: 202211 | B12: 2 | C12: 3678381.8 | D12: 0.6815 | E12: 195505 | F12: 133237.72 | G12: 20024 | H12: DC | I12: =HLOOKUP(G12,zip_tiers!$A$1:$EON$2,2,FALSE) -> 102576 | J12: =IF(I12="","No Data",IF(I12>=100000,"High",IF(I12>=40000,"Med","Low"))) -> High | K12: =dataset[[#This Row],[soda_sales]]/dataset[[#This Row],[soda_units_sold]] -> 0.68150545 | L12: =dataset[[#This Row],[implied_soda_ppu]]-dataset[[#This Row],[soda_ppu]] -> 5.445385e-06 | M12: =dataset[[#This Row],[soda_sales]]/dataset[[#This Row],[total_sales]] -> 0.03622183 | N12: =LN(dataset[[#This Row],[soda_units_sold]]) -> 12.183341 | O12: =LN(dataset[[#This Row],[soda_sales]]) -> 11.79989 | P12: =LN(dataset[[#This Row],[soda_ppu]]) -> -0.38345903 | Q12: =IF(dataset[[#This Row],[state]]="VA",1,0) -> 0
A13: 202212 | B13: 2 | C13: 3888052.5 | D13: 0.7178 | E13: 187306 | F13: 134449.84 | G13: 20024 | H13: DC | I13: =HLOOKUP(G13,zip_tiers!$A$1:$EON$2,2,FALSE) -> 102576 | J13: =IF(I13="","No Data",IF(I13>=100000,"High",IF(I13>=40000,"Med","Low"))) -> High | K13: =dataset[[#This Row],[soda_sales]]/dataset[[#This Row],[soda_units_sold]] -> 0.71780851 | L13: =dataset[[#This Row],[implied_soda_ppu]]-dataset[[#This Row],[soda_ppu]] -> 8.512274e-06 | M13: =dataset[[#This Row],[soda_sales]]/dataset[[#This Row],[total_sales]] -> 0.034580254 | N13: =LN(dataset[[#This Row],[soda_units_sold]]) -> 12.140499 | O13: =LN(dataset[[#This Row],[soda_sales]]) -> 11.808946 | P13: =LN(dataset[[#This Row],[soda_ppu]]) -> -0.3315643 | Q13: =IF(dataset[[#This Row],[state]]="VA",1,0) -> 0
... A3601: 202412 | B3601: 30 | C3601: 3112228.8 | D3601: 0.7133 | E3601: 216190 | F3601: 154212.48 | G3601: 31830 | H3601: GA | I3601: =HLOOKUP(G3601,zip_tiers!$A$1:$EON$2,2,FALSE) -> 59536.333 | J3601: =IF(I3601="","No Data",IF(I3601>=100000,"High",IF(I3601>=40000,"Med","Low"))) -> Med | K3601: =dataset[[#This Row],[soda_sales]]/dataset[[#This Row],[soda_units_sold]] -> 0.71331922 | L3601: =dataset[[#This Row],[implied_soda_ppu]]-dataset[[#This Row],[soda_ppu]] -> 1.9221056e-05 | M3601: =dataset[[#This Row],[soda_sales]]/dataset[[#This Row],[total_sales]] -> 0.049550496 | N3601: =LN(dataset[[#This Row],[soda_units_sold]]) -> 12.283913 | O3601: =LN(dataset[[#This Row],[soda_sales]]) -> 11.946087 | P3601: =LN(dataset[[#This Row],[soda_ppu]]) -> -0.33785319 | Q3601: =IF(dataset[[#This Row],[state]]="VA",1,0) -> 0

Sheet Data Dictionary
B2: Column | C2: Data Type | D2: Description
A3: stores Table | B3: store_id | C3: number | D3: unique number for each individual store
B4: zip | C4: number | D4: zip code store is located in
B5: state | C5: number | D5: state store is located in
A6: total_sales; soda_ppu; soda_units_sold; soda_sales | B6: year_month | C6: number | D6: number representing the date in yyyymm format
B7: total_sales_X | C7: dollars | D7: the dollar value of all sales (soda + all other sales) in that year_month for store_id "X"
B8: soda_ppu_X | C8: dollars | D8: the price per unit of soda in that year_month for store_id "X"
B9: soda_units_sold | C9: number | D9: the number of soda units sold in that year_month for store_id "X"
B10: soda_sales | C10: dollars | D10: the dollar value of the soda sold in that year_month for store_id "X"
A11: zip_med_income | B11: year | C11: string | D11: label to denote year median income is measured in
B12: 20001 | C12: number | D12: median income for zip code 20001
B13: 20002 | C13: number | D13: median income for zip code 20002
B14: … | C14: … | D14: …

Sheet total_sales
A1: year_month | B1: total_sales_1 | C1: total_sales_2 | D1: total_sales_3 | E1: total_sales_4 | F1: total_sales_5 | G1: total_sales_6 | H1: total_sales_7 | I1: total_sales_8 | J1: total_sales_9 | K1: total_sales_10 | L1: total_sales_11 | M1: total_sales_12 | N1: total_sales_13 | O1: total_sales_14 | P1: total_sales_15 | Q1: total_sales_16 | R1: total_sales_17 | S1: total_sales_18 | T1: total_sales_19 | U1: total_sales_20 | V1: total_sales_21 | W1: total_sales_22 | X1: total_sales_23 | Y1: total_sales_24 | Z1: total_sales_25 | AA1: total_sales_26 | AB1: total_sales_27 | AC1: total_sales_28 | AD1: total_sales_29 | AE1: total_sales_30 | AF1: total_sales_31 | AG1: total_sales_32 | AH1: total_sales_33 | AI1: total_sales_34 | AJ1: total_sales_35 | AK1: total_sales_36 | AL1: total_sales_37 | AM1: total_sales_38 | AN1: total_sales_39 | AO1: total_sales_40 | AP1: total_sales_41 | AQ1: total_sales_42 | AR1: total_sales_43 | AS1: total_sales_44 | AT1: total_sales_45 | AU1: total_sales_46 | AV1: total_sales_47 | AW1: total_sales_48 | AX1: total_sales_49 | AY1: total_sales_50 | AZ1: total_sales_51 | BA1: total_sales_52 | BB1: total_sales_53 | BC1: total_sales_54 | BD1: total_sales_55 | BE1: total_sales_56 | BF1: total_sales_57 | BG1: total_sales_58 | BH1: total_sales_59 | BI1: total_sales_60 | BJ1: total_sales_61 | BK1: total_sales_62 | BL1: total_sales_63 | BM1: total_sales_64 | BN1: total_sales_65 | BO1: total_sales_66 | BP1: total_sales_67 | BQ1: total_sales_68 | BR1: total_sales_69 | BS1: total_sales_70 | BT1: total_sales_71 | BU1: total_sales_72 | BV1: total_sales_73 | BW1: total_sales_74 | BX1: total_sales_75 | BY1: total_sales_76 | BZ1: total_sales_77 | CA1: total_sales_78 | CB1: total_sales_79 | CC1: total_sales_80 | CD1: total_sales_81 | CE1: total_sales_82 | CF1: total_sales_83 | CG1: total_sales_84 | CH1: total_sales_85 | CI1: total_sales_86 | CJ1: total_sales_87 | CK1: total_sales_88 | CL1: total_sales_89 | CM1: total_sales_90 | CN1: total_sales_91 | CO1: total_sales_92 | CP1: total_sales_93 | CQ1: total_sales_94 | CR1: total_sales_95 | CS1: total_sales_96 | CT1: total_sales_97 | CU1: total_sales_98 | CV1: total_sales_99 | CW1: total_sales_100
A2: 202201 | B2: 1918181.5 | C2: 2267236.9 | D2: 1936059 | E2: 2355901 | F2: 1877559.7 | G2: 2518868.5 | H2: 1631645.2 | I2: 2482271.3 | J2: 2328416.9 | K2: 1898096.7 | L2: 1391497 | M2: 1929318 | N2: 1650728.5 | O2: 2466696.9 | P2: 1714478.2 | Q2: 1674037.6 | R2: 2379214.1 | S2: 1727107.2 | T2: 1665354.2 | U2: 1467281.6 | V2: 1626935.2 | W2: 2507622 | X2: 1561739.3 | Y2: 1957889.3 | Z2: 1945290.7 | AA2: 1413960.4 | AB2: 1818445.3 | AC2: 1911686.8 | AD2: 2098174.9 | AE2: 1742083.4 | AF2: 1899846.3 | AG2: 1887557 | AH2: 1932495.6 | AI2: 2116639.9 | AJ2: 2279516.4 | AK2: 2249461.4 | AL2: 1874357.4 | AM2: 2674828 | AN2: 1767435.9 | AO2: 1856748.1 | AP2: 1760525.4 | AQ2: 1762955.7 | AR2: 1718735.3 | AS2: 1440151.6 | AT2: 1695219.6 | AU2: 1432703.8 | AV2: 1570846 | AW2: 1662034.5 | AX2: 1895261.4 | AY2: 1758796.8 | AZ2: 3277567.3 | BA2: 2659094.6 | BB2: 2028184.5 | BC2: 1396619.6 | BD2: 2225321.2 | BE2: 1768734.3 | BF2: 1858919.3 | BG2: 1871379.1 | BH2: 2007257.1 | BI2: 1997708.2 | BJ2: 2045027.6 | BK2: 2085999.9 | BL2: 1330328.5 | BM2: 1603264.7 | BN2: 1919092.9 | BO2: 1773539.7 | BP2: 1912596.4 | BQ2: 2432408.5 | BR2: 1985816.3 | BS2: 1926310.4 | BT2: 2575808.8 | BU2: 1724337.6 | BV2: 2126381 | BW2: 1817862.3 | BX2: 1721795.5 | BY2: 1935362.3 | BZ2: 1892382.5 | CA2: 1644087.3 | CB2: 1857660.1 | CC2: 1542271.9 | CD2: 2837392.2 | CE2: 1508480.2 | CF2: 2203432.6 | CG2: 2417628.2 | CH2: 2084651.8 | CI2: 1709423.3 | CJ2: 2676188.8 | CK2: 2435666.8 | CL2: 1858100.7 | CM2: 1672995.1 | CN2: 1964903.1 | CO2: 2594737.9 | CP2: 2083010.1 | CQ2: 1628877.6 | CR2: 1658072.6 | CS2: 1804189 | CT2: 1288201 | CU2: 1930571.5 | CV2: 2012386.9 | CW2: 2998267.7
A3: 202202 | B3: 2127771.7 | C3: 2508276.2 | D3: 2257774.7 | E3: 2626955.6 | F3: 2126141.8 | G3: 2828153.8 | H3: 1870481.2 | I3: 2834105.8 | J3: 2741429 | K3: 2124992.1 | L3: 1574979.1 | M3: 2191313.5 | N3: 1884325.9 | O3: 2811060.3 | P3: 1938706.7 | Q3: 1924202.8 | R3: 2709671.5 | S3: 1965476.2 | T3: 1898975.6 | U3: 1679203.9 | V3: 1913434.8 | W3: 2851829.9 | X3: 1780467.3 | Y3: 2198282 | Z3: 2231723.1 | AA3: 1606409.7 | AB3: 2060995.8 | AC3: 2105531.9 | AD3: 2418069 | AE3: 1966794.9 | AF3: 2144490.2 | AG3: 2194195 | AH3: 2210465.2 | AI3: 2408147 | AJ3: 2562367.4 | AK3: 2525011.2 | AL3: 2154861.2 | AM3: 3067949.9 | AN3: 2001621.8 | AO3: 2107375.1 | AP3: 1965594.8 | AQ3: 1982118.6 | AR3: 1970337.8 | AS3: 1608490.3 | AT3: 1928206.4 | AU3: 1627678.7 | AV3: 1754994.6 | AW3: 1869152.5 | AX3: 2173191.4 | AY3: 1990766.6 | AZ3: 3661260.2 | BA3: 3015362.3 | BB3: 2310524.2 | BC3: 1569845.7 | BD3: 2535279.4 | BE3: 2043084.2 | BF3: 2120710.3 | BG3: 2121672.9 | BH3: 2282062.4 | BI3: 2282360 | BJ3: 2335708.8 | BK3: 2337107.5 | BL3: 1514321.5 | BM3: 1886831.4 | BN3: 2147694.2 | BO3: 2016814.4 | BP3: 2174073.9 | BQ3: 2792798.4 | BR3: 2203527 | BS3: 2195155.8 | BT3: 2981537 | BU3: 1911757.2 | BV3: 2410610.4 | BW3: 2035259.3 | BX3: 1934469.7 | BY3: 2185666 | BZ3: 2184074 | CA3: 1910017.5 | CB3: 2110544.3 | CC3: 1708670.2 | CD3: 3273545.9 | CE3: 1733024.5 | CF3: 2485558.2 | CG3: 2721628.5 | CH3: 2397697.1 | CI3: 1959958.8 | CJ3: 3032613.4 | CK3: 2779719.2 | CL3: 2146476.2 | CM3: 1894664.1 | CN3: 2288274.5 | CO3: 2959620 | CP3: 2383726.8 | CQ3: 1841829.3 | CR3: 1916653.5 | CS3: 2048358.1 | CT3: 1447274.9 | CU3: 2172634.1 | CV3: 2282559.2 | CW3: 3347414.8
A4: 202203 | B4: 2380487.2 | C4: 2817658.1 | D4: 2446409 | E4: 2899987 | F4: 2372091.1 | G4: 3156156.6 | H4: 2105437.2 | I4: 3148534.3 | J4: 2954968.2 | K4: 2364557.4 | L4: 1762024 | M4: 2436382.9 | N4: 2122581.7 | O4: 3050868.7 | P4: 2186011.3 | Q4: 2124567.8 | R4: 2993379.4 | S4: 2198356.4 | T4: 2095833.8 | U4: 1897726.1 | V4: 2104792.7 | W4: 3231600 | X4: 1920981.1 | Y4: 2423952.9 | Z4: 2471673 | AA4: 1814356.5 | AB4: 2309362.3 | AC4: 2347111.3 | AD4: 2706212 | AE4: 2229098.9 | AF4: 2401574.5 | AG4: 2397552.1 | AH4: 2498221.9 | AI4: 2662483.6 | AJ4: 2846266.3 | AK4: 2774744.5 | AL4: 2365561.1 | AM4: 3454980.9 | AN4: 2251005.8 | AO4: 2346322.9 | AP4: 2174025.6 | AQ4: 2214672 | AR4: 2190388.5 | AS4: 1779865 | AT4: 2173819.1 | AU4: 1802518.2 | AV4: 1994084.9 | AW4: 2110806.4 | AX4: 2417236.7 | AY4: 2217310.5 | AZ4: 4097025.7 | BA4: 3389808.4 | BB4: 2565107.9 | BC4: 1741140.3 | BD4: 2912657.2 | BE4: 2280571.8 | BF4: 2399861.8 | BG4: 2369204.3 | BH4: 2523945 | BI4: 2534931.3 | BJ4: 2592545 | BK4: 2641795.5 | BL4: 1664921.8 | BM4: 2109151.3 | BN4: 2416129.9 | BO4: 2239871.3 | BP4: 2429229.7 | BQ4: 3143504.7 | BR4: 2451357.5 | BS4: 2462174.7 | BT4: 3361366.8 | BU4: 2149472.3 | BV4: 2652503 | BW4: 2225275.8 | BX4: 2198714.7 | BY4: 2455730.2 | BZ4: 2421051.6 | CA4: 2151228.9 | CB4: 2353456.1 | CC4: 1983718.6 | CD4: 3675555.6 | CE4: 1932290.6 | CF4: 2768761.5 | CG4: 2970174.4 | CH4: 2613810.2 | CI4: 2146633.8 | CJ4: 3342016.4 | CK4: 3040907.1 | CL4: 2377255.3 | CM4: 2065880.9 | CN4: 2543127 | CO4: 3313481.2 | CP4: 2666526.9 | CQ4: 2103120.1 | CR4: 2098894.1 | CS4: 2289521.9 | CT4: 1587708.6 | CU4: 2399906.7 | CV4: 2530330.1 | CW4: 3692944.8
A5: 202204 | B5: 2497642.7 | C5: 2944587.7 | D5: 2638192.3 | E5: 3035344.1 | F5: 2535190.1 | G5: 3338951.2 | H5: 2197263.8 | I5: 3356510.4 | J5: 3134744.8 | K5: 2501616.2 | L5: 1807415 | M5: 2603263.9 | N5: 2212942.2 | O5: 3297164.4 | P5: 2273348.8 | Q5: 2223268.3 | R5: 3172039.5 | S5: 2296150.4 | T5: 2213841 | U5: 1978169.3 | V5: 2190563.5 | W5: 3347786.5 | X5: 2074847.5 | Y5: 2601571.1 | Z5: 2577446.7 | AA5: 1915666.3 | AB5: 2383293.6 | AC5: 2494943.5 | AD5: 2828674.7 | AE5: 2274437.6 | AF5: 2488336.4 | AG5: 2578003.7 | AH5: 2589052.8 | AI5: 2858293.3 | AJ5: 3005773.7 | AK5: 2955976.4 | AL5: 2518456.3 | AM5: 3634635.9 | AN5: 2334865.2 | AO5: 2476520.1 | AP5: 2315444.7 | AQ5: 2307524.1 | AR5: 2327710.8 | AS5: 1883654.5 | AT5: 2298837 | AU5: 1921746.1 | AV5: 2109071.4 | AW5: 2234872.2 | AX5: 2573284.3 | AY5: 2315571.6 | AZ5: 4430923.5 | BA5: 3553748 | BB5: 2720414.4 | BC5: 1840318.5 | BD5: 2990920.3 | BE5: 2404126.2 | BF5: 2496029.9 | BG5: 2506127.7 | BH5: 2718372.6 | BI5: 2731926.6 | BJ5: 2675481.5 | BK5: 2791036.9 | BL5: 1766746.4 | BM5: 2172175 | BN5: 2534011.6 | BO5: 2366434 | BP5: 2573532.8 | BQ5: 3329712.7 | BR5: 2579707.4 | BS5: 2596668.1 | BT5: 3495226.9 | BU5: 2266956.6 | BV5: 2776353.8 | BW5: 2408953.6 | BX5: 2293471.1 | BY5: 2558356.3 | BZ5: 2610897.5 | CA5: 2187069.6 | CB5: 2473141.7 | CC5: 2057322.7 | CD5: 3831699.4 | CE5: 2017267.8 | CF5: 2949658.2 | CG5: 3138722 | CH5: 2777055.2 | CI5: 2332495.5 | CJ5: 3581723 | CK5: 3238857.3 | CL5: 2521944.1 | CM5: 2159180.3 | CN5: 2644970.3 | CO5: 3476663 | CP5: 2762183 | CQ5: 2175664.6 | CR5: 2237744.3 | CS5: 2415373.3 | CT5: 1666788.7 | CU5: 2528771.7 | CV5: 2691342.6 | CW5: 3926277.3
A6: 202205 | B6: 2665976.4 | C6: 3068859.8 | D6: 2724099.7 | E6: 3238806.1 | F6: 2615638.9 | G6: 3498835.9 | H6: 2307180.8 | I6: 3513105.7 | J6: 3262760.9 | K6: 2590016.6 | L6: 1957391.2 | M6: 2721310.9 | N6: 2321619.1 | O6: 3395847.6 | P6: 2387957.5 | Q6: 2360196.1 | R6: 3354540.2 | S6: 2411142.8 | T6: 2348535.8 | U6: 2051330.5 | V6: 2327818.5 | W6: 3563809.2 | X6: 2101667.3 | Y6: 2738109.3 | Z6: 2746784.7 | AA6: 1997996.6 | AB6: 2507198.1 | AC6: 2597653.4 | AD6: 2980395.5 | AE6: 2412349.2 | AF6: 2617120.7 | AG6: 2685518.5 | AH6: 2730707.9 | AI6: 2956801.6 | AJ6: 3180786.4 | AK6: 3129299.5 | AL6: 2637191.7 | AM6: 3846661.5 | AN6: 2440756 | AO6: 2597556.8 | AP6: 2403912.2 | AQ6: 2436471.7 | AR6: 2430267.7 | AS6: 1961041.7 | AT6: 2445522.7 | AU6: 2011844.1 | AV6: 2251372.4 | AW6: 2348850.1 | AX6: 2611681 | AY6: 2434760.7 | AZ6: 4552418.1 | BA6: 3688600.8 | BB6: 2786595.7 | BC6: 1977550.3 | BD6: 3163228.9 | BE6: 2477636.6 | BF6: 2581323.5 | BG6: 2540513.7 | BH6: 2748332.4 | BI6: 2820361.4 | BJ6: 2889431.5 | BK6: 2928177.3 | BL6: 1841162.3 | BM6: 2294025.6 | BN6: 2635503.5 | BO6: 2488297.4 | BP6: 2698462.5 | BQ6: 3439333.1 | BR6: 2722563.8 | BS6: 2733127.8 | BT6: 3622417.3 | BU6: 2405687 | BV6: 3035285.6 | BW6: 2500724.1 | BX6: 2363051.8 | BY6: 2699274.9 | BZ6: 2716038.7 | CA6: 2373727 | CB6: 2625847.8 | CC6: 2138717.5 | CD6: 4054520.6 | CE6: 2127923.9 | CF6: 3052238.4 | CG6: 3369078.9 | CH6: 2942385.3 | CI6: 2412272.3 | CJ6: 3808479 | CK6: 3386765 | CL6: 2634405.4 | CM6: 2308833.7 | CN6: 2780034.8 | CO6: 3633499.3 | CP6: 2968782.7 | CQ6: 2253012.2 | CR6: 2356350.5 | CS6: 2542649.2 | CT6: 1783878.3 | CU6: 2709608.5 | CV6: 2793337.9 | CW6: 4155823
A7: 202206 | B7: 2481630.6 | C7: 2997245.4 | D7: 2680801.5 | E7: 3064833.4 | F7: 2477077.7 | G7: 3305643.1 | H7: 2199562.5 | I7: 3257553.6 | J7: 3101837.4 | K7: 2502722.1 | L7: 1820591.5 | M7: 2561316.1 | N7: 2176319.9 | O7: 3264788.8 | P7: 2274842.8 | Q7: 2196246.3 | R7: 3196074 | S7: 2295316.6 | T7: 2236524.5 | U7: 1944100.1 | V7: 2233274.7 | W7: 3355514.1 | X7: 2024853.2 | Y7: 2584243.6 | Z7: 2554140.1 | AA7: 1927719.1 | AB7: 2417197.7 | AC7: 2471230.2 | AD7: 2785764.9 | AE7: 2310477.9 | AF7: 2560431.5 | AG7: 2569818.5 | AH7: 2588096.6 | AI7: 2805620.2 | AJ7: 2987143.8 | AK7: 3014636.3 | AL7: 2513102.8 | AM7: 3625095.4 | AN7: 2343321.8 | AO7: 2473837.9 | AP7: 2293803.8 | AQ7: 2337852.3 | AR7: 2260572.1 | AS7: 1861041.5 | AT7: 2296220.1 | AU7: 1954380.5 | AV7: 2169279.9 | AW7: 2227829.4 | AX7: 2544098.5 | AY7: 2257158.1 | AZ7: 4371921.6 | BA7: 3504939.4 | BB7: 2678703.4 | BC7: 1852565.4 | BD7: 2968917.8 | BE7: 2388951.4 | BF7: 2521286.2 | BG7: 2452418.7 | BH7: 2702669.7 | BI7: 2673203.5 | BJ7: 2801880.5 | BK7: 2793018.3 | BL7: 1748271.3 | BM7: 2187196.9 | BN7: 2524696.8 | BO7: 2350459.2 | BP7: 2585788.6 | BQ7: 3332450.3 | BR7: 2562415.7 | BS7: 2567994.8 | BT7: 3508922.4 | BU7: 2226152.9 | BV7: 2847793.7 | BW7: 2407838.7 | BX7: 2303838 | BY7: 2593083.1 | BZ7: 2559635.1 | CA7: 2199293 | CB7: 2454314 | CC7: 2076062.2 | CD7: 3862362.4 | CE7: 2046418.6 | CF7: 2934365.4 | CG7: 3212977.5 | CH7: 2748889 | CI7: 2284622.1 | CJ7: 3638575.4 | CK7: 3238337.2 | CL7: 2468506.1 | CM7: 2175844.3 | CN7: 2684322 | CO7: 3526593.4 | CP7: 2742700.6 | CQ7: 2199370.8 | CR7: 2262584 | CS7: 2417301.5 | CT7: 1675554.2 | CU7: 2539007.6 | CV7: 2706707 | CW7: 3997580.8
A8: 202207 | B8: 2434362.5 | C8: 2849718.7 | D8: 2495053.6 | E8: 2927792.6 | F8: 2330424.4 | G8: 3167383.8 | H8: 2092135.5 | I8: 3151825.8 | J8: 3008019.9 | K8: 2378917.6 | L8: 1771786.3 | M8: 2440781.5 | N8: 2109451.1 | O8: 3065602.8 | P8: 2200755.2 | Q8: 2137681.6 | R8: 3051336.7 | S8: 2184914 | T8: 2112146.8 | U8: 1886236 | V8: 2087733.5 | W8: 3211209.8 | X8: 1973462.8 | Y8: 2469644.7 | Z8: 2451951.4 | AA8: 1794583.6 | AB8: 2321468.2 | AC8: 2369180.4 | AD8: 2669473.2 | AE8: 2184112.2 | AF8: 2437029.4 | AG8: 2471140.1 | AH8: 2474594.6 | AI8: 2680006.9 | AJ8: 2931469.7 | AK8: 2836238.4 | AL8: 2364057.4 | AM8: 3500324.4 | AN8: 2290553.8 | AO8: 2380326.2 | AP8: 2227849.8 | AQ8: 2181495.5 | AR8: 2142310.2 | AS8: 1764717 | AT8: 2148423.8 | AU8: 1840887.2 | AV8: 2042603.5 | AW8: 2091323.1 | AX8: 2399526.5 | AY8: 2211380.3 | AZ8: 4086873.6 | BA8: 3389938.6 | BB8: 2564422.4 | BC8: 1749448.8 | BD8: 2891666.1 | BE8: 2279025.6 | BF8: 2334270.1 | BG8: 2367650.8 | BH8: 2523068.7 | BI8: 2556664.8 | BJ8: 2617408 | BK8: 2737645.8 | BL8: 1694846.2 | BM8: 2130490.1 | BN8: 2392398.4 | BO8: 2225283.9 | BP8: 2482666.4 | BQ8: 3157170.7 | BR8: 2462177 | BS8: 2481928.5 | BT8: 3263849.8 | BU8: 2155075 | BV8: 2618938 | BW8: 2257882.1 | BX8: 2143951.3 | BY8: 2468397.7 | BZ8: 2439037 | CA8: 2124211.3 | CB8: 2398701.5 | CC8: 1965307.1 | CD8: 3698347.5 | CE8: 1912217.7 | CF8: 2786156.5 | CG8: 3040788.3 | CH8: 2672013.5 | CI8: 2221605.3 | CJ8: 3470565.6 | CK8: 3076935 | CL8: 2388115.8 | CM8: 2105436.9 | CN8: 2532885.8 | CO8: 3316682.7 | CP8: 2636528.6 | CQ8: 2059421.2 | CR8: 2109260.6 | CS8: 2283225.6 | CT8: 1603185.9 | CU8: 2435526.1 | CV8: 2613023.5 | CW8: 3738994.6
A9: 202208 | B9: 2301597.3 | C9: 2668677.8 | D9: 2405479.9 | E9: 2780943.6 | F9: 2219309.5 | G9: 3030109 | H9: 2019802.7 | I9: 3070248.2 | J9: 2805308.5 | K9: 2228302.2 | L9: 1668999 | M9: 2350994.8 | N9: 2035375.8 | O9: 2953270.4 | P9: 2064029.4 | Q9: 2022399 | R9: 2871065.2 | S9: 2060157.8 | T9: 1996196.2 | U9: 1815487.4 | V9: 1978992.7 | W9: 3061682.6 | X9: 1877223 | Y9: 2334569.1 | Z9: 2345862.4 | AA9: 1729876.8 | AB9: 2203809.1 | AC9: 2277536.8 | AD9: 2560974.1 | AE9: 2114374.7 | AF9: 2246063.1 | AG9: 2307065.4 | AH9: 2366787.5 | AI9: 2551668.8 | AJ9: 2698227.2 | AK9: 2688312.2 | AL9: 2267123 | AM9: 3262830.5 | AN9: 2158698.7 | AO9: 2253239 | AP9: 2099729.7 | AQ9: 2105670.6 | AR9: 2074310.7 | AS9: 1699104 | AT9: 2054243 | AU9: 1735050.5 | AV9: 1938352.5 | AW9: 1988777.8 | AX9: 2295590.5 | AY9: 2063935.7 | AZ9: 3893975.2 | BA9: 3223261.8 | BB9: 2455953.7 | BC9: 1702787.3 | BD9: 2705138.1 | BE9: 2163130.7 | BF9: 2282291.5 | BG9: 2249800.8 | BH9: 2425861.3 | BI9: 2466236.5 | BJ9: 2532792.3 | BK9: 2556841.4 | BL9: 1576281.1 | BM9: 1980119.2 | BN9: 2275644.7 | BO9: 2142167.2 | BP9: 2360139.6 | BQ9: 2971093.2 | BR9: 2330402.7 | BS9: 2339227.1 | BT9: 3174431.4 | BU9: 2076826.4 | BV9: 2536201.5 | BW9: 2162087.4 | BX9: 2086500.2 | BY9: 2327396.5 | BZ9: 2340861.2 | CA9: 1986270 | CB9: 2244379.2 | CC9: 1871951.7 | CD9: 3478185.2 | CE9: 1868304.4 | CF9: 2598902.7 | CG9: 2878627.8 | CH9: 2506209 | CI9: 2091668.6 | CJ9: 3173008 | CK9: 2942702.2 | CL9: 2271072.5 | CM9: 1973025.2 | CN9: 2417708.7 | CO9: 3196693.1 | CP9: 2483393.1 | CQ9: 1983010 | CR9: 2036144.7 | CS9: 2200954.2 | CT9: 1540260.5 | CU9: 2292327.4 | CV9: 2425892.8 | CW9: 3597710.5
A10: 202209 | B10: 2291536.9 | C10: 2698851 | D10: 2360532.4 | E10: 2779739.8 | F10: 2233508.5 | G10: 3034079.7 | H10: 1986349.6 | I10: 2952876.7 | J10: 2829186 | K10: 2223770.1 | L10: 1624442.6 | M10: 2336864.4 | N10: 2017341.1 | O10: 2896670.5 | P10: 2105598.9 | Q10: 1991416.1 | R10: 2891853.2 | S10: 2063560.3 | T10: 2013097.6 | U10: 1827930.2 | V10: 2010005.8 | W10: 3026706.5 | X10: 1825637.6 | Y10: 2349764.3 | Z10: 2339434.7 | AA10: 1731545.3 | AB10: 2185903 | AC10: 2249313.5 | AD10: 2540600.1 | AE10: 2090716.7 | AF10: 2278546.9 | AG10: 2311793.3 | AH10: 2336129.8 | AI10: 2535794.6 | AJ10: 2699287.5 | AK10: 2707958.8 | AL10: 2270777.3 | AM10: 3225143.6 | AN10: 2108219.3 | AO10: 2223585.6 | AP10: 2088550.6 | AQ10: 2081187 | AR10: 2070928.2 | AS10: 1691431.3 | AT10: 2072271.3 | AU10: 1723059 | AV10: 1921648.1 | AW10: 2008294.9 | AX10: 2270680.9 | AY10: 2095699.2 | AZ10: 3924208.6 | BA10: 3244546.3 | BB10: 2434639.6 | BC10: 1662879.6 | BD10: 2715737.8 | BE10: 2137450.6 | BF10: 2217399 | BG10: 2224918.3 | BH10: 2451469.9 | BI10: 2450788.7 | BJ10: 2490969.4 | BK10: 2477062.7 | BL10: 1587644.8 | BM10: 1984706.1 | BN10: 2291855.5 | BO10: 2106087.6 | BP10: 2307982.3 | BQ10: 3048565.9 | BR10: 2388082.1 | BS10: 2324424.3 | BT10: 3119136.6 | BU10: 2009850.8 | BV10: 2532737.3 | BW10: 2189850 | BX10: 2071367.9 | BY10: 2284213.4 | BZ10: 2290189.6 | CA10: 2014444.2 | CB10: 2257380.9 | CC10: 1893618.1 | CD10: 3473139.2 | CE10: 1810517.6 | CF10: 2642510.6 | CG10: 2848690.4 | CH10: 2513817.2 | CI10: 2065177 | CJ10: 3245748.4 | CK10: 2953069.4 | CL10: 2207097.7 | CM10: 1999182.2 | CN10: 2431138.3 | CO10: 3171616.3 | CP10: 2469191.8 | CQ10: 1929394.9 | CR10: 1997113.4 | CS10: 2199161.6 | CT10: 1523257.3 | CU10: 2293456.4 | CV10: 2404328.4 | CW10: 3575896.8
A11: 202210 | B11: 2803750.5 | C11: 3295612.1 | D11: 2882393.7 | E11: 3421854.1 | F11: 2815750.4 | G11: 3742261.7 | H11: 2433664.4 | I11: 3705582.3 | J11: 3397741.6 | K11: 2770171.7 | L11: 2065648.7 | M11: 2854208.7 | N11: 2482666.7 | O11: 3608572.9 | P11: 2576277.7 | Q11: 2498859.8 | R11: 3561940.6 | S11: 2557579.2 | T11: 2394624.4 | U11: 2182373.1 | V11: 2418910 | W11: 3645278.9 | X11: 2273653.1 | Y11: 2917241.8 | Z11: 2857484.9 | AA11: 2067242 | AB11: 2697729.7 | AC11: 2735397 | AD11: 3140088 | AE11: 2557976 | AF11: 2790640.2 | AG11: 2849593 | AH11: 2847143.1 | AI11: 3127588.6 | AJ11: 3349673.1 | AK11: 3261367.3 | AL11: 2796748.9 | AM11: 3969354.1 | AN11: 2594082.7 | AO11: 2753714.8 | AP11: 2545674.4 | AQ11: 2564482.2 | AR11: 2540873.3 | AS11: 2069416.1 | AT11: 2528817.9 | AU11: 2107011.1 | AV11: 2360086.8 | AW11: 2459444.2 | AX11: 2800577.9 | AY11: 2563207.5 | AZ11: 4734713.5 | BA11: 3893621.4 | BB11: 2995891.7 | BC11: 2007638.7 | BD11: 3271135 | BE11: 2658237.1 | BF11: 2769147.8 | BG11: 2745172.4 | BH11: 2966027.1 | BI11: 2952490.3 | BJ11: 3007764.9 | BK11: 3088715.8 | BL11: 1974387.7 | BM11: 2464687.7 | BN11: 2776172.3 | BO11: 2643135.5 | BP11: 2819863 | BQ11: 3609758.6 | BR11: 2867454.8 | BS11: 2845494.4 | BT11: 3904504.2 | BU11: 2509761.1 | BV11: 3099955.7 | BW11: 2708915.3 | BX11: 2542382.8 | BY11: 2802738.7 | BZ11: 2826382.8 | CA11: 2414517.6 | CB11: 2740372.6 | CC11: 2314612.8 | CD11: 4334220.4 | CE11: 2222226.7 | CF11: 3219411.1 | CG11: 3517492.8 | CH11: 3056599.4 | CI11: 2503193.1 | CJ11: 3966910.8 | CK11: 3582525.7 | CL11: 2761570.6 | CM11: 2443764.6 | CN11: 2961535.3 | CO11: 3934784.8 | CP11: 3082130.8 | CQ11: 2439091 | CR11: 2484309.7 | CS11: 2709815 | CT11: 1875158.2 | CU11: 2827578.9 | CV11: 2976240.6 | CW11: 4418233.8
A12: 202211 | B12: 3106804.7 | C12: 3678381.8 | D12: 3359814 | E12: 3901767.3 | F12: 3153951.8 | G12: 4244388.6 | H12: 2800698.9 | I12: 4228518.7 | J12: 3941102.8 | K12: 3127944 | L12: 2313978.1 | M12: 3209905.1 | N12: 2773415.7 | O12: 4085370.7 | P12: 2932821.4 | Q12: 2778480.8 | R12: 3979871.3 | S12: 2928498.9 | T12: 2792518.7 | U12: 2495461.5 | V12: 2782480.8 | W12: 4237001.5 | X12: 2567036.5 | Y12: 3232500.5 | Z12: 3265221.3 | AA12: 2390309.1 | AB12: 3052203.3 | AC12: 3089711.3 | AD12: 3484987.2 | AE12: 2867444.6 | AF12: 3166787.4 | AG12: 3228833.9 | AH12: 3228395.6 | AI12: 3506286.4 | AJ12: 3723461.5 | AK12: 3741727.7 | AL12: 3113385.3 | AM12: 4601987.2 | AN12: 2977762.1 | AO12: 3155995.6 | AP12: 2832758 | AQ12: 2884198.1 | AR12: 2864354.8 | AS12: 2354538.5 | AT12: 2919782.8 | AU12: 2412256.7 | AV12: 2683765.3 | AW12: 2768831.3 | AX12: 3188125.2 | AY12: 2907775.4 | AZ12: 5356260.3 | BA12: 4462550.4 | BB12: 3443109.1 | BC12: 2323022.9 | BD12: 3826217.5 | BE12: 3010198.6 | BF12: 3082069.4 | BG12: 3145263.7 | BH12: 3364905 | BI12: 3408888.3 | BJ12: 3461705.3 | BK12: 3531947.3 | BL12: 2254961.9 | BM12: 2777951.8 | BN12: 3238461 | BO12: 2946521.4 | BP12: 3254620.9 | BQ12: 4232167.3 | BR12: 3303921 | BS12: 3292182.4 | BT12: 4320577.1 | BU12: 2904606.5 | BV12: 3632845 | BW12: 3039701.7 | BX12: 2896143.3 | BY12: 3219602 | BZ12: 3231403.2 | CA12: 2795277.8 | CB12: 3182917 | CC12: 2618157.2 | CD12: 4870709.5 | CE12: 2543463 | CF12: 3714464.9 | CG12: 4092424.2 | CH12: 3544114.3 | CI12: 2872637.5 | CJ12: 4574079.8 | CK12: 4102642.4 | CL12: 3138538.9 | CM12: 2775023.6 | CN12: 3310856.6 | CO12: 4420544.3 | CP12: 3492080.2 | CQ12: 2729286.4 | CR12: 2789992.6 | CS12: 3024180.5 | CT12: 2114784.3 | CU12: 3196070 | CV12: 3371607.7 | CW12: 5020547.9
A13: 202212 | B13: 3346291.9 | C13: 3888052.5 | D13: 3411174.3 | E13: 4059651.6 | F13: 3296948.6 | G13: 4311191 | H13: 2901192.1 | I13: 4371520.7 | J13: 4065767.2 | K13: 3253358.4 | L13: 2388800.2 | M13: 3395911.3 | N13: 2918940.6 | O13: 4279302.1 | P13: 3013677.8 | Q13: 2916519.8 | R13: 4166351.3 | S13: 3019577.1 | T13: 2882021.9 | U13: 2603242.9 | V13: 2933134.7 | W13: 4363761.9 | X13: 2672906.5 | Y13: 3441417.7 | Z13: 3387408 | AA13: 2504700.2 | AB13: 3176039.1 | AC13: 3261815.6 | AD13: 3692082.4 | AE13: 3033589.3 | AF13: 3354011.2 | AG13: 3338396.6 | AH13: 3334988 | AI13: 3681114.8 | AJ13: 3928213.7 | AK13: 3963587.9 | AL13: 3249791 | AM13: 4737206.6 | AN13: 3077559.4 | AO13: 3256602.1 | AP13: 3089026.8 | AQ13: 3047293 | AR13: 2974435.9 | AS13: 2459765.6 | AT13: 2974756.1 | AU13: 2487071.9 | AV13: 2824587 | AW13: 2986316.6 | AX13: 3338465.8 | AY13: 3029918.4 | AZ13: 5670784.6 | BA13: 4678979.3 | BB13: 3576439.9 | BC13: 2471825.5 | BD13: 3854433.4 | BE13: 3133357.8 | BF13: 3258063.2 | BG13: 3226295.9 | BH13: 3431612.2 | BI13: 3521170.5 | BJ13: 3592403.5 | BK13: 3648852.6 | BL13: 2344389.9 | BM13: 2934775.7 | BN13: 3316003 | BO13: 3095004.7 | BP13: 3361885 | BQ13: 4409538.8 | BR13: 3430514.2 | BS13: 3413961.4 | BT13: 4653332.9 | BU13: 2979834.7 | BV13: 3726721 | BW13: 3143865.8 | BX13: 3031303.5 | BY13: 3362341.1 | BZ13: 3364559 | CA13: 2920026.6 | CB13: 3236093.2 | CC13: 2729254.6 | CD13: 5192524.2 | CE13: 2640902.2 | CF13: 3857735 | CG13: 4175282 | CH13: 3668178.2 | CI13: 2985658.6 | CJ13: 4606782.6 | CK13: 4216069.4 | CL13: 3252064.2 | CM13: 2901502.3 | CN13: 3463341.3 | CO13: 4622768.6 | CP13: 3606749.5 | CQ13: 2843838.9 | CR13: 2924635.4 | CS13: 3107433 | CT13: 2195118.9 | CU13: 3349501.1 | CV13: 3586172.8 | CW13: 5229425.2
... A37: 202412 | B37: 3465029.1 | C37: 4055742.8 | D37: 3510841.6 | E37: 4168719.8 | F37: 3318117.2 | G37: 4497095 | H37: 3018129.2 | I37: 4511660.2 | J37: 4294468.5 | K37: 3424621.8 | L37: 2549145.4 | M37: 3513185.2 | N37: 2998746.8 | O37: 4411229.3 | P37: 3050632.5 | Q37: 3010240.6 | R37: 4348242.7 | S37: 3110310.1 | T37: 3051833.2 | U37: 2724591.3 | V37: 3014691.7 | W37: 4578177.7 | X37: 2815616.6 | Y37: 3557379 | Z37: 3536128 | AA37: 2589442.8 | AB37: 3288003.2 | AC37: 3427330.8 | AD37: 3894773.4 | AE37: 3112228.8 | AF37: 3457709.4 | AG37: 3504929.8 | AH37: 3515089 | AI37: 3855010.6 | AJ37: 4148836.4 | AK37: 4045826.3 | AL37: 3441953.1 | AM37: 4867072.3 | AN37: 3209853 | AO37: 3418375.9 | AP37: 3109345.3 | AQ37: 3106309.6 | AR37: 3156479.3 | AS37: 2589719.8 | AT37: 3078024.5 | AU37: 2595394.8 | AV37: 2887703.1 | AW37: 2999812 | AX37: 3435731.1 | AY37: 3176354.8 | AZ37: 5934473.6 | BA37: 4865186.4 | BB37: 3707182.9 | BC37: 2553084 | BD37: 4176811.5 | BE37: 3308914.2 | BF37: 3403909.9 | BG37: 3385169.3 | BH37: 3647787.9 | BI37: 3617470 | BJ37: 3757237.5 | BK37: 3765516.2 | BL37: 2384203 | BM37: 2987225.6 | BN37: 3493753.9 | BO37: 3208552.9 | BP37: 3461785.7 | BQ37: 4546406.3 | BR37: 3580058.4 | BS37: 3507047.6 | BT37: 4688768.5 | BU37: 3113172 | BV37: 3836315.3 | BW37: 3286277.2 | BX37: 3134156 | BY37: 3477960.5 | BZ37: 3466880.3 | CA37: 3020715.9 | CB37: 3365921.9 | CC37: 2807692.6 | CD37: 5266813.3 | CE37: 2806348.9 | CF37: 3985655 | CG37: 4346614.8 | CH37: 3758565.9 | CI37: 3175619.7 | CJ37: 4835431.4 | CK37: 4407626.9 | CL37: 3423108.6 | CM37: 3012729.2 | CN37: 3624664.4 | CO37: 4856093.6 | CP37: 3802044.7 | CQ37: 2971012 | CR37: 3084213.7 | CS37: 3285068.4 | CT37: 2334841.2 | CU37: 3531813.1 | CV37: 3723044.2 | CW37: 5298265.1

Sheet stores
A1: store_id | B1: zip | C1: state
A2: 1 | B2: 23230 | C2: VA
A3: 2 | B3: 20024 | C3: DC
A4: 3 | B4: 30308 | C4: GA
A5: 4 | B5: 30033 | C5: GA
A6: 5 | B6: 20427 | C6: DC
A7: 6 | B7: 23233 | C7: VA
A8: 7 | B8: 23025 | C8: VA
A9: 8 | B9: 21087 | C9: MD
A10: 9 | B10: 23457 | C10: VA
A11: 10 | B11: 23666 | C11: VA
A12: 11 | B12: 28587 | C12: NC
A13: 12 | B13: 22511 | C13: VA
... A101: 100 | B101: 20676 | C101: MD

Sheet soda_ppu
A1: year_month | B1: total_sales_1 | C1: total_sales_2 | D1: total_sales_3 | E1: total_sales_4 | F1: total_sales_5 | G1: total_sales_6 | H1: total_sales_7 | I1: total_sales_8 | J1: total_sales_9 | K1: total_sales_10 | L1: total_sales_11 | M1: total_sales_12 | N1: total_sales_13 | O1: total_sales_14 | P1: total_sales_15 | Q1: total_sales_16 | R1: total_sales_17 | S1: total_sales_18 | T1: total_sales_19 | U1: total_sales_20 | V1: total_sales_21 | W1: total_sales_22 | X1: total_sales_23 | Y1: total_sales_24 | Z1: total_sales_25 | AA1: total_sales_26 | AB1: total_sales_27 | AC1: total_sales_28 | AD1: total_sales_29 | AE1: total_sales_30 | AF1: total_sales_31 | AG1: total_sales_32 | AH1: total_sales_33 | AI1: total_sales_34 | AJ1: total_sales_35 | AK1: total_sales_36 | AL1: total_sales_37 | AM1: total_sales_38 | AN1: total_sales_39 | AO1: total_sales_40 | AP1: total_sales_41 | AQ1: total_sales_42 | AR1: total_sales_43 | AS1: total_sales_44 | AT1: total_sales_45 | AU1: total_sales_46 | AV1: total_sales_47 | AW1: total_sales_48 | AX1: total_sales_49 | AY1: total_sales_50 | AZ1: total_sales_51 | BA1: total_sales_52 | BB1: total_sales_53 | BC1: total_sales_54 | BD1: total_sales_55 | BE1: total_sales_56 | BF1: total_sales_57 | BG1: total_sales_58 | BH1: total_sales_59 | BI1: total_sales_60 | BJ1: total_sales_61 | BK1: total_sales_62 | BL1: total_sales_63 | BM1: total_sales_64 | BN1: total_sales_65 | BO1: total_sales_66 | BP1: total_sales_67 | BQ1: total_sales_68 | BR1: total_sales_69 | BS1: total_sales_70 | BT1: total_sales_71 | BU1: total_sales_72 | BV1: total_sales_73 | BW1: total_sales_74 | BX1: total_sales_75 | BY1: total_sales_76 | BZ1: total_sales_77 | CA1: total_sales_78 | CB1: total_sales_79 | CC1: total_sales_80 | CD1: total_sales_81 | CE1: total_sales_82 | CF1: total_sales_83 | CG1: total_sales_84 | CH1: total_sales_85 | CI1: total_sales_86 | CJ1: total_sales_87 | CK1: total_sales_88 | CL1: total_sales_89 | CM1: total_sales_90 | CN1: total_sales_91 | CO1: total_sales_92 | CP1: total_sales_93 | CQ1: total_sales_94 | CR1: total_sales_95 | CS1: total_sales_96 | CT1: total_sales_97 | CU1: total_sales_98 | CV1: total_sales_99 | CW1: total_sales_100
A2: 202201 | B2: 0.72128611 | C2: 0.70708444 | D2: 0.68312716 | E2: 0.61097691 | F2: 0.69278296 | G2: 0.72449255 | H2: 0.68822753 | I2: 0.67687395 | J2: 0.6964368 | K2: 0.72933885 | L2: 0.73128634 | M2: 0.72600414 | N2: 0.62748019 | O2: 0.72457759 | P2: 0.6999979 | Q2: 0.7309587 | R2: 0.69726521 | S2: 0.72690038 | T2: 0.71590313 | U2: 0.6736 | V2: 0.68534537 | W2: 0.69610184 | X2: 0.73601433 | Y2: 0.67575086 | Z2: 0.71238609 | AA2: 0.67154188 | AB2: 0.69720491 | AC2: 0.71989627 | AD2: 0.65950438 | AE2: 0.65958126 | AF2: 0.68594551 | AG2: 0.71281014 | AH2: 0.72037089 | AI2: 0.70088984 | AJ2: 0.65184912 | AK2: 0.65077106 | AL2: 0.73747279 | AM2: 0.65134095 | AN2: 0.69855383 | AO2: 0.65315014 | AP2: 0.63744149 | AQ2: 0.69626903 | AR2: 0.67970607 | AS2: 0.67294639 | AT2: 0.68545122 | AU2: 0.6578804 | AV2: 0.65373118 | AW2: 0.68867615 | AX2: 0.69968361 | AY2: 0.66964137 | AZ2: 0.6799431 | BA2: 0.74927129 | BB2: 0.70761314 | BC2: 0.71709229 | BD2: 0.7339764 | BE2: 0.67368748 | BF2: 0.68854687 | BG2: 0.68680913 | BH2: 0.70469418 | BI2: 0.73646965 | BJ2: 0.67282467 | BK2: 0.70524101 | BL2: 0.71018127 | BM2: 0.71117973 | BN2: 0.68379482 | BO2: 0.68647708 | BP2: 0.68341806 | BQ2: 0.74298176 | BR2: 0.72486508 | BS2: 0.76031024 | BT2: 0.69666027 | BU2: 0.72532613 | BV2: 0.70654547 | BW2: 0.71521074 | BX2: 0.71880857 | BY2: 0.63342257 | BZ2: 0.68588006 | CA2: 0.62330244 | CB2: 0.62984935 | CC2: 0.6492996 | CD2: 0.70734051 | CE2: 0.64551325 | CF2: 0.68290517 | CG2: 0.71745183 | CH2: 0.65749051 | CI2: 0.63675367 | CJ2: 0.71673919 | CK2: 0.70618843 | CL2: 0.7171316 | CM2: 0.73988198 | CN2: 0.7181464 | CO2: 0.74464389 | CP2: 0.67664289 | CQ2: 0.65761473 | CR2: 0.61136166 | CS2: 0.68268561 | CT2: 0.71593659 | CU2: 0.69943523 | CV2: 0.7047416 | CW2: 0.696248
A3: 202202 | B3: 0.73254691 | C3: 0.69612618 | D3: 0.67708103 | E3: 0.63528364 | F3: 0.70299404 | G3: 0.71479794 | H3: 0.68232565 | I3: 0.68483053 | J3: 0.69549083 | K3: 0.69634329 | L3: 0.7374811 | M3: 0.73388375 | N3: 0.63136952 | O3: 0.7360253 | P3: 0.70607741 | Q3: 0.73014786 | R3: 0.70663095 | S3: 0.74477773 | T3: 0.74122417 | U3: 0.70273752 | V3: 0.70944978 | W3: 0.70621466 | X3: 0.73070628 | Y3: 0.66805304 | Z3: 0.71812168 | AA3: 0.66368298 | AB3: 0.70451929 | AC3: 0.70315497 | AD3: 0.68376157 | AE3: 0.68083167 | AF3: 0.67857925 | AG3: 0.70860902 | AH3: 0.74015561 | AI3: 0.7086259 | AJ3: 0.68455419 | AK3: 0.69018374 | AL3: 0.72252427 | AM3: 0.68731555 | AN3: 0.68462754 | AO3: 0.70924581 | AP3: 0.67679896 | AQ3: 0.71086201 | AR3: 0.67665824 | AS3: 0.67849213 | AT3: 0.67258866 | AU3: 0.68121026 | AV3: 0.69440679 | AW3: 0.68002092 | AX3: 0.70135166 | AY3: 0.67797991 | AZ3: 0.68683924 | BA3: 0.7214409 | BB3: 0.71221666 | BC3: 0.74040029 | BD3: 0.72408998 | BE3: 0.65644234 | BF3: 0.69724216 | BG3: 0.72920094 | BH3: 0.70685442 | BI3: 0.72987461 | BJ3: 0.69252736 | BK3: 0.71420842 | BL3: 0.71979426 | BM3: 0.7184367 | BN3: 0.65917002 | BO3: 0.69344547 | BP3: 0.67794405 | BQ3: 0.71876533 | BR3: 0.71817752 | BS3: 0.75930388 | BT3: 0.70609348 | BU3: 0.73093972 | BV3: 0.69056575 | BW3: 0.75106955 | BX3: 0.75181948 | BY3: 0.62758879 | BZ3: 0.68439809 | CA3: 0.64380356 | CB3: 0.65982487 | CC3: 0.68520955 | CD3: 0.73568648 | CE3: 0.68381475 | CF3: 0.69334046 | CG3: 0.75477344 | CH3: 0.73328423 | CI3: 0.64497375 | CJ3: 0.74128421 | CK3: 0.70692003 | CL3: 0.70851971 | CM3: 0.71984491 | CN3: 0.73162691 | CO3: 0.76608374 | CP3: 0.69218125 | CQ3: 0.66949303 | CR3: 0.63953741 | CS3: 0.70498423 | CT3: 0.71741889 | CU3: 0.69951908 | CV3: 0.66969886 | CW3: 0.7214184
A4: 202203 | B4: 0.74708597 | C4: 0.7272752 | D4: 0.68476477 | E4: 0.64702879 | F4: 0.70150664 | G4: 0.72108545 | H4: 0.70581703 | I4: 0.68097579 | J4: 0.7075647 | K4: 0.73885609 | L4: 0.73373048 | M4: 0.741838 | N4: 0.62728472 | O4: 0.72384126 | P4: 0.70342557 | Q4: 0.72410458 | R4: 0.69716589 | S4: 0.74377214 | T4: 0.70588042 | U4: 0.69889063 | V4: 0.70317236 | W4: 0.66809458 | X4: 0.72536441 | Y4: 0.6830293 | Z4: 0.70754078 | AA4: 0.6643821 | AB4: 0.71693954 | AC4: 0.72865852 | AD4: 0.70039396 | AE4: 0.66555142 | AF4: 0.68945901 | AG4: 0.72635995 | AH4: 0.73480684 | AI4: 0.71983255 | AJ4: 0.65276256 | AK4: 0.69116998 | AL4: 0.73925234 | AM4: 0.67118492 | AN4: 0.67009884 | AO4: 0.72136373 | AP4: 0.66565238 | AQ4: 0.71789203 | AR4: 0.69547606 | AS4: 0.68934663 | AT4: 0.69016305 | AU4: 0.66021058 | AV4: 0.69033376 | AW4: 0.68673262 | AX4: 0.72972007 | AY4: 0.69469161 | AZ4: 0.67950942 | BA4: 0.76240575 | BB4: 0.71110237 | BC4: 0.7559939 | BD4: 0.72007189 | BE4: 0.69276572 | BF4: 0.68529072 | BG4: 0.73197765 | BH4: 0.70926018 | BI4: 0.72943732 | BJ4: 0.64755706 | BK4: 0.74762651 | BL4: 0.72048675 | BM4: 0.70676536 | BN4: 0.67924035 | BO4: 0.66587035 | BP4: 0.73480485 | BQ4: 0.74190868 | BR4: 0.7451782 | BS4: 0.72756269 | BT4: 0.72761422 | BU4: 0.76015423 | BV4: 0.71049259 | BW4: 0.71123533 | BX4: 0.74380132 | BY4: 0.64905162 | BZ4: 0.69402509 | CA4: 0.64305213 | CB4: 0.63400927 | CC4: 0.68572218 | CD4: 0.74564826 | CE4: 0.68573047 | CF4: 0.7088035 | CG4: 0.75093473 | CH4: 0.68032324 | CI4: 0.6539252 | CJ4: 0.72502897 | CK4: 0.71143197 | CL4: 0.68820561 | CM4: 0.73529712 | CN4: 0.7399469 | CO4: 0.71507129 | CP4: 0.68118198 | CQ4: 0.68604723 | CR4: 0.61374286 | CS4: 0.68212602 | CT4: 0.73426067 | CU4: 0.70115025 | CV4: 0.70895252 | CW4: 0.71484924
A5: 202204 | B5: 0.7194158 | C5: 0.73703265 | D5: 0.67717818 | E5: 0.65339917 | F5: 0.7126658 | G5: 0.72193948 | H5: 0.7079505 | I5: 0.68422799 | J5: 0.71576436 | K5: 0.73536894 | L5: 0.74020972 | M5: 0.69415549 | N5: 0.62434188 | O5: 0.70994456 | P5: 0.71066977 | Q5: 0.73616291 | R5: 0.70956588 | S5: 0.75253755 | T5: 0.73394209 | U5: 0.6865149 | V5: 0.69023394 | W5: 0.6846252 | X5: 0.75995753 | Y5: 0.69915394 | Z5: 0.73189413 | AA5: 0.65193985 | AB5: 0.71616116 | AC5: 0.71077219 | AD5: 0.67649312 | AE5: 0.65887808 | AF5: 0.65938375 | AG5: 0.74479474 | AH5: 0.69540271 | AI5: 0.72465736 | AJ5: 0.67086735 | AK5: 0.68546107 | AL5: 0.72286588 | AM5: 0.64861508 | AN5: 0.66959586 | AO5: 0.69540451 | AP5: 0.68682015 | AQ5: 0.7135249 | AR5: 0.6922937 | AS5: 0.6883019 | AT5: 0.69639347 | AU5: 0.67381485 | AV5: 0.66050411 | AW5: 0.67048794 | AX5: 0.72367837 | AY5: 0.68012388 | AZ5: 0.68772573 | BA5: 0.73703951 | BB5: 0.70487005 | BC5: 0.76597685 | BD5: 0.72670598 | BE5: 0.69019491 | BF5: 0.6903725 | BG5: 0.71796343 | BH5: 0.7638339 | BI5: 0.73740653 | BJ5: 0.64563385 | BK5: 0.75710378 | BL5: 0.73703908 | BM5: 0.70223491 | BN5: 0.66794359 | BO5: 0.69089271 | BP5: 0.71905809 | BQ5: 0.72616165 | BR5: 0.72999927 | BS5: 0.74860811 | BT5: 0.70572389 | BU5: 0.72558658 | BV5: 0.6951929 | BW5: 0.71310649 | BX5: 0.73748602 | BY5: 0.66545363 | BZ5: 0.70463574 | CA5: 0.63142359 | CB5: 0.63130075 | CC5: 0.68149407 | CD5: 0.74670527 | CE5: 0.65606754 | CF5: 0.70620291 | CG5: 0.73761176 | CH5: 0.69397075 | CI5: 0.64546157 | CJ5: 0.72570309 | CK5: 0.6896918 | CL5: 0.70666046 | CM5: 0.73288286 | CN5: 0.77291413 | CO5: 0.75584797 | CP5: 0.67675242 | CQ5: 0.65511282 | CR5: 0.62234793 | CS5: 0.65978907 | CT5: 0.70034103 | CU5: 0.6943941 | CV5: 0.70194023 | CW5: 0.70711869
A6: 202205 | B6: 0.74669868 | C6: 0.72247295 | D6: 0.70063526 | E6: 0.64187817 | F6: 0.70546685 | G6: 0.69776568 | H6: 0.71118658 | I6: 0.67165617 | J6: 0.70608198 | K6: 0.73970484 | L6: 0.72551186 | M6: 0.7187314 | N6: 0.63332928 | O6: 0.74302548 | P6: 0.72780332 | Q6: 0.75496672 | R6: 0.7022852 | S6: 0.71645471 | T6: 0.70590695 | U6: 0.72135034 | V6: 0.68010791 | W6: 0.66599573 | X6: 0.69335859 | Y6: 0.69247639 | Z6: 0.73611154 | AA6: 0.66641513 | AB6: 0.74200328 | AC6: 0.74481199 | AD6: 0.67013059 | AE6: 0.68046026 | AF6: 0.66083889 | AG6: 0.72455302 | AH6: 0.71806436 | AI6: 0.71602539 | AJ6: 0.66075482 | AK6: 0.69557876 | AL6: 0.76108955 | AM6: 0.62379229 | AN6: 0.67270884 | AO6: 0.70777012 | AP6: 0.68529727 | AQ6: 0.72117342 | AR6: 0.67933663 | AS6: 0.71486433 | AT6: 0.67596096 | AU6: 0.70054932 | AV6: 0.68388452 | AW6: 0.68493586 | AX6: 0.70594507 | AY6: 0.68393548 | AZ6: 0.6804293 | BA6: 0.74435714 | BB6: 0.71254537 | BC6: 0.75288332 | BD6: 0.72346057 | BE6: 0.67077214 | BF6: 0.68924634 | BG6: 0.71600712 | BH6: 0.71223847 | BI6: 0.75182171 | BJ6: 0.67976361 | BK6: 0.72661502 | BL6: 0.72543391 | BM6: 0.73627345 | BN6: 0.68393401 | BO6: 0.69334057 | BP6: 0.70600709 | BQ6: 0.75896433 | BR6: 0.73298228 | BS6: 0.75031326 | BT6: 0.71290096 | BU6: 0.72437819 | BV6: 0.70719242 | BW6: 0.70761127 | BX6: 0.7292684 | BY6: 0.64188342 | BZ6: 0.68990316 | CA6: 0.62392898 | CB6: 0.64490877 | CC6: 0.68745783 | CD6: 0.71821718 | CE6: 0.68716043 | CF6: 0.69397294 | CG6: 0.75405786 | CH6: 0.68961555 | CI6: 0.65445074 | CJ6: 0.7315805 | CK6: 0.7227808 | CL6: 0.70305069 | CM6: 0.73557019 | CN6: 0.72614281 | CO6: 0.75063232 | CP6: 0.68225416 | CQ6: 0.67626796 | CR6: 0.61936554 | CS6: 0.6880128 | CT6: 0.7203338 | CU6: 0.67793642 | CV6: 0.68781671 | CW6: 0.7094596
A7: 202206 | B7: 0.72526562 | C7: 0.69395817 | D7: 0.68219667 | E7: 0.66633646 | F7: 0.70174022 | G7: 0.72215573 | H7: 0.69721614 | I7: 0.68817972 | J7: 0.71111518 | K7: 0.73102171 | L7: 0.75110889 | M7: 0.71464276 | N7: 0.61695804 | O7: 0.72934158 | P7: 0.70826412 | Q7: 0.74825836 | R7: 0.68671329 | S7: 0.72123805 | T7: 0.69961594 | U7: 0.69759736 | V7: 0.68604266 | W7: 0.67354289 | X7: 0.71307094 | Y7: 0.67049506 | Z7: 0.71972209 | AA7: 0.64990521 | AB7: 0.73525604 | AC7: 0.74941951 | AD7: 0.67546118 | AE7: 0.63879226 | AF7: 0.67163482 | AG7: 0.75410497 | AH7: 0.73893164 | AI7: 0.71943332 | AJ7: 0.67452384 | AK7: 0.6581031 | AL7: 0.72719549 | AM7: 0.66773835 | AN7: 0.68718274 | AO7: 0.6915313 | AP7: 0.65891135 | AQ7: 0.73586787 | AR7: 0.69416833 | AS7: 0.69455162 | AT7: 0.69192726 | AU7: 0.67158125 | AV7: 0.66524473 | AW7: 0.68417374 | AX7: 0.70656598 | AY7: 0.67948598 | AZ7: 0.69302444 | BA7: 0.76334872 | BB7: 0.71784304 | BC7: 0.7272769 | BD7: 0.72005139 | BE7: 0.68989953 | BF7: 0.69651623 | BG7: 0.71538918 | BH7: 0.71412302 | BI7: 0.69230106 | BJ7: 0.65340958 | BK7: 0.74913899 | BL7: 0.70713942 | BM7: 0.74397965 | BN7: 0.68849145 | BO7: 0.68209698 | BP7: 0.70682098 | BQ7: 0.75180391 | BR7: 0.71112156 | BS7: 0.74830238 | BT7: 0.71544789 | BU7: 0.7519093 | BV7: 0.68528826 | BW7: 0.70483904 | BX7: 0.73651027 | BY7: 0.63760155 | BZ7: 0.6792596 | CA7: 0.63070839 | CB7: 0.61880571 | CC7: 0.675791 | CD7: 0.7328741 | CE7: 0.65727044 | CF7: 0.68720871 | CG7: 0.73656194 | CH7: 0.68749417 | CI7: 0.63811006 | CJ7: 0.73785872 | CK7: 0.72578798 | CL7: 0.71201949 | CM7: 0.7317009 | CN7: 0.72759093 | CO7: 0.73356402 | CP7: 0.66193783 | CQ7: 0.69411434 | CR7: 0.63575409 | CS7: 0.69826637 | CT7: 0.72359716 | CU7: 0.72855677 | CV7: 0.7121639 | CW7: 0.72263057
A8: 202207 | B8: 0.74298321 | C8: 0.71169636 | D8: 0.68387474 | E8: 0.64551079 | F8: 0.71851114 | G8: 0.71146391 | H8: 0.69192325 | I8: 0.68076853 | J8: 0.71791076 | K8: 0.71955216 | L8: 0.74243371 | M8: 0.68821621 | N8: 0.64535181 | O8: 0.72723863 | P8: 0.7221571 | Q8: 0.72930742 | R8: 0.70081096 | S8: 0.72924712 | T8: 0.71188292 | U8: 0.70948454 | V8: 0.6743095 | W8: 0.67483082 | X8: 0.72341638 | Y8: 0.68142348 | Z8: 0.72718856 | AA8: 0.64225553 | AB8: 0.73072096 | AC8: 0.73395968 | AD8: 0.64275694 | AE8: 0.66670752 | AF8: 0.6676167 | AG8: 0.72412498 | AH8: 0.71341438 | AI8: 0.66262608 | AJ8: 0.67001584 | AK8: 0.68490213 | AL8: 0.72364414 | AM8: 0.66269383 | AN8: 0.71039252 | AO8: 0.70031884 | AP8: 0.69055291 | AQ8: 0.70724887 | AR8: 0.69462715 | AS8: 0.70154086 | AT8: 0.71236439 | AU8: 0.6925041 | AV8: 0.65025529 | AW8: 0.68898649 | AX8: 0.69258443 | AY8: 0.68206007 | AZ8: 0.67008294 | BA8: 0.75212962 | BB8: 0.70799084 | BC8: 0.75492165 | BD8: 0.73814038 | BE8: 0.69679932 | BF8: 0.68163785 | BG8: 0.70470568 | BH8: 0.714261 | BI8: 0.72860411 | BJ8: 0.69541446 | BK8: 0.72463034 | BL8: 0.71752895 | BM8: 0.71671023 | BN8: 0.67779757 | BO8: 0.67894538 | BP8: 0.68109098 | BQ8: 0.75030078 | BR8: 0.70477557 | BS8: 0.77205075 | BT8: 0.70763399 | BU8: 0.74886142 | BV8: 0.67935213 | BW8: 0.7189201 | BX8: 0.75805491 | BY8: 0.65730986 | BZ8: 0.71089444 | CA8: 0.62996213 | CB8: 0.63748286 | CC8: 0.67787527 | CD8: 0.74922894 | CE8: 0.67008717 | CF8: 0.68893227 | CG8: 0.74994913 | CH8: 0.71748791 | CI8: 0.62835634 | CJ8: 0.75747044 | CK8: 0.70666985 | CL8: 0.71960088 | CM8: 0.73415861 | CN8: 0.77150561 | CO8: 0.74925953 | CP8: 0.69655599 | CQ8: 0.66460453 | CR8: 0.61240119 | CS8: 0.71132436 | CT8: 0.73075081 | CU8: 0.67863235 | CV8: 0.71744971 | CW8: 0.69834306
A9: 202208 | B9: 0.69986066 | C9: 0.70810423 | D9: 0.67716325 | E9: 0.64427537 | F9: 0.70490762 | G9: 0.74189062 | H9: 0.69626766 | I9: 0.69215879 | J9: 0.73390341 | K9: 0.74812753 | L9: 0.74188999 | M9: 0.72870067 | N9: 0.63439622 | O9: 0.7396985 | P9: 0.69227827 | Q9: 0.76247794 | R9: 0.65607283 | S9: 0.75525877 | T9: 0.71094506 | U9: 0.70496496 | V9: 0.67187211 | W9: 0.67046917 | X9: 0.71722964 | Y9: 0.67964456 | Z9: 0.71258518 | AA9: 0.6625338 | AB9: 0.73412921 | AC9: 0.72126958 | AD9: 0.67706278 | AE9: 0.67452734 | AF9: 0.66454486 | AG9: 0.74387045 | AH9: 0.71513485 | AI9: 0.70767629 | AJ9: 0.66065938 | AK9: 0.65150084 | AL9: 0.77279625 | AM9: 0.66413185 | AN9: 0.70335298 | AO9: 0.72452206 | AP9: 0.70401949 | AQ9: 0.72331682 | AR9: 0.69521743 | AS9: 0.68813753 | AT9: 0.69266485 | AU9: 0.67377202 | AV9: 0.67861054 | AW9: 0.68144022 | AX9: 0.72435113 | AY9: 0.67419246 | AZ9: 0.68565077 | BA9: 0.72948166 | BB9: 0.69262125 | BC9: 0.72654498 | BD9: 0.75581442 | BE9: 0.68691449 | BF9: 0.70131564 | BG9: 0.71384598 | BH9: 0.71455289 | BI9: 0.71079335 | BJ9: 0.67585439 | BK9: 0.71855988 | BL9: 0.72388674 | BM9: 0.7211854 | BN9: 0.68010289 | BO9: 0.69452543 | BP9: 0.73490197 | BQ9: 0.74388276 | BR9: 0.72937649 | BS9: 0.76403825 | BT9: 0.69467592 | BU9: 0.74283939 | BV9: 0.66470844 | BW9: 0.71625854 | BX9: 0.7389951 | BY9: 0.64771206 | BZ9: 0.70656509 | CA9: 0.64208257 | CB9: 0.64605833 | CC9: 0.68271112 | CD9: 0.72643038 | CE9: 0.64563719 | CF9: 0.68492166 | CG9: 0.74073822 | CH9: 0.69338689 | CI9: 0.64406365 | CJ9: 0.73272211 | CK9: 0.70878171 | CL9: 0.72627769 | CM9: 0.70622446 | CN9: 0.7862629 | CO9: 0.73550043 | CP9: 0.67955838 | CQ9: 0.66827796 | CR9: 0.62353952 | CS9: 0.70218667 | CT9: 0.71360837 | CU9: 0.6911074 | CV9: 0.71833126 | CW9: 0.71042837
A10: 202209 | B10: 0.7171257 | C10: 0.69666339 | D10: 0.67116631 | E10: 0.62286895 | F10: 0.67933258 | G10: 0.71072956 | H10: 0.69915038 | I10: 0.69665141 | J10: 0.71535859 | K10: 0.72606071 | L10: 0.74411256 | M10: 0.7148475 | N10: 0.6266774 | O10: 0.73297413 | P10: 0.71181261 | Q10: 0.75725977 | R10: 0.70262301 | S10: 0.75346818 | T10: 0.70522989 | U10: 0.69753976 | V10: 0.6677264 | W10: 0.66299869 | X10: 0.70096455 | Y10: 0.65310087 | Z10: 0.71707933 | AA10: 0.67220528 | AB10: 0.71628606 | AC10: 0.71818264 | AD10: 0.66091285 | AE10: 0.65999066 | AF10: 0.67054319 | AG10: 0.74455079 | AH10: 0.73720712 | AI10: 0.70900155 | AJ10: 0.69995156 | AK10: 0.68092485 | AL10: 0.72759213 | AM10: 0.66490032 | AN10: 0.70840813 | AO10: 0.69241083 | AP10: 0.69078297 | AQ10: 0.72191232 | AR10: 0.69223128 | AS10: 0.67109177 | AT10: 0.70618288 | AU10: 0.65654738 | AV10: 0.67159707 | AW10: 0.70159652 | AX10: 0.71723613 | AY10: 0.68107341 | AZ10: 0.66210726 | BA10: 0.75077743 | BB10: 0.7003933 | BC10: 0.74134977 | BD10: 0.72273122 | BE10: 0.70475502 | BF10: 0.69676414 | BG10: 0.71600513 | BH10: 0.72251371 | BI10: 0.74538182 | BJ10: 0.65849715 | BK10: 0.73051762 | BL10: 0.71767917 | BM10: 0.73123782 | BN10: 0.68922105 | BO10: 0.6792481 | BP10: 0.72852449 | BQ10: 0.74920217 | BR10: 0.74329298 | BS10: 0.73787511 | BT10: 0.69391137 | BU10: 0.69664311 | BV10: 0.67808293 | BW10: 0.73615086 | BX10: 0.74009579 | BY10: 0.65822823 | BZ10: 0.69554893 | CA10: 0.6511782 | CB10: 0.65928058 | CC10: 0.68774399 | CD10: 0.73334762 | CE10: 0.66679021 | CF10: 0.70629322 | CG10: 0.7738094 | CH10: 0.6727423 | CI10: 0.62808083 | CJ10: 0.71251304 | CK10: 0.70828123 | CL10: 0.71688477 | CM10: 0.71378865 | CN10: 0.73457499 | CO10: 0.74085826 | CP10: 0.68686174 | CQ10: 0.65610751 | CR10: 0.63205516 | CS10: 0.70176026 | CT10: 0.73455659 | CU10: 0.71760285 | CV10: 0.68503876 | CW10: 0.70914287
A11: 202210 | B11: 0.72732501 | C11: 0.70435375 | D11: 0.66987122 | E11: 0.6637591 | F11: 0.70502568 | G11: 0.72331329 | H11: 0.67703503 | I11: 0.72084753 | J11: 0.69416784 | K11: 0.7391622 | L11: 0.71382653 | M11: 0.71931311 | N11: 0.62149517 | O11: 0.70718597 | P11: 0.70990265 | Q11: 0.75066358 | R11: 0.68746062 | S11: 0.73021265 | T11: 0.71323696 | U11: 0.72934706 | V11: 0.66286027 | W11: 0.69383982 | X11: 0.70523119 | Y11: 0.69804486 | Z11: 0.73966552 | AA11: 0.67878603 | AB11: 0.69362564 | AC11: 0.73237989 | AD11: 0.6847503 | AE11: 0.64635419 | AF11: 0.69934797 | AG11: 0.72209465 | AH11: 0.73061502 | AI11: 0.69809828 | AJ11: 0.67187678 | AK11: 0.68531786 | AL11: 0.72012972 | AM11: 0.65972444 | AN11: 0.69154586 | AO11: 0.7004517 | AP11: 0.70409469 | AQ11: 0.72389292 | AR11: 0.69207861 | AS11: 0.70492693 | AT11: 0.68689469 | AU11: 0.65953741 | AV11: 0.68258631 | AW11: 0.68823251 | AX11: 0.72469399 | AY11: 0.68247675 | AZ11: 0.68249641 | BA11: 0.78171601 | BB11: 0.71399053 | BC11: 0.73677832 | BD11: 0.72562446 | BE11: 0.66417756 | BF11: 0.6831977 | BG11: 0.73470913 | BH11: 0.71982144 | BI11: 0.74363922 | BJ11: 0.69773142 | BK11: 0.74590219 | BL11: 0.73227621 | BM11: 0.74779688 | BN11: 0.67261828 | BO11: 0.69872934 | BP11: 0.70232647 | BQ11: 0.72919161 | BR11: 0.72683027 | BS11: 0.7380623 | BT11: 0.73413484 | BU11: 0.78482634 | BV11: 0.68218759 | BW11: 0.70301088 | BX11: 0.72224266 | BY11: 0.65098068 | BZ11: 0.68192151 | CA11: 0.64943042 | CB11: 0.62862984 | CC11: 0.69999756 | CD11: 0.72065857 | CE11: 0.67834102 | CF11: 0.68741529 | CG11: 0.75783457 | CH11: 0.69777325 | CI11: 0.66349586 | CJ11: 0.71066399 | CK11: 0.74342682 | CL11: 0.69102155 | CM11: 0.74528704 | CN11: 0.7409872 | CO11: 0.76043168 | CP11: 0.67983815 | CQ11: 0.66079374 | CR11: 0.6368443 | CS11: 0.69147399 | CT11: 0.71379179 | CU11: 0.68054899 | CV11: 0.69350794 | CW11: 0.73602829
A12: 202211 | B12: 0.70306026 | C12: 0.68150545 | D12: 0.68881996 | E12: 0.65266273 | F12: 0.70335469 | G12: 0.69920908 | H12: 0.7014641 | I12: 0.66316908 | J12: 0.73032171 | K12: 0.73601357 | L12: 0.75790762 | M12: 0.7093233 | N12: 0.64829365 | O12: 0.73497623 | P12: 0.69283692 | Q12: 0.7396404 | R12: 0.71004806 | S12: 0.73183312 | T12: 0.71349454 | U12: 0.7060866 | V12: 0.68356037 | W12: 0.68483656 | X12: 0.7422875 | Y12: 0.6874855 | Z12: 0.71569288 | AA12: 0.66917602 | AB12: 0.74066369 | AC12: 0.71957747 | AD12: 0.68785509 | AE12: 0.65992356 | AF12: 0.68850093 | AG12: 0.71477931 | AH12: 0.70980825 | AI12: 0.69085845 | AJ12: 0.66718393 | AK12: 0.68921522 | AL12: 0.74682626 | AM12: 0.65110094 | AN12: 0.68536606 | AO12: 0.68817293 | AP12: 0.67187338 | AQ12: 0.71298707 | AR12: 0.68359572 | AS12: 0.67536076 | AT12: 0.69263569 | AU12: 0.69487245 | AV12: 0.66793241 | AW12: 0.69650979 | AX12: 0.72380508 | AY12: 0.69864103 | AZ12: 0.6644875 | BA12: 0.74071288 | BB12: 0.71283942 | BC12: 0.73289992 | BD12: 0.75143418 | BE12: 0.65980793 | BF12: 0.6904807 | BG12: 0.714978 | BH12: 0.72926131 | BI12: 0.7190425 | BJ12: 0.66780496 | BK12: 0.72001843 | BL12: 0.71916437 | BM12: 0.7277597 | BN12: 0.67488163 | BO12: 0.65841155 | BP12: 0.73413925 | BQ12: 0.75743257 | BR12: 0.70857774 | BS12: 0.73580445 | BT12: 0.71253874 | BU12: 0.73175111 | BV12: 0.69088816 | BW12: 0.73536555 | BX12: 0.75381059 | BY12: 0.63620322 | BZ12: 0.70853571 | CA12: 0.6327224 | CB12: 0.64426354 | CC12: 0.6744541 | CD12: 0.72188216 | CE12: 0.67255227 | CF12: 0.69712713 | CG12: 0.74718989 | CH12: 0.67337255 | CI12: 0.64854338 | CJ12: 0.75498754 | CK12: 0.69795244 | CL12: 0.73731702 | CM12: 0.70524985 | CN12: 0.7503037 | CO12: 0.7655852 | CP12: 0.66925918 | CQ12: 0.69454827 | CR12: 0.63811616 | CS12: 0.66740634 | CT12: 0.70347071 | CU12: 0.68651098 | CV12: 0.6903645 | CW12: 0.72785948
A13: 202212 | B13: 0.73028386 | C13: 0.71780851 | D13: 0.69615515 | E13: 0.61593259 | F13: 0.68405945 | G13: 0.72311292 | H13: 0.7090039 | I13: 0.67121544 | J13: 0.68789066 | K13: 0.73209569 | L13: 0.74360751 | M13: 0.70772566 | N13: 0.64075183 | O13: 0.73955916 | P13: 0.7087855 | Q13: 0.76332222 | R13: 0.68831104 | S13: 0.75759749 | T13: 0.72426178 | U13: 0.70738005 | V13: 0.68372592 | W13: 0.67173085 | X13: 0.73838625 | Y13: 0.67102755 | Z13: 0.72241439 | AA13: 0.67079856 | AB13: 0.7248975 | AC13: 0.70718121 | AD13: 0.67233537 | AE13: 0.64917519 | AF13: 0.67190062 | AG13: 0.71715671 | AH13: 0.69469782 | AI13: 0.71623872 | AJ13: 0.68576605 | AK13: 0.68028562 | AL13: 0.75084053 | AM13: 0.66919664 | AN13: 0.72298259 | AO13: 0.7016584 | AP13: 0.68176947 | AQ13: 0.70224356 | AR13: 0.68966627 | AS13: 0.68726199 | AT13: 0.70579449 | AU13: 0.6790236 | AV13: 0.65293471 | AW13: 0.68679523 | AX13: 0.69967932 | AY13: 0.69519693 | AZ13: 0.68689977 | BA13: 0.7504822 | BB13: 0.729006 | BC13: 0.71512211 | BD13: 0.69307152 | BE13: 0.65956494 | BF13: 0.68834793 | BG13: 0.72027557 | BH13: 0.712304 | BI13: 0.70153612 | BJ13: 0.66587805 | BK13: 0.73872237 | BL13: 0.7178922 | BM13: 0.74307597 | BN13: 0.67934797 | BO13: 0.70085742 | BP13: 0.70077536 | BQ13: 0.75684591 | BR13: 0.72334162 | BS13: 0.75661707 | BT13: 0.71622402 | BU13: 0.72948234 | BV13: 0.68239487 | BW13: 0.72628162 | BX13: 0.70119541 | BY13: 0.65606543 | BZ13: 0.68391877 | CA13: 0.64858867 | CB13: 0.62336217 | CC13: 0.67860209 | CD13: 0.73381288 | CE13: 0.65464 | CF13: 0.67632781 | CG13: 0.74804873 | CH13: 0.66882699 | CI13: 0.65236869 | CJ13: 0.71072497 | CK13: 0.71576361 | CL13: 0.71770253 | CM13: 0.73681761 | CN13: 0.72541665 | CO13: 0.72457271 | CP13: 0.66107955 | CQ13: 0.67519476 | CR13: 0.63947655 | CS13: 0.68292793 | CT13: 0.7473268 | CU13: 0.68465376 | CV13: 0.6945272 | CW13: 0.70807332
... A37: 202412 | B37: 0.77607377 | C37: 0.76940729 | D37: 0.74585706 | E37: 0.68600915 | F37: 0.72935941 | G37: 0.77139389 | H37: 0.75107298 | I37: 0.76133678 | J37: 0.77048825 | K37: 0.78567822 | L37: 0.83786867 | M37: 0.77519298 | N37: 0.65519527 | O37: 0.81322271 | P37: 0.79334 | Q37: 0.79617175 | R37: 0.75078955 | S37: 0.85466613 | T37: 0.81600797 | U37: 0.76108613 | V37: 0.73504667 | W37: 0.74623593 | X37: 0.82377333 | Y37: 0.72539656 | Z37: 0.79119323 | AA37: 0.68260921 | AB37: 0.76432239 | AC37: 0.7816317 | AD37: 0.71947652 | AE37: 0.71331922 | AF37: 0.74369763 | AG37: 0.77526512 | AH37: 0.7678759 | AI37: 0.77192894 | AJ37: 0.71075698 | AK37: 0.7757105 | AL37: 0.7811814 | AM37: 0.74086723 | AN37: 0.81401471 | AO37: 0.7358382 | AP37: 0.74881595 | AQ37: 0.80139914 | AR37: 0.7475136 | AS37: 0.75578124 | AT37: 0.7542144 | AU37: 0.7331954 | AV37: 0.73854338 | AW37: 0.74415658 | AX37: 0.7534229 | AY37: 0.74466369 | AZ37: 0.73324746 | BA37: 0.82400744 | BB37: 0.79326371 | BC37: 0.80723867 | BD37: 0.79631671 | BE37: 0.73117207 | BF37: 0.73525194 | BG37: 0.8005902 | BH37: 0.76308435 | BI37: 0.81555732 | BJ37: 0.74772728 | BK37: 0.78690325 | BL37: 0.78729007 | BM37: 0.79561041 | BN37: 0.77192941 | BO37: 0.76315679 | BP37: 0.75200748 | BQ37: 0.7818718 | BR37: 0.79889401 | BS37: 0.79411545 | BT37: 0.77684743 | BU37: 0.8365823 | BV37: 0.751528 | BW37: 0.77351351 | BX37: 0.80243633 | BY37: 0.6980262 | BZ37: 0.76795922 | CA37: 0.65769099 | CB37: 0.69071645 | CC37: 0.76901008 | CD37: 0.80193248 | CE37: 0.74636056 | CF37: 0.74183972 | CG37: 0.77888106 | CH37: 0.73988213 | CI37: 0.68560587 | CJ37: 0.75944878 | CK37: 0.77776959 | CL37: 0.82483383 | CM37: 0.8236861 | CN37: 0.79397615 | CO37: 0.80391448 | CP37: 0.76851287 | CQ37: 0.71371674 | CR37: 0.70559071 | CS37: 0.73868773 | CT37: 0.78527868 | CU37: 0.76847151 | CV37: 0.79681799 | CW37: 0.77234905

Sheet soda_units_sold
A1: year_month | B1: total_sales_1 | C1: total_sales_2 | D1: total_sales_3 | E1: total_sales_4 | F1: total_sales_5 | G1: total_sales_6 | H1: total_sales_7 | I1: total_sales_8 | J1: total_sales_9 | K1: total_sales_10 | L1: total_sales_11 | M1: total_sales_12 | N1: total_sales_13 | O1: total_sales_14 | P1: total_sales_15 | Q1: total_sales_16 | R1: total_sales_17 | S1: total_sales_18 | T1: total_sales_19 | U1: total_sales_20 | V1: total_sales_21 | W1: total_sales_22 | X1: total_sales_23 | Y1: total_sales_24 | Z1: total_sales_25 | AA1: total_sales_26 | AB1: total_sales_27 | AC1: total_sales_28 | AD1: total_sales_29 | AE1: total_sales_30 | AF1: total_sales_31 | AG1: total_sales_32 | AH1: total_sales_33 | AI1: total_sales_34 | AJ1: total_sales_35 | AK1: total_sales_36 | AL1: total_sales_37 | AM1: total_sales_38 | AN1: total_sales_39 | AO1: total_sales_40 | AP1: total_sales_41 | AQ1: total_sales_42 | AR1: total_sales_43 | AS1: total_sales_44 | AT1: total_sales_45 | AU1: total_sales_46 | AV1: total_sales_47 | AW1: total_sales_48 | AX1: total_sales_49 | AY1: total_sales_50 | AZ1: total_sales_51 | BA1: total_sales_52 | BB1: total_sales_53 | BC1: total_sales_54 | BD1: total_sales_55 | BE1: total_sales_56 | BF1: total_sales_57 | BG1: total_sales_58 | BH1: total_sales_59 | BI1: total_sales_60 | BJ1: total_sales_61 | BK1: total_sales_62 | BL1: total_sales_63 | BM1: total_sales_64 | BN1: total_sales_65 | BO1: total_sales_66 | BP1: total_sales_67 | BQ1: total_sales_68 | BR1: total_sales_69 | BS1: total_sales_70 | BT1: total_sales_71 | BU1: total_sales_72 | BV1: total_sales_73 | BW1: total_sales_74 | BX1: total_sales_75 | BY1: total_sales_76 | BZ1: total_sales_77 | CA1: total_sales_78 | CB1: total_sales_79 | CC1: total_sales_80 | CD1: total_sales_81 | CE1: total_sales_82 | CF1: total_sales_83 | CG1: total_sales_84 | CH1: total_sales_85 | CI1: total_sales_86 | CJ1: total_sales_87 | CK1: total_sales_88 | CL1: total_sales_89 | CM1: total_sales_90 | CN1: total_sales_91 | CO1: total_sales_92 | CP1: total_sales_93 | CQ1: total_sales_94 | CR1: total_sales_95 | CS1: total_sales_96 | CT1: total_sales_97 | CU1: total_sales_98 | CV1: total_sales_99 | CW1: total_sales_100
A2: 202201 | B2: 141066 | C2: 142774 | D2: 143803 | E2: 154699 | F2: 142045 | G2: 122288 | H2: 145954 | I2: 126046 | J2: 132240 | K2: 132471 | L2: 129125 | M2: 131566 | N2: 169616 | O2: 133827 | P2: 155074 | Q2: 133360 | R2: 123796 | S2: 142517 | T2: 136461 | U2: 136442 | V2: 135944 | W2: 139822 | X2: 127237 | Y2: 149491 | Z2: 145662 | AA2: 160722 | AB2: 151104 | AC2: 142591 | AD2: 162824 | AE2: 167697 | AF2: 137173 | AG2: 143567 | AH2: 132524 | AI2: 143419 | AJ2: 143275 | AK2: 134578 | AL2: 143527 | AM2: 136304 | AN2: 150196 | AO2: 165778 | AP2: 175386 | AQ2: 153673 | AR2: 141889 | AS2: 159412 | AT2: 155374 | AU2: 159836 | AV2: 162694 | AW2: 151112 | AX2: 131620 | AY2: 159649 | AZ2: 71344 | BA2: 119293 | BB2: 152115 | BC2: 133261 | BD2: 138675 | BE2: 155168 | BF2: 154898 | BG2: 136015 | BH2: 133592 | BI2: 138812 | BJ2: 137700 | BK2: 151399 | BL2: 118955 | BM2: 135420 | BN2: 154695 | BO2: 154993 | BP2: 152334 | BQ2: 116580 | BR2: 130290 | BS2: 137043 | BT2: 123292 | BU2: 144127 | BV2: 140277 | BW2: 136525 | BX2: 148225 | BY2: 159998 | BZ2: 157207 | CA2: 175465 | CB2: 153651 | CC2: 155268 | CD2: 82702 | CE2: 163332 | CF2: 146852 | CG2: 131655 | CH2: 163288 | CI2: 171667 | CJ2: 130671 | CK2: 142756 | CL2: 148055 | CM2: 128234 | CN2: 144953 | CO2: 119732 | CP2: 141107 | CQ2: 155130 | CR2: 155212 | CS2: 155600 | CT2: 115092 | CU2: 137122 | CV2: 132377 | CW2: 101664
A3: 202202 | B3: 149265 | C3: 159898 | D3: 169302 | E3: 166409 | F3: 156978 | G3: 135320 | H3: 170661 | I3: 144565 | J3: 152800 | K3: 155614 | L3: 144838 | M3: 147301 | N3: 187176 | O3: 147116 | P3: 177200 | Q3: 153607 | R3: 138911 | S3: 156286 | T3: 151040 | U3: 144371 | V3: 149900 | W3: 156531 | X3: 143200 | Y3: 166274 | Z3: 167262 | AA3: 187304 | AB3: 169064 | AC3: 166319 | AD3: 178654 | AE3: 176627 | AF3: 157068 | AG3: 166639 | AH3: 145388 | AI3: 164681 | AJ3: 152948 | AK3: 141343 | AL3: 167529 | AM3: 149896 | AN3: 176238 | AO3: 169447 | AP3: 186229 | AQ3: 168441 | AR3: 169315 | AS3: 181350 | AT3: 178775 | AU3: 175339 | AV3: 168326 | AW3: 173040 | AX3: 148871 | AY3: 179703 | AZ3: 80078 | BA3: 138608 | BB3: 174978 | BC3: 141639 | BD3: 158561 | BE3: 179636 | BF3: 172237 | BG3: 148796 | BH3: 153077 | BI3: 159993 | BJ3: 149675 | BK3: 169981 | BL3: 133652 | BM3: 157254 | BN3: 176386 | BO3: 174160 | BP3: 173953 | BQ3: 137198 | BR3: 147471 | BS3: 158100 | BT3: 139817 | BU3: 153392 | BV3: 159308 | BW3: 140408 | BX3: 157192 | BY3: 181643 | BZ3: 183643 | CA3: 193687 | CB3: 169322 | CC3: 162543 | CD3: 92127 | CE3: 177507 | CF3: 162324 | CG3: 141898 | CH3: 169678 | CI3: 190371 | CJ3: 143903 | CK3: 160638 | CL3: 176824 | CM3: 154199 | CN3: 165681 | CO3: 132370 | CP3: 157423 | CQ3: 171348 | CR3: 171702 | CS3: 173431 | CT3: 131754 | CU3: 152118 | CV3: 156249 | CW3: 109401
A4: 202203 | B4: 169964 | C4: 185067 | D4: 191364 | E4: 190755 | F4: 192838 | G4: 159115 | H4: 194983 | I4: 171479 | J4: 171791 | K4: 176192 | L4: 176325 | M4: 173419 | N4: 222997 | O4: 172678 | P4: 209296 | Q4: 182136 | R4: 167458 | S4: 184917 | T4: 185146 | U4: 173269 | V4: 175139 | W4: 197641 | X4: 166137 | Y4: 191740 | Z4: 196941 | AA4: 218470 | AB4: 196968 | AC4: 182548 | AD4: 203241 | AE4: 225418 | AF4: 187404 | AG4: 189076 | AH4: 178156 | AI4: 188330 | AJ4: 182568 | AK4: 164759 | AL4: 190861 | AM4: 184304 | AN4: 210992 | AO4: 200143 | AP4: 218551 | AQ4: 195820 | AR4: 190613 | AS4: 201235 | AT4: 209019 | AU4: 214048 | AV4: 200652 | AW4: 202471 | AX4: 171569 | AY4: 203664 | AZ4: 93158 | BA4: 157463 | BB4: 205007 | BC4: 157101 | BD4: 192179 | BE4: 200587 | BF4: 209385 | BG4: 171996 | BH4: 178109 | BI4: 186487 | BJ4: 184026 | BK4: 193948 | BL4: 156281 | BM4: 186870 | BN4: 207113 | BO4: 211870 | BP4: 189343 | BQ4: 159311 | BR4: 166795 | BS4: 193118 | BT4: 165419 | BU4: 177517 | BV4: 184301 | BW4: 174495 | BX4: 194078 | BY4: 213575 | BZ4: 211254 | CA4: 233119 | CB4: 200809 | CC4: 202043 | CD4: 109555 | CE4: 202894 | CF4: 190168 | CG4: 165077 | CH4: 210457 | CI4: 219461 | CJ4: 164669 | CK4: 189736 | CL4: 219126 | CM4: 168522 | CN4: 194011 | CO4: 162724 | CP4: 188245 | CQ4: 197685 | CR4: 206238 | CS4: 211551 | CT4: 144939 | CU4: 175930 | CV4: 175969 | CW4: 126916
A5: 202204 | B5: 209250 | C5: 210840 | D5: 232589 | E5: 221681 | F5: 218415 | G5: 186966 | H5: 227966 | I5: 199607 | J5: 195869 | K5: 206802 | L5: 193349 | M5: 220296 | N5: 262237 | O5: 209161 | P5: 236418 | Q5: 207469 | R5: 190987 | S5: 209888 | T5: 209250 | U5: 209693 | V5: 205679 | W5: 219089 | X5: 183520 | Y5: 221157 | Z5: 221781 | AA5: 263906 | AB5: 224474 | AC5: 222271 | AD5: 243011 | AE5: 254618 | AF5: 219250 | AG5: 217857 | AH5: 214565 | AI5: 217719 | AJ5: 214639 | AK5: 196792 | AL5: 229063 | AM5: 213202 | AN5: 245093 | AO5: 241508 | AP5: 250115 | AQ5: 227068 | AR5: 221806 | AS5: 233663 | AT5: 239938 | AU5: 242627 | AV5: 256062 | AW5: 246046 | AX5: 203762 | AY5: 241636 | AZ5: 112601 | BA5: 187493 | BB5: 237634 | BC5: 179888 | BD5: 219664 | BE5: 240592 | BF5: 238717 | BG5: 203245 | BH5: 198591 | BI5: 218156 | BJ5: 212527 | BK5: 224886 | BL5: 169727 | BM5: 219718 | BN5: 244837 | BO5: 238341 | BP5: 227506 | BQ5: 190078 | BR5: 198201 | BS5: 218437 | BT5: 189653 | BU5: 216923 | BV5: 215437 | BW5: 212211 | BX5: 224587 | BY5: 232752 | BZ5: 247385 | CA5: 263689 | CB5: 236212 | CC5: 230778 | CD5: 125528 | CE5: 251009 | CF5: 217490 | CG5: 190438 | CH5: 241048 | CI5: 265394 | CJ5: 199507 | CK5: 226899 | CL5: 245361 | CM5: 196872 | CN5: 209683 | CO5: 186604 | CP5: 220140 | CQ5: 239205 | CR5: 241457 | CS5: 252136 | CT5: 188763 | CU5: 212190 | CV5: 205988 | CW5: 152082
A6: 202205 | B6: 230459 | C6: 232179 | D6: 243372 | E6: 247153 | F6: 235283 | G6: 213921 | H6: 243313 | I6: 221155 | J6: 223736 | K6: 219453 | L6: 226991 | M6: 230199 | N6: 281878 | O6: 217837 | P6: 255452 | Q6: 223263 | R6: 213290 | S6: 247943 | T6: 240738 | U6: 208668 | V6: 233379 | W6: 246928 | X6: 228605 | Y6: 250119 | Z6: 244493 | AA6: 276441 | AB6: 237587 | AC6: 229865 | AD6: 267165 | AE6: 271746 | AF6: 239876 | AG6: 241284 | AH6: 230624 | AI6: 241890 | AJ6: 242658 | AK6: 216492 | AL6: 233768 | AM6: 243650 | AN6: 266287 | AO6: 260504 | AP6: 274106 | AQ6: 246282 | AR6: 247478 | AS6: 239237 | AT6: 280979 | AU6: 254378 | AV6: 267992 | AW6: 259733 | AX6: 222157 | AY6: 266561 | AZ6: 121360 | BA6: 201833 | BB6: 253955 | BC6: 210472 | BD6: 238646 | BE6: 266141 | BF6: 263836 | BG6: 218806 | BH6: 222346 | BI6: 233173 | BJ6: 231758 | BK6: 257397 | BL6: 197376 | BM6: 227505 | BN6: 255028 | BO6: 261793 | BP6: 248944 | BQ6: 200496 | BR6: 223966 | BS6: 241790 | BT6: 209089 | BU6: 245409 | BV6: 242019 | BW6: 229077 | BX6: 246261 | BY6: 263106 | BZ6: 276041 | CA6: 301536 | CB6: 261839 | CC6: 248833 | CD6: 141797 | CE6: 263179 | CF6: 245662 | CG6: 215542 | CH6: 269759 | CI6: 282734 | CJ6: 218839 | CK6: 235632 | CL6: 270553 | CM6: 217966 | CN6: 248591 | CO6: 200539 | CP6: 240738 | CQ6: 253489 | CR6: 265253 | CS6: 260086 | CT6: 197345 | CU6: 235492 | CV6: 227374 | CW6: 168814
A7: 202206 | B7: 240831 | C7: 250867 | D7: 271643 | E7: 256001 | F7: 248339 | G7: 214291 | H7: 263046 | I7: 219060 | J7: 231901 | K7: 233961 | L7: 216718 | M7: 242542 | N7: 293980 | O7: 231672 | P7: 271219 | Q7: 225518 | R7: 224673 | S7: 252442 | T7: 254395 | U7: 224257 | V7: 239016 | W7: 248952 | X7: 233007 | Y7: 266879 | Z7: 248121 | AA7: 307335 | AB7: 251051 | AC7: 236101 | AD7: 273893 | AE7: 305653 | AF7: 259660 | AG7: 248084 | AH7: 228378 | AI7: 248329 | AJ7: 241629 | AK7: 232788 | AL7: 260323 | AM7: 239554 | AN7: 275312 | AO7: 279096 | AP7: 292656 | AQ7: 254103 | AR7: 242659 | AS7: 262378 | AT7: 273613 | AU7: 293185 | AV7: 290555 | AW7: 263575 | AX7: 233122 | AY7: 272228 | AZ7: 126835 | BA7: 210448 | BB7: 268268 | BC7: 233586 | BD7: 244324 | BE7: 274705 | BF7: 277162 | BG7: 233259 | BH7: 241849 | BI7: 260474 | BJ7: 252793 | BK7: 261834 | BL7: 214391 | BM7: 231033 | BN7: 265647 | BO7: 278075 | BP7: 267556 | BQ7: 212203 | BR7: 232944 | BS7: 248379 | BT7: 221161 | BU7: 236349 | BV7: 255234 | BW7: 240174 | BX7: 260838 | BY7: 281046 | BZ7: 287006 | CA7: 305610 | CB7: 280027 | CC7: 271243 | CD7: 146537 | CE7: 287528 | CF7: 260999 | CG7: 229708 | CH7: 277587 | CI7: 301535 | CJ7: 226468 | CK7: 246696 | CL7: 272345 | CM7: 226242 | CN7: 259522 | CO7: 210074 | CP7: 253871 | CQ7: 264139 | CR7: 270494 | CS7: 271924 | CT7: 201187 | CU7: 232412 | CV7: 237548 | CW7: 176558
A8: 202207 | B8: 242066 | C8: 256267 | D8: 270606 | E8: 269013 | F8: 247921 | G8: 220984 | H8: 274265 | I8: 230955 | J8: 232450 | K8: 250017 | L8: 234073 | M8: 251124 | N8: 294774 | O8: 237924 | P8: 276232 | Q8: 249277 | R8: 230341 | S8: 256961 | T8: 257779 | U8: 232481 | V8: 251567 | W8: 259751 | X8: 236014 | Y8: 271417 | Z8: 258181 | AA8: 311819 | AB8: 265634 | AC8: 253129 | AD8: 298333 | AE8: 300840 | AF8: 265401 | AG8: 267993 | AH8: 245871 | AI8: 273107 | AJ8: 259859 | AK8: 231768 | AL8: 263948 | AM8: 253956 | AN8: 277099 | AO8: 287335 | AP8: 293297 | AQ8: 276774 | AR8: 257430 | AS8: 265458 | AT8: 271735 | AU8: 283109 | AV8: 310055 | AW8: 273344 | AX8: 242902 | AY8: 287385 | AZ8: 128099 | BA8: 214776 | BB8: 269793 | BC8: 215226 | BD8: 257362 | BE8: 273178 | BF8: 287778 | BG8: 243451 | BH8: 243962 | BI8: 258179 | BJ8: 247415 | BK8: 280832 | BL8: 216372 | BM8: 259424 | BN8: 276091 | BO8: 286383 | BP8: 289911 | BQ8: 218113 | BR8: 243624 | BS8: 246332 | BT8: 219830 | BU8: 245228 | BV8: 257129 | BW8: 243410 | BX8: 248474 | BY8: 283587 | BZ8: 282080 | CA8: 328920 | CB8: 278980 | CC8: 274835 | CD8: 151365 | CE8: 286643 | CF8: 262350 | CG8: 233284 | CH8: 281149 | CI8: 320350 | CJ8: 229008 | CK8: 259065 | CL8: 286068 | CM8: 235506 | CN8: 252931 | CO8: 220547 | CP8: 251521 | CQ8: 281979 | CR8: 285479 | CS8: 276459 | CT8: 202171 | CU8: 252903 | CV8: 247007 | CW8: 176327
A9: 202208 | B9: 229065 | C9: 224536 | D9: 244613 | E9: 234947 | F9: 221748 | G9: 192797 | H9: 241683 | I9: 204330 | J9: 198575 | K9: 204873 | L9: 205732 | M9: 212507 | N9: 269126 | O9: 204886 | P9: 253225 | Q9: 209248 | R9: 207763 | S9: 214826 | T9: 227140 | U9: 208682 | V9: 223358 | W9: 232827 | X9: 211616 | Y9: 232707 | Z9: 233112 | AA9: 268162 | AB9: 225646 | AC9: 228744 | AD9: 251013 | AE9: 258288 | AF9: 227462 | AG9: 224241 | AH9: 213512 | AI9: 228605 | AJ9: 219847 | AK9: 210189 | AL9: 220221 | AM9: 213672 | AN9: 242366 | AO9: 242182 | AP9: 249070 | AQ9: 236779 | AR9: 224693 | AS9: 247379 | AT9: 249449 | AU9: 257067 | AV9: 256565 | AW9: 241520 | AX9: 212766 | AY9: 249683 | AZ9: 111778 | BA9: 193042 | BB9: 249859 | BC9: 214698 | BD9: 217010 | BE9: 249588 | BF9: 245822 | BG9: 208857 | BH9: 213159 | BI9: 231829 | BJ9: 221376 | BK9: 246090 | BL9: 187262 | BM9: 219554 | BN9: 242371 | BO9: 249351 | BP9: 231699 | BQ9: 187358 | BR9: 205579 | BS9: 218542 | BT9: 197979 | BU9: 223318 | BV9: 229019 | BW9: 214351 | BX9: 235364 | BY9: 247421 | BZ9: 249893 | CA9: 270412 | CB9: 239517 | CC9: 241682 | CD9: 130294 | CE9: 275631 | CF9: 229720 | CG9: 203084 | CH9: 245200 | CI9: 277150 | CJ9: 197363 | CK9: 227921 | CL9: 246315 | CM9: 218094 | CN9: 217216 | CO9: 195236 | CP9: 222767 | CQ9: 246061 | CR9: 251687 | CS9: 245817 | CT9: 190502 | CU9: 214681 | CV9: 210831 | CW9: 159785
A10: 202209 | B10: 212133 | C10: 219688 | D10: 231185 | E10: 226241 | F10: 221234 | G10: 186116 | H10: 227440 | I10: 192105 | J10: 199923 | K10: 201743 | L10: 188781 | M10: 207630 | N10: 257195 | O10: 192838 | P10: 241123 | Q10: 196532 | R10: 193170 | S10: 207638 | T10: 219835 | U10: 201522 | V10: 216715 | W10: 219723 | X10: 203874 | Y10: 236276 | Z10: 224798 | AA10: 252963 | AB10: 226415 | AC10: 214684 | AD10: 242067 | AE10: 250644 | AF10: 219130 | AG10: 211459 | AH10: 196808 | AI10: 220232 | AJ10: 201819 | AK10: 199983 | AL10: 223732 | AM10: 205484 | AN10: 226014 | AO10: 237459 | AP10: 247093 | AQ10: 225835 | AR10: 215797 | AS10: 243285 | AT10: 238324 | AU10: 253990 | AV10: 243992 | AW10: 223761 | AX10: 197053 | AY10: 240399 | AZ10: 109790 | BA10: 188991 | BB10: 238100 | BC10: 189892 | BD10: 219018 | BE10: 224745 | BF10: 234002 | BG10: 198942 | BH10: 202325 | BI10: 211326 | BJ10: 212635 | BK10: 227945 | BL10: 183457 | BM10: 208160 | BN10: 225785 | BO10: 241765 | BP10: 221325 | BQ10: 185454 | BR10: 197973 | BS10: 220240 | BT10: 189985 | BU10: 223866 | BV10: 213895 | BW10: 200494 | BX10: 218894 | BY10: 230933 | BZ10: 239915 | CA10: 263938 | CB10: 229687 | CC10: 232932 | CD10: 126822 | CE10: 242449 | CF10: 219418 | CG10: 183413 | CH10: 243685 | CI10: 267883 | CJ10: 193921 | CK10: 219502 | CL10: 231751 | CM10: 208961 | CN10: 227607 | CO10: 182378 | CP10: 210971 | CQ10: 233086 | CR10: 229529 | CS10: 233785 | CT10: 167682 | CU10: 199011 | CV10: 206133 | CW10: 152902
A11: 202210 | B11: 202011 | C11: 204975 | D11: 218135 | E11: 211301 | F11: 210625 | G11: 180259 | H11: 227404 | I11: 182876 | J11: 190913 | K11: 190810 | L11: 209694 | M11: 197995 | N11: 250090 | O11: 196772 | P11: 229890 | Q11: 195741 | R11: 189020 | S11: 212352 | T11: 202669 | U11: 178744 | V11: 203861 | W11: 204508 | X11: 198946 | Y11: 211821 | Z11: 206918 | AA11: 231141 | AB11: 222847 | AC11: 204267 | AD11: 229294 | AE11: 252490 | AF11: 201846 | AG11: 210321 | AH11: 192227 | AI11: 211453 | AJ11: 199808 | AK11: 183489 | AL11: 219431 | AM11: 197194 | AN11: 222050 | AO11: 229461 | AP11: 227364 | AQ11: 218563 | AR11: 211506 | AS11: 216279 | AT11: 231143 | AU11: 240259 | AV11: 229694 | AW11: 224030 | AX11: 189130 | AY11: 226990 | AZ11: 102675 | BA11: 170654 | BB11: 225552 | BC11: 183286 | BD11: 204008 | BE11: 237151 | BF11: 232255 | BG11: 185438 | BH11: 198258 | BI11: 200268 | BJ11: 195372 | BK11: 215801 | BL11: 167782 | BM11: 193887 | BN11: 224019 | BO11: 228702 | BP11: 219577 | BQ11: 172574 | BR11: 193542 | BS11: 207411 | BT11: 179531 | BU11: 187807 | BV11: 209356 | BW11: 205658 | BX11: 223377 | BY11: 222397 | BZ11: 236988 | CA11: 243917 | CB11: 225995 | CC11: 221011 | CD11: 123495 | CE11: 227666 | CF11: 213145 | CG11: 182159 | CH11: 228509 | CI11: 236613 | CJ11: 190011 | CK11: 197919 | CL11: 238030 | CM11: 186708 | CN11: 214427 | CO11: 178349 | CP11: 205468 | CQ11: 229879 | CR11: 226655 | CS11: 233597 | CT11: 174777 | CU11: 202143 | CV11: 195542 | CW11: 144189
A12: 202211 | B12: 191296 | C12: 195505 | D12: 209809 | E12: 204015 | F12: 197972 | G12: 174650 | H12: 207363 | I12: 184187 | J12: 174808 | K12: 182927 | L12: 167785 | M12: 186050 | N12: 225620 | O12: 180311 | P12: 225116 | Q12: 184537 | R12: 170349 | S12: 198584 | T12: 195456 | U12: 179560 | V12: 188448 | W12: 196385 | X12: 170177 | Y12: 199297 | Z12: 200732 | AA12: 228501 | AB12: 196867 | AC12: 193001 | AD12: 208558 | AE12: 223783 | AF12: 194357 | AG12: 202017 | AH12: 184442 | AI12: 200237 | AJ12: 189471 | AK12: 177804 | AL12: 194964 | AM12: 192547 | AN12: 216053 | AO12: 221124 | AP12: 222645 | AQ12: 207309 | AR12: 197983 | AS12: 220496 | AT12: 224513 | AU12: 210760 | AV12: 229744 | AW12: 203821 | AX12: 180592 | AY12: 212225 | AZ12: 98025 | BA12: 171955 | BB12: 217913 | BC12: 177199 | BD12: 196520 | BE12: 224828 | BF12: 213120 | BG12: 180999 | BH12: 184079 | BI12: 198805 | BJ12: 190699 | BK12: 210668 | BL12: 167701 | BM12: 190134 | BN12: 220670 | BO12: 223035 | BP12: 202683 | BQ12: 169341 | BR12: 184515 | BS12: 199965 | BT12: 168090 | BU12: 198537 | BV12: 199202 | BW12: 183314 | BX12: 197469 | BY12: 219290 | BZ12: 218560 | CA12: 246163 | CB12: 212680 | CC12: 212634 | CD12: 114465 | CE12: 215747 | CF12: 203652 | CG12: 176721 | CH12: 228531 | CI12: 234622 | CJ12: 177222 | CK12: 199317 | CL12: 204700 | CM12: 191755 | CN12: 195629 | CO12: 166527 | CP12: 202182 | CQ12: 203243 | CR12: 210514 | CS12: 222522 | CT12: 171027 | CU12: 191128 | CV12: 190503 | CW12: 136194
A13: 202212 | B13: 183842 | C13: 187306 | D13: 198017 | E13: 204808 | F13: 196359 | G13: 161085 | H13: 197005 | I13: 177515 | J13: 178840 | K13: 179254 | L13: 170816 | M13: 185460 | N13: 221651 | O13: 175611 | P13: 209787 | Q13: 172061 | R13: 170253 | S13: 183815 | T13: 185726 | U13: 173386 | V13: 187446 | W13: 193911 | X13: 167404 | Y13: 204422 | Z13: 199685 | AA13: 219882 | AB13: 194255 | AC13: 193932 | AD13: 212688 | AE13: 225021 | AF13: 200575 | AG13: 195057 | AH13: 182853 | AI13: 192814 | AJ13: 184874 | AK13: 178059 | AL13: 188224 | AM13: 182260 | AN13: 197384 | AO13: 208590 | AP13: 222653 | AQ13: 209365 | AR13: 194208 | AS13: 207185 | AT13: 205895 | AU13: 207403 | AV13: 226032 | AW13: 213164 | AX13: 179907 | AY13: 204575 | AZ13: 96220 | BA13: 164218 | BB13: 203461 | BC13: 185917 | BD13: 194261 | BE13: 213346 | BF13: 213054 | BG13: 174251 | BH13: 177568 | BI13: 195928 | BJ13: 188448 | BK13: 202026 | BL13: 162298 | BM13: 180212 | BN13: 205648 | BO13: 205279 | BP13: 202567 | BQ13: 161466 | BR13: 179589 | BS13: 189372 | BT13: 169196 | BU13: 191809 | BV13: 192145 | BW13: 180621 | BX13: 213002 | BY13: 209312 | BZ13: 214938 | CA13: 229031 | CB13: 211269 | CC13: 205572 | CD13: 113312 | CE13: 214857 | CF13: 207339 | CG13: 170278 | CH13: 214867 | CI13: 223862 | CJ13: 170261 | CK13: 187935 | CL13: 205697 | CM13: 174941 | CN13: 198468 | CO13: 166017 | CP13: 194069 | CQ13: 206243 | CR13: 205201 | CS13: 210487 | CT13: 136816 | CU13: 185017 | CV13: 182124 | CW13: 136495
... A37: 202412 | B37: 177938 | C37: 182064 | D37: 186283 | E37: 191119 | F37: 182722 | G37: 156171 | H37: 190845 | I37: 163652 | J37: 169485 | K37: 177594 | L37: 148080 | M37: 177471 | N37: 221755 | O37: 169693 | P37: 188006 | Q37: 172694 | R37: 165765 | S37: 161853 | T37: 169302 | U37: 168527 | V37: 177562 | W37: 185679 | X37: 152554 | Y37: 194203 | Z37: 183730 | AA37: 230580 | AB37: 195392 | AC37: 182504 | AD37: 208974 | AE37: 216190 | AF37: 183257 | AG37: 190607 | AH37: 173486 | AI37: 184161 | AJ37: 186419 | AK37: 158033 | AL37: 195072 | AM37: 172984 | AN37: 178806 | AO37: 211554 | AP37: 203718 | AQ37: 181846 | AR37: 184065 | AS37: 191149 | AT37: 198999 | AU37: 201917 | AV37: 200023 | AW37: 194216 | AX37: 172400 | AY37: 201762 | AZ37: 93524 | BA37: 156612 | BB37: 194584 | BC37: 163610 | BD37: 187526 | BE37: 203152 | BF37: 206997 | BG37: 166893 | BH37: 179471 | BI37: 174300 | BJ37: 175135 | BK37: 197380 | BL37: 147472 | BM37: 173270 | BN37: 192787 | BO37: 198211 | BP37: 194167 | BQ37: 161102 | BR37: 165635 | BS37: 186591 | BT37: 159230 | BU37: 169647 | BV37: 180522 | BW37: 177855 | BX37: 187537 | BY37: 202652 | BZ37: 200291 | CA37: 236444 | CB37: 198557 | CC37: 180973 | CD37: 104094 | CE37: 199952 | CF37: 191724 | CG37: 165265 | CH37: 204597 | CI37: 230445 | CJ37: 166402 | CK37: 183075 | CL37: 188341 | CM37: 159121 | CN37: 193313 | CO37: 159498 | CP37: 176135 | CQ37: 202536 | CR37: 196221 | CS37: 205185 | CT37: 145696 | CU37: 176628 | CV37: 168767 | CW37: 126276

Sheet soda_sales
A1: year_month | B1: total_sales_1 | C1: total_sales_2 | D1: total_sales_3 | E1: total_sales_4 | F1: total_sales_5 | G1: total_sales_6 | H1: total_sales_7 | I1: total_sales_8 | J1: total_sales_9 | K1: total_sales_10 | L1: total_sales_11 | M1: total_sales_12 | N1: total_sales_13 | O1: total_sales_14 | P1: total_sales_15 | Q1: total_sales_16 | R1: total_sales_17 | S1: total_sales_18 | T1: total_sales_19 | U1: total_sales_20 | V1: total_sales_21 | W1: total_sales_22 | X1: total_sales_23 | Y1: total_sales_24 | Z1: total_sales_25 | AA1: total_sales_26 | AB1: total_sales_27 | AC1: total_sales_28 | AD1: total_sales_29 | AE1: total_sales_30 | AF1: total_sales_31 | AG1: total_sales_32 | AH1: total_sales_33 | AI1: total_sales_34 | AJ1: total_sales_35 | AK1: total_sales_36 | AL1: total_sales_37 | AM1: total_sales_38 | AN1: total_sales_39 | AO1: total_sales_40 | AP1: total_sales_41 | AQ1: total_sales_42 | AR1: total_sales_43 | AS1: total_sales_44 | AT1: total_sales_45 | AU1: total_sales_46 | AV1: total_sales_47 | AW1: total_sales_48 | AX1: total_sales_49 | AY1: total_sales_50 | AZ1: total_sales_51 | BA1: total_sales_52 | BB1: total_sales_53 | BC1: total_sales_54 | BD1: total_sales_55 | BE1: total_sales_56 | BF1: total_sales_57 | BG1: total_sales_58 | BH1: total_sales_59 | BI1: total_sales_60 | BJ1: total_sales_61 | BK1: total_sales_62 | BL1: total_sales_63 | BM1: total_sales_64 | BN1: total_sales_65 | BO1: total_sales_66 | BP1: total_sales_67 | BQ1: total_sales_68 | BR1: total_sales_69 | BS1: total_sales_70 | BT1: total_sales_71 | BU1: total_sales_72 | BV1: total_sales_73 | BW1: total_sales_74 | BX1: total_sales_75 | BY1: total_sales_76 | BZ1: total_sales_77 | CA1: total_sales_78 | CB1: total_sales_79 | CC1: total_sales_80 | CD1: total_sales_81 | CE1: total_sales_82 | CF1: total_sales_83 | CG1: total_sales_84 | CH1: total_sales_85 | CI1: total_sales_86 | CJ1: total_sales_87 | CK1: total_sales_88 | CL1: total_sales_89 | CM1: total_sales_90 | CN1: total_sales_91 | CO1: total_sales_92 | CP1: total_sales_93 | CQ1: total_sales_94 | CR1: total_sales_95 | CS1: total_sales_96 | CT1: total_sales_97 | CU1: total_sales_98 | CV1: total_sales_99 | CW1: total_sales_100
A2: 202201 | B2: 101748.95 | C2: 100953.27 | D2: 98235.735 | E2: 94517.517 | F2: 98406.356 | G2: 88596.745 | H2: 100449.56 | I2: 85317.254 | J2: 92096.802 | K2: 96616.246 | L2: 94427.349 | M2: 95517.461 | N2: 106430.68 | O2: 96968.045 | P2: 108551.47 | Q2: 97480.652 | R2: 86318.643 | S2: 103595.66 | T2: 97692.857 | U2: 91907.332 | V2: 93168.592 | W2: 97330.351 | X2: 93648.255 | Y2: 101018.67 | Z2: 103767.58 | AA2: 107931.55 | AB2: 105350.45 | AC2: 102650.73 | AD2: 107383.14 | AE2: 110609.8 | AF2: 94093.203 | AG2: 102336.01 | AH2: 95466.432 | AI2: 100520.92 | AJ2: 93393.683 | AK2: 87579.468 | AL2: 105847.26 | AM2: 88780.377 | AN2: 104919.99 | AO2: 108277.92 | AP2: 111798.31 | AQ2: 106997.75 | AR2: 96442.814 | AS2: 107275.73 | AT2: 106501.3 | AU2: 105152.97 | AV2: 106358.14 | AW2: 104067.23 | AX2: 92092.356 | AY2: 106907.58 | AZ2: 48509.86 | BA2: 89382.82 | BB2: 107638.57 | BC2: 95560.436 | BD2: 101784.18 | BE2: 104534.74 | BF2: 106654.53 | BG2: 93416.343 | BH2: 94141.505 | BI2: 102230.82 | BJ2: 92647.957 | BK2: 106772.78 | BL2: 84479.612 | BM2: 96307.959 | BN2: 105779.64 | BO2: 106399.14 | BP2: 104107.81 | BQ2: 86616.813 | BR2: 94442.671 | BS2: 104195.2 | BT2: 85892.638 | BU2: 104539.08 | BV2: 99112.079 | BW2: 97644.146 | BX2: 106545.4 | BY2: 101346.34 | BZ2: 107825.15 | CA2: 109367.76 | CB2: 96776.983 | CC2: 100815.45 | CD2: 58498.475 | CE2: 105432.97 | CF2: 100285.99 | CG2: 94456.121 | CH2: 107360.31 | CI2: 109309.59 | CJ2: 93657.026 | CK2: 100812.64 | CL2: 106174.92 | CM2: 94878.026 | CN2: 104097.47 | CO2: 89157.703 | CP2: 95479.049 | CQ2: 102015.77 | CR2: 94890.666 | CS2: 106225.88 | CT2: 82398.574 | CU2: 95907.958 | CV2: 93291.579 | CW2: 70783.356
A3: 202202 | B3: 109343.61 | C3: 111309.18 | D3: 114631.17 | E3: 105716.92 | F3: 110354.6 | G3: 96726.457 | H3: 116446.38 | I3: 99002.526 | J3: 106271 | K3: 108360.77 | L3: 106815.29 | M3: 108101.81 | N3: 118177.22 | O3: 108281.1 | P3: 125116.92 | Q3: 112155.82 | R3: 98158.812 | S3: 116398.33 | T3: 111954.5 | U3: 101454.92 | V3: 106346.52 | W3: 110544.49 | X3: 104637.14 | Y3: 111079.85 | Z3: 120114.47 | AA3: 124310.48 | AB3: 119108.85 | AC3: 116948.03 | AD3: 122156.74 | AE3: 120253.26 | AF3: 106583.09 | AG3: 118081.9 | AH3: 107609.74 | AI3: 116697.22 | AJ3: 104701.19 | AK3: 97552.641 | AL3: 121043.77 | AM3: 103025.85 | AN3: 120657.39 | AO3: 120179.58 | AP3: 126039.59 | AQ3: 119738.31 | AR3: 114568.39 | AS3: 123044.55 | AT3: 120242.04 | AU3: 119442.73 | AV3: 116886.72 | AW3: 117670.82 | AX3: 104410.92 | AY3: 121835.02 | AZ3: 55000.713 | BA3: 99997.48 | BB3: 124622.25 | BC3: 104869.56 | BD3: 114812.43 | BE3: 117920.68 | BF3: 120090.9 | BG3: 108502.18 | BH3: 108203.15 | BI3: 116774.83 | BJ3: 103654.03 | BK3: 121401.86 | BL3: 96201.943 | BM3: 112977.05 | BN3: 116268.36 | BO3: 120770.46 | BP3: 117930.4 | BQ3: 98613.166 | BR3: 105910.36 | BS3: 120045.94 | BT3: 98723.872 | BU3: 112120.31 | BV3: 110012.65 | BW3: 105456.17 | BX3: 118180.01 | BY3: 113997.11 | BZ3: 125684.92 | CA3: 124696.38 | CB3: 111722.87 | CC3: 111376.02 | CD3: 67776.589 | CE3: 121381.9 | CF3: 112545.8 | CG3: 107100.84 | CH3: 124422.2 | CI3: 122784.3 | CJ3: 106673.02 | CK3: 113558.22 | CL3: 125283.29 | CM3: 110999.37 | CN3: 121216.68 | CO3: 101406.5 | CP3: 108965.25 | CQ3: 114716.29 | CR3: 109809.85 | CS3: 122266.12 | CT3: 94522.808 | CU3: 106409.44 | CV3: 104639.78 | CW3: 78923.895
A4: 202203 | B4: 126977.72 | C4: 134594.64 | D4: 131039.33 | E4: 123423.98 | F4: 135277.14 | G4: 114735.51 | H4: 137622.32 | I4: 116773.05 | J4: 121553.25 | K4: 130180.53 | L4: 129375.03 | M4: 128648.8 | N4: 139882.61 | O4: 124991.46 | P4: 147224.16 | Q4: 131885.51 | R4: 116746 | S4: 137536.11 | T4: 130690.94 | U4: 121096.08 | V4: 123152.9 | W4: 132042.88 | X4: 120509.87 | Y4: 130964.04 | Z4: 139343.79 | AA4: 145147.56 | AB4: 141214.15 | AC4: 133015.15 | AD4: 142348.77 | AE4: 150027.27 | AF4: 129207.38 | AG4: 137337.23 | AH4: 130910.25 | AI4: 135566.06 | AJ4: 119173.55 | AK4: 113876.47 | AL4: 141094.44 | AM4: 123702.06 | AN4: 141385.49 | AO4: 144375.9 | AP4: 145478.99 | AQ4: 140577.62 | AR4: 132566.78 | AS4: 138720.67 | AT4: 144257.19 | AU4: 141316.75 | AV4: 138516.85 | AW4: 139043.44 | AX4: 125197.34 | AY4: 141483.67 | AZ4: 63301.738 | BA4: 120050.7 | BB4: 145780.96 | BC4: 118767.4 | BD4: 138382.7 | BE4: 138959.8 | BF4: 143489.6 | BG4: 125897.23 | BH4: 126325.62 | BI4: 136030.58 | BJ4: 119167.33 | BK4: 145000.67 | BL4: 112598.39 | BM4: 132073.24 | BN4: 140679.51 | BO4: 141077.95 | BP4: 139130.15 | BQ4: 118194.21 | BR4: 124292 | BS4: 140505.45 | BT4: 120361.22 | BU4: 134940.3 | BV4: 130944.5 | BW4: 124107.01 | BX4: 144355.47 | BY4: 138621.2 | BZ4: 146615.58 | CA4: 149907.67 | CB4: 127314.77 | CC4: 138545.37 | CD4: 81689.495 | CE4: 139130.6 | CF4: 134791.74 | CG4: 123962.05 | CH4: 143178.79 | CI4: 143511.08 | CJ4: 119389.8 | CK4: 134984.26 | CL4: 150803.74 | CM4: 123913.74 | CN4: 143557.84 | CO4: 116359.26 | CP4: 128229.1 | CQ4: 135621.25 | CR4: 126577.1 | CS4: 144304.44 | CT4: 106423.01 | CU4: 123353.36 | CV4: 124753.67 | CW4: 90725.807
A5: 202204 | B5: 150537.76 | C5: 155395.96 | D5: 157504.2 | E5: 144846.18 | F5: 155656.9 | G5: 134978.14 | H5: 161388.64 | I5: 136576.7 | J5: 140196.05 | K5: 152075.77 | L5: 143118.81 | M5: 152919.68 | N5: 163725.54 | O5: 148492.71 | P5: 168015.13 | Q5: 152730.98 | R5: 135517.86 | S5: 157948.6 | T5: 153577.38 | U5: 143957.37 | V5: 141966.63 | W5: 149993.85 | X5: 139467.41 | Y5: 154622.79 | Z5: 162320.21 | AA5: 172050.84 | AB5: 160759.56 | AC5: 157984.04 | AD5: 164395.27 | AE5: 167762.22 | AF5: 144569.89 | AG5: 162258.75 | AH5: 149209.08 | AI5: 157771.68 | AJ5: 143994.3 | AK5: 134893.25 | AL5: 165581.83 | AM5: 138286.03 | AN5: 164113.26 | AO5: 167945.75 | AP5: 171784.02 | AQ5: 162018.67 | AR5: 153554.9 | AS5: 160830.69 | AT5: 167091.26 | AU5: 163485.68 | AV5: 169130 | AW5: 164970.88 | AX5: 147458.15 | AY5: 164342.41 | AZ5: 77438.605 | BA5: 138189.75 | BB5: 167501.09 | BC5: 137790.04 | BD5: 159631.14 | BE5: 166055.37 | BF5: 164803.65 | BG5: 145922.48 | BH5: 151690.54 | BI5: 160869.66 | BJ5: 137214.63 | BK5: 170262.04 | BL5: 125095.43 | BM5: 154293.65 | BN5: 163537.31 | BO5: 164668.06 | BP5: 163590.03 | BQ5: 138027.35 | BR5: 144686.59 | BS5: 163523.71 | BT5: 133842.65 | BU5: 157396.42 | BV5: 149770.27 | BW5: 151329.04 | BX5: 165629.77 | BY5: 154885.66 | BZ5: 174316.31 | CA5: 166499.46 | CB5: 149120.81 | CC5: 157273.84 | CD5: 93732.419 | CE5: 164678.86 | CF5: 153592.07 | CG5: 140469.31 | CH5: 167280.26 | CI5: 171301.63 | CJ5: 144782.85 | CK5: 156490.38 | CL5: 173386.92 | CM5: 144284.12 | CN5: 162066.95 | CO5: 141044.25 | CP5: 148980.28 | CQ5: 156706.26 | CR5: 150270.26 | CS5: 166356.58 | CT5: 132198.47 | CU5: 147343.48 | CV5: 144591.26 | CW5: 107540.02
A6: 202205 | B6: 172083.43 | C6: 167743.05 | D6: 170515 | E6: 158642.12 | F6: 165984.36 | G6: 149266.73 | H6: 173040.94 | I6: 148540.12 | J6: 157975.96 | K6: 162330.45 | L6: 164684.66 | M6: 165451.25 | N6: 178521.59 | O6: 161858.44 | P6: 185918.81 | Q6: 168556.13 | R6: 149790.41 | S6: 177639.93 | T6: 169938.63 | U6: 150522.73 | V6: 158722.9 | W6: 164452.99 | X6: 158505.24 | Y6: 173201.5 | Z6: 179974.12 | AA6: 184224.47 | AB6: 176290.33 | AC6: 171206.21 | AD6: 179035.44 | AE6: 184912.35 | AF6: 158519.39 | AG6: 174823.05 | AH6: 165602.87 | AI6: 173199.38 | AJ6: 160337.44 | AK6: 150587.24 | AL6: 177918.38 | AM6: 151986.99 | AN6: 179133.62 | AO6: 184376.95 | AP6: 187844.09 | AQ6: 177612.03 | AR6: 168120.87 | AS6: 171022 | AT6: 189930.83 | AU6: 178204.34 | AV6: 183275.58 | AW6: 177900.45 | AX6: 156830.64 | AY6: 182310.53 | AZ6: 82576.9 | BA6: 150235.84 | BB6: 180954.46 | BC6: 158460.86 | BD6: 172650.97 | BE6: 178519.97 | BF6: 181848 | BG6: 156666.65 | BH6: 158363.37 | BI6: 175304.52 | BJ6: 157540.66 | BK6: 187028.53 | BL6: 143183.24 | BM6: 167505.89 | BN6: 174422.32 | BO6: 181511.71 | BP6: 175756.23 | BQ6: 152169.31 | BR6: 164163.11 | BS6: 181418.24 | BT6: 149059.75 | BU6: 177768.93 | BV6: 171154 | BW6: 162097.47 | BX6: 179590.36 | BY6: 168883.38 | BZ6: 190441.56 | CA6: 188137.05 | CB6: 168862.27 | CC6: 171062.2 | CD6: 101841.04 | CE6: 180846.2 | CF6: 170482.78 | CG6: 162531.14 | CH6: 186030 | CI6: 185035.48 | CJ6: 160098.35 | CK6: 170310.28 | CL6: 190212.47 | CM6: 160329.29 | CN6: 180512.57 | CO6: 150531.05 | CP6: 164244.5 | CQ6: 171426.49 | CR6: 164288.57 | CS6: 178942.5 | CT6: 142154.27 | CU6: 159648.6 | CV6: 156391.64 | CW6: 119766.71
A7: 202206 | B7: 174666.44 | C7: 174091.2 | D7: 185313.95 | E7: 170582.8 | F7: 174269.46 | G7: 154751.47 | H7: 183399.92 | I7: 150752.65 | J7: 164908.32 | K7: 171030.57 | L7: 162778.82 | M7: 173330.88 | N7: 181373.32 | O7: 168968.02 | P7: 192094.69 | Q7: 168745.73 | R7: 154285.94 | S7: 182070.78 | T7: 177978.8 | U7: 156441.09 | V7: 163975.17 | W7: 167679.85 | X7: 166150.52 | Y7: 178941.05 | Z7: 178578.16 | AA7: 199738.62 | AB7: 184586.76 | AC7: 176938.7 | AD7: 185004.09 | AE7: 195248.77 | AF7: 174396.7 | AG7: 187081.38 | AH7: 168755.73 | AI7: 178656.16 | AJ7: 162984.52 | AK7: 153198.5 | AL7: 189305.71 | AM7: 159959.39 | AN7: 189189.65 | AO7: 193003.62 | AP7: 192834.36 | AQ7: 186986.23 | AR7: 168446.19 | AS7: 182235.06 | AT7: 189320.29 | AU7: 196897.55 | AV7: 193290.18 | AW7: 180331.09 | AX7: 164716.07 | AY7: 184975.11 | AZ7: 87899.755 | BA7: 160645.21 | BB7: 192574.32 | BC7: 169881.7 | BD7: 175925.84 | BE7: 189518.85 | BF7: 193047.83 | BG7: 166870.97 | BH7: 172709.94 | BI7: 180326.43 | BJ7: 165177.37 | BK7: 196150.06 | BL7: 151604.33 | BM7: 171883.85 | BN7: 182895.69 | BO7: 189674.12 | BP7: 189114.2 | BQ7: 159535.05 | BR7: 165651.5 | BS7: 185862.6 | BT7: 158229.17 | BU7: 177713.01 | BV7: 174908.86 | BW7: 169284.01 | BX7: 192109.87 | BY7: 179195.37 | BZ7: 194951.58 | CA7: 192750.79 | CB7: 173282.31 | CC7: 183303.58 | CD7: 107393.17 | CE7: 188983.65 | CF7: 179360.78 | CG7: 169194.17 | CH7: 190839.44 | CI7: 192412.52 | CJ7: 167101.39 | CK7: 179048.99 | CL7: 193914.95 | CM7: 165541.48 | CN7: 188825.85 | CO7: 154102.73 | CP7: 168046.82 | CQ7: 183342.67 | CR7: 171967.67 | CS7: 189875.38 | CT7: 145578.34 | CU7: 169325.34 | CV7: 169173.11 | CW7: 127586.21
A8: 202207 | B8: 179850.97 | C8: 182384.29 | D8: 185060.61 | E8: 173650.79 | F8: 178134 | G8: 157222.14 | H8: 189770.33 | I8: 157226.89 | J8: 166878.36 | K8: 179900.27 | L8: 173783.68 | M8: 172827.61 | N8: 190232.94 | O8: 173027.52 | P8: 199482.9 | Q8: 181799.57 | R8: 161425.5 | S8: 187388.07 | T8: 183508.47 | U8: 164941.68 | V8: 169634.02 | W8: 175287.98 | X8: 170736.39 | Y8: 184949.92 | Z8: 187746.27 | AA8: 200267.48 | AB8: 194104.33 | AC8: 185786.48 | AD8: 191755.61 | AE8: 200572.29 | AF8: 177186.14 | AG8: 194060.43 | AH8: 175407.91 | AI8: 180967.82 | AJ8: 174109.65 | AK8: 158738.4 | AL8: 191004.42 | AM8: 168295.08 | AN8: 196849.06 | AO8: 201226.11 | AP8: 202537.1 | AQ8: 195748.1 | AR8: 178817.87 | AS8: 186229.63 | AT8: 193574.34 | AU8: 196054.14 | AV8: 201614.9 | AW8: 188330.32 | AX8: 168230.14 | AY8: 196013.83 | AZ8: 85836.955 | BA8: 161539.39 | BB8: 191010.97 | BC8: 162478.77 | BD8: 189969.28 | BE8: 190350.25 | BF8: 196160.38 | BG8: 171561.3 | BH8: 174252.54 | BI8: 188110.28 | BJ8: 172055.97 | BK8: 203499.39 | BL8: 155253.17 | BM8: 185931.83 | BN8: 187133.81 | BO8: 194438.42 | BP8: 197455.77 | BQ8: 163650.35 | BR8: 171700.24 | BS8: 190180.81 | BT8: 155559.18 | BU8: 183641.79 | BV8: 174681.13 | BW8: 174992.34 | BX8: 188356.94 | BY8: 186404.53 | BZ8: 200529.1 | CA8: 207207.14 | CB8: 177844.97 | CC8: 186303.85 | CD8: 113407.04 | CE8: 192075.8 | CF8: 180741.38 | CG8: 174951.13 | CH8: 201721.01 | CI8: 201293.96 | CJ8: 173466.79 | CK8: 183073.43 | CL8: 205854.79 | CM8: 172898.76 | CN8: 195137.69 | CO8: 165246.94 | CP8: 175198.46 | CQ8: 187404.52 | CR8: 174827.68 | CS8: 196652.02 | CT8: 147736.62 | CU8: 171628.16 | CV8: 177215.1 | CW8: 123136.74
A9: 202208 | B9: 160313.58 | C9: 158994.89 | D9: 165642.93 | E9: 151370.57 | F9: 156311.86 | G9: 143034.29 | H9: 168276.06 | I9: 141428.81 | J9: 145734.87 | K9: 153271.13 | L9: 152630.51 | M9: 154853.99 | N9: 170732.52 | O9: 151553.87 | P9: 175302.16 | Q9: 159546.98 | R9: 136307.66 | S9: 162249.22 | T9: 161484.06 | U9: 147113.5 | V9: 150068.01 | W9: 156103.33 | X9: 151777.27 | Y9: 158158.05 | Z9: 166112.16 | AA9: 177666.39 | AB9: 165653.32 | AC9: 164986.09 | AD9: 169951.56 | AE9: 174222.32 | AF9: 151158.7 | AG9: 166806.25 | AH9: 152689.87 | AI9: 161778.34 | AJ9: 145243.98 | AK9: 136938.31 | AL9: 170185.96 | AM9: 141906.38 | AN9: 170468.85 | AO9: 175466.2 | AP9: 175350.13 | AQ9: 171266.23 | AR9: 156210.49 | AS9: 170230.78 | AT9: 172784.56 | AU9: 173204.55 | AV9: 174107.71 | AW9: 164581.44 | AX9: 154117.29 | AY9: 168334.39 | AZ9: 76640.672 | BA9: 140820.6 | BB9: 173057.65 | BC9: 155987.75 | BD9: 164019.29 | BE9: 171445.61 | BF9: 172398.81 | BG9: 149091.73 | BH9: 152313.38 | BI9: 164782.51 | BJ9: 149617.94 | BK9: 176830.4 | BL9: 135556.48 | BM9: 158339.14 | BN9: 164837.22 | BO9: 173180.61 | BP9: 170276.05 | BQ9: 139372.39 | BR9: 149944.49 | BS9: 166974.45 | BT9: 137531.24 | BU9: 165889.41 | BV9: 152230.86 | BW9: 153530.73 | BX9: 173932.84 | BY9: 160257.57 | BZ9: 176565.67 | CA9: 173626.83 | CB9: 154741.95 | CC9: 164998.99 | CD9: 94649.52 | CE9: 177957.62 | CF9: 157340.2 | CG9: 150432.08 | CH9: 170018.47 | CI9: 178502.24 | CJ9: 144612.23 | CK9: 161546.24 | CL9: 178893.09 | CM9: 154023.32 | CN9: 170788.88 | CO9: 143596.16 | CP9: 151383.18 | CQ9: 164437.14 | CR9: 156936.79 | CS9: 172609.42 | CT9: 135943.82 | CU9: 148367.63 | CV9: 151446.5 | CW9: 113515.8
A10: 202209 | B10: 152126.03 | C10: 153048.59 | D10: 155163.58 | E10: 140918.49 | F10: 150291.46 | G10: 132278.14 | H10: 159014.76 | I10: 133830.22 | J10: 143016.64 | K10: 146477.67 | L10: 140474.31 | M10: 148423.79 | N10: 161178.29 | O10: 141345.27 | P10: 171634.39 | Q10: 148825.78 | R10: 135725.69 | S10: 156448.63 | T10: 155034.21 | U10: 140569.61 | V10: 144706.33 | W10: 145676.06 | X10: 142908.45 | Y10: 154312.06 | Z10: 161198 | AA10: 170043.07 | AB10: 162177.91 | AC10: 154182.32 | AD10: 159985.19 | AE10: 165422.7 | AF10: 146936.13 | AG10: 157441.97 | AH10: 145088.26 | AI10: 156144.83 | AJ10: 141263.52 | AK10: 136173.39 | AL10: 162785.64 | AM10: 136626.38 | AN10: 160110.15 | AO10: 164419.18 | AP10: 170687.64 | AQ10: 163033.07 | AR10: 149381.43 | AS10: 163266.56 | AT10: 168300.33 | AU10: 166756.47 | AV10: 163864.31 | AW10: 156989.94 | AX10: 141333.53 | AY10: 163729.37 | AZ10: 72692.756 | BA10: 141890.18 | BB10: 166763.64 | BC10: 140776.39 | BD10: 158291.15 | BE10: 158390.17 | BF10: 163044.2 | BG10: 142443.49 | BH10: 146182.59 | BI10: 157518.56 | BJ10: 140019.54 | BK10: 166517.84 | BL10: 131663.27 | BM10: 152214.46 | BN10: 155615.77 | BO10: 164218.42 | BP10: 161240.68 | BQ10: 138942.54 | BR10: 147151.94 | BS10: 162509.61 | BT10: 131832.75 | BU10: 155954.71 | BV10: 145038.55 | BW10: 147593.83 | BX10: 162002.53 | BY10: 152006.62 | BZ10: 166872.62 | CA10: 171870.67 | CB10: 151428.18 | CC10: 160197.58 | CD10: 93004.612 | CE10: 161662.62 | CF10: 154973.45 | CG10: 141926.7 | CH10: 163937.21 | CI10: 168252.18 | CJ10: 138171.24 | CK10: 155469.15 | CL10: 166138.76 | CM10: 149153.99 | CN10: 167194.41 | CO10: 135116.25 | CP10: 144907.91 | CQ10: 152929.47 | CR10: 145074.99 | CS10: 164061.02 | CT10: 123171.92 | CU10: 142810.86 | CV10: 141209.09 | CW10: 108429.36
A11: 202210 | B11: 146927.65 | C11: 144374.91 | D11: 146122.36 | E11: 140252.96 | F11: 148496.03 | G11: 130383.73 | H11: 153960.47 | I11: 131825.71 | J11: 132525.66 | K11: 141039.54 | L11: 149685.14 | M11: 142420.4 | N11: 155429.73 | O11: 139154.4 | P11: 163199.52 | Q11: 146935.64 | R11: 129943.81 | S11: 155062.12 | T11: 144551.02 | U11: 130366.41 | V11: 135131.36 | W11: 141895.79 | X11: 140302.92 | Y11: 147860.56 | Z11: 153050.11 | AA11: 156895.28 | AB11: 154572.39 | AC11: 149601.04 | AD11: 157009.13 | AE11: 163197.97 | AF11: 141160.59 | AG11: 151871.67 | AH11: 140443.93 | AI11: 147614.98 | AJ11: 134246.36 | AK11: 125748.29 | AL11: 158018.78 | AM11: 130093.7 | AN11: 153557.76 | AO11: 160726.35 | AP11: 160085.79 | AQ11: 158216.21 | AR11: 146378.78 | AS11: 152460.89 | AT11: 158770.9 | AU11: 158459.8 | AV11: 156785.98 | AW11: 154184.73 | AX11: 137061.37 | AY11: 154915.4 | AZ11: 70075.318 | BA11: 133402.96 | BB11: 161041.99 | BC11: 135041.15 | BD11: 148033.19 | BE11: 157510.37 | BF11: 158676.08 | BG11: 136242.99 | BH11: 142710.36 | BI11: 148927.14 | BJ11: 136317.18 | BK11: 160966.44 | BL11: 122862.77 | BM11: 144988.09 | BN11: 150679.27 | BO11: 159800.8 | BP11: 154214.74 | BQ11: 125839.51 | BR11: 140672.18 | BS11: 153082.24 | BT11: 131799.96 | BU11: 147395.88 | BV11: 142820.07 | BW11: 144579.81 | BX11: 161332.4 | BY11: 144776.15 | BZ11: 161607.21 | CA11: 158407.12 | CB11: 142067.2 | CC11: 154707.16 | CD11: 88997.73 | CE11: 154435.19 | CF11: 146519.13 | CG11: 138046.39 | CH11: 159447.47 | CI11: 156991.75 | CJ11: 135033.98 | CK11: 147138.29 | CL11: 164483.86 | CM11: 139151.05 | CN11: 158887.66 | CO11: 135622.23 | CP11: 139684.98 | CQ11: 151902.61 | CR11: 144343.94 | CS11: 161526.25 | CT11: 124754.39 | CU11: 137568.22 | CV11: 135609.93 | CW11: 106127.18
A12: 202211 | B12: 134492.62 | C12: 133237.72 | D12: 144520.63 | E12: 133152.99 | F12: 139244.53 | G12: 122116.87 | H12: 145457.7 | I12: 122147.12 | J12: 127666.08 | K12: 134636.75 | L12: 127165.53 | M12: 131969.6 | N12: 146268.01 | O12: 132524.3 | P12: 155968.68 | Q12: 136491.02 | R12: 120955.98 | S12: 145330.35 | T12: 139456.79 | U12: 126784.91 | V12: 128815.58 | W12: 134491.63 | X12: 126320.26 | Y12: 137013.8 | Z12: 143662.46 | AA12: 152907.39 | AB12: 145812.24 | AC12: 138879.17 | AD12: 143457.68 | AE12: 147679.67 | AF12: 133814.98 | AG12: 144397.57 | AH12: 130918.45 | AI12: 138335.42 | AJ12: 126412.01 | AK12: 122545.22 | AL12: 145604.23 | AM12: 125367.53 | AN12: 148075.39 | AO12: 152171.55 | AP12: 149589.25 | AQ12: 147808.64 | AR12: 135340.33 | AS12: 148914.35 | AT12: 155505.72 | AU12: 146451.32 | AV12: 153453.46 | AW12: 141963.32 | AX12: 130713.41 | AY12: 148269.09 | AZ12: 65136.388 | BA12: 127369.28 | BB12: 155336.98 | BC12: 129869.13 | BD12: 147671.84 | BE12: 148343.3 | BF12: 147155.25 | BG12: 129410.3 | BH12: 134241.69 | BI12: 142949.24 | BJ12: 127349.74 | BK12: 151684.84 | BL12: 120604.58 | BM12: 138371.86 | BN12: 148926.13 | BO12: 146848.82 | BP12: 148797.54 | BQ12: 128264.39 | BR12: 130743.22 | BS12: 147135.14 | BT12: 119770.64 | BU12: 145279.67 | BV12: 137626.3 | BW12: 134802.8 | BX12: 148854.22 | BY12: 139513 | BZ12: 154857.57 | CA12: 155752.85 | CB12: 137021.97 | CC12: 143411.87 | CD12: 82630.242 | CE12: 145101.14 | CF12: 141971.33 | CG12: 132044.15 | CH12: 153886.5 | CI12: 152162.55 | CJ12: 133800.4 | CK12: 139113.79 | CL12: 150928.79 | CM12: 135235.18 | CN12: 146781.16 | CO12: 127490.61 | CP12: 135312.16 | CQ12: 141162.07 | CR12: 134332.38 | CS12: 148512.59 | CT12: 120312.49 | CU12: 131211.47 | CV12: 131516.51 | CW12: 99130.093
A13: 202212 | B13: 134256.85 | C13: 134449.84 | D13: 137850.55 | E13: 126147.92 | F13: 134321.23 | G13: 116482.64 | H13: 139677.31 | I13: 119150.81 | J13: 123022.37 | K13: 131231.08 | L13: 127020.06 | M13: 131254.8 | N13: 142023.28 | O13: 129874.72 | P13: 148693.98 | Q13: 131337.98 | R13: 117187.02 | S13: 139257.78 | T13: 134514.24 | U13: 122649.8 | V13: 128161.69 | W13: 130256 | X13: 123608.81 | Y13: 137172.79 | Z13: 144255.32 | AA13: 147496.53 | AB13: 140814.96 | AC13: 137145.07 | AD13: 142997.67 | AE13: 146078.05 | AF13: 134766.47 | AG13: 139886.44 | AH13: 127027.58 | AI13: 138100.85 | AJ13: 126780.31 | AK13: 121130.98 | AL13: 141326.21 | AM13: 121967.78 | AN13: 142705.2 | AO13: 146358.93 | AP13: 151798.02 | AQ13: 147025.22 | AR13: 133938.71 | AS13: 142390.37 | AT13: 145319.56 | AU13: 140831.53 | AV13: 147584.14 | AW13: 146400.02 | AX13: 125877.21 | AY13: 142219.91 | AZ13: 66093.496 | BA13: 123242.69 | BB13: 148324.29 | BC13: 132953.36 | BD13: 134636.77 | BE13: 140715.54 | BF13: 146655.28 | BG13: 125508.74 | BH13: 126482.4 | BI13: 137450.57 | BJ13: 125483.39 | BK13: 149241.13 | BL13: 116512.47 | BM13: 133911.21 | BN13: 139706.55 | BO13: 143871.31 | BP13: 141953.96 | BQ13: 122204.88 | BR13: 129904.2 | BS13: 143282.09 | BT13: 121182.24 | BU13: 139921.28 | BV13: 131118.76 | BW13: 131181.71 | BX13: 149356.02 | BY13: 137322.37 | BZ13: 147000.13 | CA13: 148546.91 | CB13: 131697.1 | CC13: 139501.59 | CD13: 83149.805 | CE13: 140653.99 | CF13: 140229.13 | CG13: 127376.24 | CH13: 143708.85 | CI13: 146040.56 | CJ13: 121008.74 | CK13: 134517.03 | CL13: 147629.26 | CM13: 128899.61 | CN13: 143971.99 | CO13: 120291.39 | CP13: 128295.05 | CQ13: 139254.19 | CR13: 131221.23 | CS13: 143747.45 | CT13: 102246.26 | CU13: 126672.58 | CV13: 126490.07 | CW13: 96648.467
... A37: 202412 | B37: 138093.01 | C37: 140081.37 | D37: 138940.49 | E37: 131109.38 | F37: 133270.01 | G37: 120469.36 | H37: 143338.52 | I37: 124594.29 | J37: 130586.2 | K37: 139531.74 | L37: 124071.59 | M37: 137574.27 | N37: 145292.83 | O37: 137998.2 | P37: 149152.68 | Q37: 137494.08 | R37: 124454.63 | S37: 138330.28 | T37: 138151.78 | U37: 128263.56 | V37: 130516.36 | W37: 138560.34 | X37: 125669.92 | Y37: 140874.19 | Z37: 145365.93 | AA37: 157396.03 | AB37: 149342.48 | AC37: 142650.91 | AD37: 150351.89 | AE37: 154212.48 | AF37: 136287.8 | AG37: 147770.96 | AH37: 133215.72 | AI37: 142159.21 | AJ37: 132498.6 | AK37: 122587.86 | AL37: 152386.62 | AM37: 128158.18 | AN37: 145550.71 | AO37: 155669.51 | AP37: 152547.29 | AQ37: 145731.23 | AR37: 137591.09 | AS37: 144466.83 | AT37: 150087.91 | AU37: 148044.62 | AV37: 147725.66 | AW37: 144527.11 | AX37: 129890.11 | AY37: 150244.84 | AZ37: 68576.236 | BA37: 129049.45 | BB37: 154356.42 | BC37: 132072.32 | BD37: 149330.09 | BE37: 148539.07 | BF37: 152194.95 | BG37: 133612.9 | BH37: 136951.51 | BI37: 142151.64 | BJ37: 130953.22 | BK37: 155318.96 | BL37: 116103.24 | BM37: 137855.41 | BN37: 148817.95 | BO37: 151266.07 | BP37: 146015.04 | BQ37: 125961.11 | BR37: 132324.81 | BS37: 148174.8 | BT37: 123697.42 | BU37: 141923.68 | BV37: 135667.34 | BW37: 137573.25 | BX37: 150486.5 | BY37: 141456.41 | BZ37: 153815.32 | CA37: 155507.09 | CB37: 137146.59 | CC37: 139170.06 | CD37: 83476.359 | CE37: 149236.29 | CF37: 142228.48 | CG37: 128721.78 | CH37: 151377.66 | CI37: 157994.44 | CJ37: 126373.8 | CK37: 142390.17 | CL37: 155350.03 | CM37: 131065.76 | CN37: 153485.91 | CO37: 128222.75 | CP37: 135362.01 | CQ37: 144553.33 | CR37: 138451.71 | CS37: 151567.64 | CT37: 114411.96 | CU37: 135733.59 | CV37: 134476.58 | CW37: 97529.149

Sheet zip_med_income
